Workbook
Name \A: #REF!
Name \A: #REF!
Name \A: #REF!
Name \A: #REF!
Name \A: #REF!
Name \A: #REF!
Name \A: #REF!
Name \A: #REF!
Name \A: #REF!
Name \A: #REF!
Name \A: #REF!
Name \A: #REF!
Name \A: #REF!
Name \G: #REF!
Name \G: #REF!
Name \G: #REF!
Name \G: #REF!
Name \G: #REF!
Name \G: #REF!
Name \G: #REF!
Name \G: #REF!
Name \G: #REF!
Name \G: #REF!
Name \G: #REF!
Name \G: #REF!
Name \X: #REF!
Name \X: #REF!
Name \X: #REF!
Name \X: #REF!
Name \X: #REF!
Name \X: #REF!
Name \X: #REF!
Name \X: #REF!
Name \X: #REF!
Name \X: #REF!
Name \X: #REF!
Name \X: #REF!
Name ___DAT1: #REF!
Name ___DAT1: #REF!
Name ___DAT1: #REF!
Name ___DAT1: #REF!
Name ___DAT1: #REF!
Name ___DAT1: #REF!
Name ___DAT1: #REF!
Name ___DAT1: #REF!
Name ___DAT1: #REF!
Name ___DAT1: #REF!
Name ___DAT1: #REF!
Name ___DAT1: #REF!
Name ___DAT10: #REF!
Name ___DAT10: #REF!
Name ___DAT10: #REF!
Name ___DAT10: #REF!
Name ___DAT10: #REF!
Name ___DAT10: #REF!
Name ___DAT10: #REF!
Name ___DAT10: #REF!
Name ___DAT10: #REF!
Name ___DAT10: #REF!
Name ___DAT10: #REF!

Sheet COVER PAGE
A1: LAGOS STATE INTERNAL REVENUE SERVICES
A4: TAX AUDIT REPORT
A6: NAME OF THE COMPANY:
A7: 3C HUB BRAND MANAGEMENT LIMITED
A10: PERIOD OF AUDIT:
A11: 2023&2024
A14: PREPARED BY
A15: PETABIZ NIGERIA LIMITED

Sheet Status
A4: AUDIT REPORT
A10: STATUS REPORT ON 3C HUB BRAND MANAGEMENT LIMITED
A13: THE COMPANY
A14: 3C HUB BRAND MANAGEMENT LIMITED was incorporated under COMPANIES AND ALLIED MATTERS
A15: ACT 2004 as a Limited Company on the 5TH June 2014 with RC number 1195308
A16: The company is into Trading
A19: STAFF
A20: The Company engaged the services of 217 Local staff and 5 expatriate staff in the 2021 year audit.
A23: PAYE
A24: There were evidence of PAYE deducted from the company's staff emolument and remittances were made.
A25: The evidence of remittances were included in the report of the company.
A28: WITHHOLDING TAX
... A38: There was evidence of payment in this regard.

Sheet CONTENT
A2: Table of Contents | H2: Page
A4: Company Profile | H4: 1
A6: Audit Check List | H6: 2
A8: Staff Cost Analysis | H8: 3
A10: Payroll Cost Analysis | H10: 4
A12: Analysis of Director's Emoluments | H12: 5
A14: Analysis of Payroll Cost - Expatriate | H14: 6
A16: Analysis of Operating Expenses | H16: 7
A18: Schedule of Withholding Tax | H18: 8
A20: Schedule of List of Tax Payers | H20: 9
A22: Summary of Tax Remittances Receipts PAYE | H22: 10
A24: Schedule of Withholding Tax Remittances | H24: 11
A26: Business/Office Location of Tax Payer | H26: 12
A28: Development Levy | H28: 13
A30: Hotel Occupancy & Restaurant Consumption Check List | H30: 14
A32: Hotel Occupancy & Restaurant Consumption | H32: 15

Sheet FIELD REPORT FORM
A1: COMPANY PROFILE
A6: 1 | B6: NAME OF COMPANY: | H6: 3C HUB BRAND MANAGEMENT LIMITED
A9: 2 | B9: YEAR OF INCORPORATION: | H9: 5TH JUNE 2014
A12: 3a | B12: PRESENT ADDRESS AND LOCATION: | H12: 20, OBAFEMI AWOLOWA WAY, IKEJA, LAGOS
A14: 3b | B14: CORPORATE E-MAIL ADDRESS: | H14: finance.3cng@yiwill.com
A17: 4 | B17: NATURE OF BUSINESS: | H17: TRADING
A20: 5a | B20: PHONE NO OF THE MD/THE ACCOUNTANT: | H20: 08142121843
A22: 5b | B22: CONTACT's E-MAIL ADDRESS:
A25: 6 | B25: RC NO: | H25: 1195308'
A28: 7 | B28: AGENCY REF: | H28: LA/IRS/TA/C14326/FS033/NA/38428//05/25
A31: 8 | B31: SECTOR: | H31: TRADING
A34: 9 | B34: YEAR END: | H34: 31ST DECEMBER
A37: 10 | B37: PERIOD OF AUDIT: | J37: 2023&2024
A40: 11 | B40: NAME & SIGN OF TAMA: | H40: PETABIZ NIGERIA LIMITED
H42: JUNAID-OWOKORODU KAFILAT
A43: 12 | B43: NAME & SIGN OF BIR STAFF: | H43: SOYOMBO ANTHONY ADEYEMI
H44: AKINRINOLA ADEKEMI OLUSEUN

Sheet Audit Check List
C4: STATUTORY TAX AUDIT - BASIC INFORMATION CHECKLIST | J4: RC NO : 1195308
C5: COMPANY NAME : 3C HUB BRAND MANAGEMENT | J5: TAX STATION REGISTERED:
C6: ADDRESS : 20, OBAFEMI AWOLOWA WAY, IKEJA, LAGOS
C7: YEARS OF ASSESSMENT : 2023&2024 | J7: AUDIT TEAM LEADER:MRS JUNAID-OWOKORODU KAFILAT
C8: DATE OF AUDIT : 18/07/2025
J9: TAMA: PETABIZ NIGERIA LIMITED
D10: 2023&2024 | E10: 2014 | F10: 2013 | G10: 2012 | H10: 2011 | I10: 2010 | J10: REMARKS
B11: 1 | C11: General Information
C12: Certificate of Incorporation
C13: CAC Form 2 & 7
C14: Audited Financial Statement
C15: Management Account
C16: Trial Balance/General Ledger
C17: Evidence of Business Premises Paid
C18: List of Branches in Nigeria
C19: List of Location/Offices in Lagos
C20: Evidence of Previous Year Audit
B23: 2 | C23: PAYE
C24: Staff Monthly Payroll
C25: Schedule Upront/Quarterly Payments
C26: Schedule Non-payroll payments to Staff
C27: Schedule of Benefits-in-kind to staff
C28: Staff Salary Schedule to Bank
C29: Employer Annual Declaration Form (H1)
C30: Sample of Employment Letters
C31: Scheme of Pension Remittance
C32: Evidence of PAYE Remittance
C33: Evidence of Development Levy Paid
B36: 3 | C36: Directors & Senior Management Staff
C37: Directors Emolument/Senior Management Staff Payroll
C38: Direct/Self Assessment
C39: Contract of Employment/Contract Agreement
C40: Schedule of Benefits-in-kind (Perquisites)
C41: Scheme of Pension Remittance
C42: Evidence of PAYE Remittance
C43: Evidence of Development Levy Paid
C44: Evidence of Life Assurance Policy
C45: Evidence of Gratuities
C46: Evidence of NHIS
C47: Evidence of NHF
B50: 4 | C50: Expatriate
C51: Expatriate Payroll
C52: Expatriate Contract/Terms of Employment
C53: Employers' Annual Declaration Form Filed For Expatriates
C54: Company's Expatriate Quota Grant/Permit
C55: Monthly Expatriate Returns to Immigration
C56: Registration/Renewal of CERPAC
C57: Schedule of Benefits-in-kind
C58: Rent Agreement for Expatriate Residence
C59: Evidence of Salary Paid in Nigeria and Abroad
C60: Scheme of Pension Remittance
C61: Evidence of PAYE Remittance
C62: Evidence of Development Levy Paid
B65: 5 | C65: Withholding Tax
C66: List of Vendors/Suppliers
C67: Schedule of WHT payment to Vendors/Suppliers
C68: Schedule of Dividend Paid to Shareholders
C69: Schedule of Interest Paid to Customers/Depositors
C70: Schedule of Commission Paid to Agents/Marketers
C71: Copy of Office Rent Agreements
C72: Evidence of WHT remittance

Sheet Staff Cost Analysis
B2: Analysis of Employee Benefit/Staff Cost
C4: 2023&2024
C5: Naira
B6: Total Staff Cost As Par Audited Financial Statement
B8: Total as par Audited Financial Statement
B9: Number Staff
B10: Employee Salaries & Wages
B11: Pension Contribution
B12: Other employee benefits
B15: Resident in Lagos
B16: Number Staff
B17: Employee Salaries & Wages
B18: Pension Contribution
B19: Other employee benefits

Sheet Payroll Cost Analysis 2023
D2: Analysis of Payroll Cost - Nigerian Staff | H2: 2023
B4: S/N | C4: Employees Details | K4: Payroll Items | V4: Deductions
C5: Staff Number | D5: Last Name | E5: First Name | F5: Other Name | G5: Designation | H5: ABC - ID | I5: Location | J5: No. of Month | K5: Basic | L5: Pensionable Income | O5: Non Pensionable Income | T5: One-Off Allowances | U5: Total Pay | V5: Pensions | W5: NHIS | X5: Gratuity | Y5: NHF | Z5: Life Assurance Premium
L6: Housing | M6: Transport | N6: BHT | O6: Utility | P6: Dressing | Q6: Lunch | R6: Leave | S6: Others
B7: 1 | N7: =K7+L7+M7 -> 0 | V7: =8%*N7 -> 0 | W7: =5%*N7 -> 0 | Y7: =2.5%*N7 -> 0
N8: =K8+L8+M8 -> 0 | V8: =8%*N8 -> 0 | W8: =5%*N8 -> 0 | Y8: =2.5%*N8 -> 0
N9: =K9+L9+M9 -> 0 | V9: =8%*N9 -> 0 | W9: =5%*N9 -> 0 | Y9: =2.5%*N9 -> 0
N10: =K10+L10+M10 -> 0 | V10: =8%*N10 -> 0 | W10: =5%*N10 -> 0 | Y10: =2.5%*N10 -> 0
N11: =K11+L11+M11 -> 0 | V11: =8%*N11 -> 0 | W11: =5%*N11 -> 0 | Y11: =2.5%*N11 -> 0
N12: =K12+L12+M12 -> 0 | V12: =8%*N12 -> 0 | W12: =5%*N12 -> 0 | Y12: =2.5%*N12 -> 0
N13: =K13+L13+M13 -> 0 | V13: =8%*N13 -> 0 | W13: =5%*N13 -> 0 | Y13: =2.5%*N13 -> 0
N14: =K14+L14+M14 -> 0 | V14: =8%*N14 -> 0 | W14: =5%*N14 -> 0 | Y14: =2.5%*N14 -> 0
N15: =K15+L15+M15 -> 0 | V15: =8%*N15 -> 0 | W15: =5%*N15 -> 0 | Y15: =2.5%*N15 -> 0
N16: =K16+L16+M16 -> 0 | V16: =8%*N16 -> 0 | W16: =5%*N16 -> 0 | Y16: =2.5%*N16 -> 0
N17: =K17+L17+M17 -> 0 | V17: =8%*N17 -> 0 | W17: =5%*N17 -> 0 | Y17: =2.5%*N17 -> 0
N18: =K18+L18+M18 -> 0 | V18: =8%*N18 -> 0 | W18: =5%*N18 -> 0 | Y18: =2.5%*N18 -> 0
N19: =K19+L19+M19 -> 0 | V19: =8%*N19 -> 0 | W19: =5%*N19 -> 0 | Y19: =2.5%*N19 -> 0
... N110: =K110+L110+M110 -> 0 | V110: =8%*N110 -> 0 | W110: =5%*N110 -> 0 | Y110: =2.5%*N110 -> 0

Sheet Payroll Cost Analysis 2024
D2: Analysis of Payroll Cost - Nigerian Staff | H2: 2024
B4: S/N | C4: Employees Details | K4: Payroll Items | V4: Deductions
C5: Staff Number | D5: Last Name | E5: First Name | F5: Other Name | G5: Designation | H5: ABC - ID | I5: Location | J5: No. of Month | K5: Basic | L5: Pensionable Income | O5: Non Pensionable Income | T5: One-Off Allowances | U5: Total Pay | V5: Pensions | W5: NHIS | X5: Gratuity | Y5: NHF | Z5: Life Assurance Premium
L6: Housing | M6: Transport | N6: BHT | O6: Utility | P6: Dressing | Q6: Lunch | R6: Leave | S6: Others
B7: 1 | N7: =K7+L7+M7 -> 0 | V7: =8%*N7 -> 0 | W7: =5%*N7 -> 0 | Y7: =2.5%*N7 -> 0
N8: =K8+L8+M8 -> 0 | V8: =8%*N8 -> 0 | W8: =5%*N8 -> 0 | Y8: =2.5%*N8 -> 0
N9: =K9+L9+M9 -> 0 | V9: =8%*N9 -> 0 | W9: =5%*N9 -> 0 | Y9: =2.5%*N9 -> 0
N10: =K10+L10+M10 -> 0 | V10: =8%*N10 -> 0 | W10: =5%*N10 -> 0 | Y10: =2.5%*N10 -> 0
N11: =K11+L11+M11 -> 0 | V11: =8%*N11 -> 0 | W11: =5%*N11 -> 0 | Y11: =2.5%*N11 -> 0
N12: =K12+L12+M12 -> 0 | V12: =8%*N12 -> 0 | W12: =5%*N12 -> 0 | Y12: =2.5%*N12 -> 0
N13: =K13+L13+M13 -> 0 | V13: =8%*N13 -> 0 | W13: =5%*N13 -> 0 | Y13: =2.5%*N13 -> 0
N14: =K14+L14+M14 -> 0 | V14: =8%*N14 -> 0 | W14: =5%*N14 -> 0 | Y14: =2.5%*N14 -> 0
N15: =K15+L15+M15 -> 0 | V15: =8%*N15 -> 0 | W15: =5%*N15 -> 0 | Y15: =2.5%*N15 -> 0
N16: =K16+L16+M16 -> 0 | V16: =8%*N16 -> 0 | W16: =5%*N16 -> 0 | Y16: =2.5%*N16 -> 0
N17: =K17+L17+M17 -> 0 | V17: =8%*N17 -> 0 | W17: =5%*N17 -> 0 | Y17: =2.5%*N17 -> 0
N18: =K18+L18+M18 -> 0 | V18: =8%*N18 -> 0 | W18: =5%*N18 -> 0 | Y18: =2.5%*N18 -> 0
N19: =K19+L19+M19 -> 0 | V19: =8%*N19 -> 0 | W19: =5%*N19 -> 0 | Y19: =2.5%*N19 -> 0
... N110: =K110+L110+M110 -> 0 | V110: =8%*N110 -> 0 | W110: =5%*N110 -> 0 | Y110: =2.5%*N110 -> 0

Sheet Expatriate 2023
C2: Analysis of Payroll Cost - Expatriate | G2: 2023
A4: S/N | B4: Employees Details | K4: Payroll Items | U4: Benefits -in-kind | X4: Deductions
B5: Staff Number | C5: Last Name | D5: First Name | E5: Other Name | F5: Designation | G5: ABC - ID | H5: Location | I5: Nationality | J5: No. of Month | K5: Basic | L5: Pensionable Income | N5: Non Pensionable Income | S5: One-Off Allowances | T5: Total Pay | U5: Motor Vehicles | V5: House/Rent | W5: Other Benefits | X5: Pensions | Y5: Life Assurance | Z5: Others*
L6: Housing | M6: Transport | N6: Utility | O6: Dressing | P6: Lunch | Q6: Leave | R6: Others
Y18: * Please Specify

Sheet Expatriate 2024
C2: Analysis of Payroll Cost - Expatriate | G2: 2024
A4: S/N | B4: Employees Details | K4: Payroll Items | U4: Benefits -in-kind | X4: Deductions
B5: Staff Number | C5: Last Name | D5: First Name | E5: Other Name | F5: Designation | G5: ABC - ID | H5: Location | I5: Nationality | J5: No. of Month | K5: Basic | L5: Pensionable Income | N5: Non Pensionable Income | S5: One-Off Allowances | T5: Total Pay | U5: Motor Vehicles | V5: House/Rent | W5: Other Benefits | X5: Pensions | Y5: Life Assurance | Z5: Others*
L6: Housing | M6: Transport | N6: Utility | O6: Dressing | P6: Lunch | Q6: Leave | R6: Others
Y18: * Please Specify

Sheet WHT Schedule 2023
D2: Schedule of WHT - Payment to Individuals/Enterprises/Business Name in Lagos
C3: Transaction | E3: Payment | F3: Nature of | G3: Transaction | I3: WITHHOLDING
B4: S/N | C4: Date | D4: Names of Companies/Beneficiaries | E4: Voucher No | F4: Transaction | G4: Amount | I4: AMOUNT
B5: 1
B6: 2
B7: 3
B8: 4
B9: 5
B10: 6
B11: 7
B12: 8
B13: 9
B14: 10
B15: 11
B16: 12
... B37: 33

Sheet WHT Schedule 2024
D2: Schedule of WHT - Payment to Individuals/Enterprises/Business Name in Lagos
C3: Transaction | E3: Payment | F3: Nature of | G3: Transaction | I3: WITHHOLDING
B4: S/N | C4: Date | D4: Names of Companies/Beneficiaries | E4: Voucher No | F4: Transaction | G4: Amount | I4: AMOUNT
B5: 1
B6: 2
B7: 3
B8: 4
B9: 5
B10: 6
B11: 7
B12: 8
B13: 9
B14: 10
B15: 11
B16: 12
... B37: 33

Sheet WHT SMRY 2023
A1: LAGOS STATE GOVERNMENT
A2: NAME:
A3: WHT SUMMARY SHEET
A4: JAN-DEC : | B4: 2023
A5: Registration No ( RC ):
A6: Date of Registration:
A7: Nature of Business:
E9: 2023
C10: GROSS | D10: RATE | E10: WHT DUE
C11: N | D11: % | E11: N
B13: CONTRACT / SUPPLY | C13: 0 | D13: 0.05 | E13: =C13*0.05 -> 0
B15: LEGAL / PROF. FEES | C15: 0 | D15: 0.05 | E15: =C15*0.05 -> 0
B17: SERVICE | C17: 0 | D17: 0.05 | E17: =C17*0.05 -> 0
B19: AUDIT FEES | C19: 0 | D19: 0.05 | E19: =C19*0.05 -> 0
B21: CONSULTANCY FEE | C21: 0 | D21: 0.05 | E21: =C21*D21 -> 0
B23: DIVIDENDS | C23: 0 | D23: 0.1 | E23: =C23*0.1 -> 0
B25: DIRECTORS FEES | C25: 0 | D25: 0.1 | E25: =C25*0.1 -> 0
B27: RENT | C27: 0 | D27: 0.1 | E27: =C27*0.1 -> 0
B29: COMMISSION | C29: 0 | D29: 0.1 | E29: =C29*0.1 -> 0
C31: =SUM(C13:C30) -> 0 | E31: =SUM(E13:E30) -> 0

Sheet WHT SMRY 2024
A1: LAGOS STATE GOVERNMENT
A2: NAME:
A3: WHT SUMMARY SHEET
A4: JAN-DEC : | B4: 2024
A5: Registration No ( RC ):
A6: Date of Registration:
A7: Nature of Business:
E9: 2024 | I9: 2023
C10: GROSS | D10: RATE | E10: WHT DUE | G10: GROSS | H10: RATE | I10: WHT DUE
C11: N | D11: % | E11: N | G11: N | H11: % | I11: N
B13: CONTRACT / SUPPLY | C13: 0 | D13: 0.05 | E13: =C13*0.05 -> 0 | G13: 0 | H13: 0.05 | I13: =G13*0.05 -> 0
B15: LEGAL / PROF. FEES | C15: 0 | D15: 0.05 | E15: =C15*0.05 -> 0 | G15: 1000000 | H15: 0.05 | I15: =G15*0.05 -> 50000
B17: SERVICE | C17: 0 | D17: 0.05 | E17: =C17*0.05 -> 0 | G17: 0 | H17: 0.05 | I17: =G17*0.05 -> 0
B19: AUDIT FEES | C19: 3000000 | D19: 0.05 | E19: =C19*0.05 -> 150000 | G19: 2000000 | H19: 0.05 | I19: =G19*0.05 -> 100000
B21: CONSULTANCY FEE | C21: 0 | D21: 0.05 | E21: =C21*D21 -> 0 | G21: 0 | H21: 0.05 | I21: =G21*H21 -> 0
B23: DIVIDENDS | C23: 0 | D23: 0.1 | E23: =C23*0.1 -> 0 | G23: 0 | H23: 0.1 | I23: =G23*0.1 -> 0
B25: DIRECTORS FEES | C25: 0 | D25: 0.1 | E25: =C25*0.1 -> 0 | G25: 0 | H25: 0.1 | I25: =G25*0.1 -> 0
B27: RENT | C27: =E27*10 -> 11200000 | D27: 0.1 | E27: =+'WHT Remittance 2024'!C13 -> 1120000 | G27: =I27*10 -> 22500000 | H27: 0.1 | I27: =+'WHT Remittance 2023'!C12 -> 2250000
B29: COMMISSION | C29: 0 | D29: 0.1 | E29: =C29*0.1 -> 0 | G29: 0 | H29: 0.1 | I29: =G29*0.1 -> 0
C31: =SUM(C13:C30) -> 14200000 | E31: =SUM(E13:E30) -> 1270000 | G31: =SUM(G13:G30) -> 25500000 | I31: =SUM(I13:I30) -> 2400000

Sheet  PAYE Remittances 2023
C3: SUMMARY OF TAX REMITTANCE RECEIPT 2023 PAYE
B5: S/N | C5: Receipt No | D5: Amount | E5: Period Covered | F5: Date of Payment | G5: Bank
B6: 1 | C6: 51239606/TNMGNVUP | D6: 580200 | E6: JANUARY | F6: 22/03/2023 | G6: FCMB
B7: 2 | C7: 51239599/NRHPNMWI | D7: 585800 | E7: FEBRUARY | F7: 22/03/2023 | G7: FCMB
B8: 3 | C8: 51720496/XJYHLULI | D8: 587400 | E8: MARCH | F8: 18/03/2023 | G8: ACCESS
B9: 4 | C9: 51720513/ANLATDFZ | D9: 572300 | E9: APRIL | F9: 18/03/2023 | G9: ACCESS
B10: 5 | C10: 51941341/MVWHPLHW | D10: 577100 | E10: MAY | F10: 45175 | G10: ACCESS
B11: 6 | C11: 52216957/JUKYUZUR | D11: 574500 | E11: JUNE | F11: 45206 | G11: ACCESS
B12: 7 | C12: 52521244/ZDKBGECC | D12: 577400 | E12: JULY | F12: 45238 | G12: ACCESS
B13: 8 | C13: 52769775/CRIXGYDV | D13: 581500 | E13: AUGUST | F13: 45086 | G13: ACCESS
B14: 9 | C14: 53106832/KEPNJGDD | D14: 569500 | E14: SEPTEMBER | F14: 45056 | G14: ACCESS
B15: 10 | C15: 53433029/RZNAWYNZ | D15: 563593 | E15: OCTOBER | F15: 44996 | G15: ACCESS
B16: 11 | C16: 53819864/QJWRMQDS | D16: 562902 | E16: NOVEMBER | F16: 45272 | G16: ACCESS
B17: 12 | C17: 54023592/JAEJRYRT | D17: 562902 | E17: DECEMBER | F17: 45505 | G17: ACCESS
D18: 6895097

Sheet PAYE Remittances 2024
C3: SUMMARY OF TAX REMITTANCE RECEIPT 2024 PAYE
B5: S/N | C5: Receipt No | D5: Amount | E5: Period Covered | F5: Date of Payment | G5: Bank
B6: 1 | C6: 54409365/YKZAJTJN | D6: 545253.33 | E6: JANUARY | F6: 15/02/2024 | G6: ACCESS
B7: 2 | C7: 54725500/AYSWDGBU | D7: 545253.35 | E7: FEBRUARY | F7: 21/03/2024 | G7: ACCESS
B8: 3 | C8: 54947689/USELDNTH | D8: 546102.66 | E8: MARCH | F8: 18/04/2024 | G8: ACCESS
B9: 4 | C9: 55304724/ktlpdqii | D9: 170222 | E9: APRIL | F9: 24/05/2024 | G9: ACCESS
B10: 5 | C10: 55567069/AGMGFMUR | D10: 170300 | E10: MAY | F10: 26/06/2024 | G10: ACCESS
B11: 6 | C11: 55886106/ZANJHMKW | D11: 171071 | E11: JUNE | F11: 31/07/2024 | G11: ACCESS
B12: 7 | C12: 56037877/GYCFMTHE | D12: 170000 | E12: JULY | F12: 30/08/2024 | G12: ACCESS
B13: 8 | C13: 56151305/TAKKZCQP | D13: 166863 | E13: AUGUST | F13: 20/09/2024 | G13: ACCESS
B14: 9 | C14: 56593668/DPTVPGYG | D14: 159108 | E14: SEPTEMBER | F14: 22/10/2024 | G14: ACCESS
B15: 10 | C15: 56894697/ATFALKRE | D15: 159677 | E15: OCTOBER | F15: 25/11/2024 | G15: ACCESS
B16: 11 | C16: 57374232/DLFRLXMD | D16: 154630 | E16: NOVEMBER | F16: 45809 | G16: ACCESS
B17: 12 | C17: 57374082/DXTKHMGP | D17: 154630 | E17: DECEMBER | F17: 45809 | G17: ACCESS
D19: =SUM(D6:D18) -> 3113110.3

Sheet  Direct Assessment 2023&2024
C3: SUMMARY OF TAX REMITTANCE RECEIPT DIRECT ASSESSMENT 2023
B5: S/N | C5: Receipt No | D5: Amount | E5: Period Covered | F5: Date of Payment | G5: Bank
B6: 1 | C6: 55787462/DRPSPEWA | D6: 245980 | E6: JANUARY | F6: 19/07/2024 | G6: ZENITH
E7: FEBRUARY
E8: MARCH
C11: SUMMARY OF TAX REMITTANCE RECEIPT DIRECT ASSESSMENT 2024
B13: S/N | C13: Receipt No | D13: Amount | E13: Period Covered | F13: Date of Payment | G13: Bank
B14: 1 | C14: 58360132/CEQCZLDV | D14: 280000 | E14: JANUARY | F14: 30/04/2025 | G14: ZENITH
E15: FEBRUARY
E16: MARCH

Sheet WHT Remittance 2023
B2: SCHEDULE OF WITHHOLDING TAX REMITTANCES
B4: S/N | C4: Amount Paid | D4: Period Covered | E4: Date of Payment | F4: Receipt No | G4: Nature of Transaction | H4: Bank
B5: 1 | C5: 150000 | D5: JANUARY | E5: 18/01/2024 | F5: 54095484/DPFVLCSA | G5: RENT | H5: ACCESS
B6: 2 | C6: 800000 | D6: FEBRUARY | E6: 18/01/2024 | F6: 54095437/CYYZHVGS | G6: RENT | H6: ACCESS
B7: 3 | C7: 300000 | D7: MARCH | E7: 18/01/2024 | F7: 5409543/VRBJIRSE | G7: RENT | H7: ACCESS
B8: 4 | C8: 250000 | D8: APRIL | E8: 18/01/2024 | F8: 54095452/UVKVHHVE | G8: RENT | H8: ACCESS
B9: 5 | C9: 300000 | D9: MAY | E9: 18/01/2024 | F9: 54095465/GXTSGMJB | G9: RENT | H9: ACCESS
B10: 6 | C10: 300000 | D10: JUNE | E10: 18/01/2024 | F10: 54095490/FSVKKYTF | G10: RENT | H10: ACCESS
B11: 7 | C11: 150000 | D11: JULY | E11: 18/01/2024 | F11: 54095484/DPFVLCSA | G11: RENT | H11: ACCESS
C12: 2250000

Sheet WHT Remittance 2024
B2: SCHEDULE OF WITHHOLDING TAX REMITTANCES
B4: S/N | C4: Amount Paid | D4: Period Covered | E4: Date of Payment | F4: Receipt No | G4: Nature of Transaction | H4: Bank
B5: 1 | C5: 140000 | D5: JANUARY | E5: 16/01/2025 | F5: 57457377/WRFJFADY | G5: RENT | H5: ACCESS
B6: 2 | C6: 90000 | D6: FEBRUARY | E6: 16/01/2025 | F6: 57457850/BRFVLEJQ | G6: RENT | H6: ACCESS
B7: 3 | C7: 250000 | D7: MARCH | E7: 16/01/2025 | F7: 57457863/VKLPYIXN | G7: RENT | H7: ACCESS
B8: 4 | C8: 150000 | D8: APRIL | E8: 16/01/2025 | F8: 57458222/UZGXZPCK | G8: RENT | H8: ACCESS
B9: 5 | C9: 300000 | D9: MAY | E9: 16/01/2025 | F9: 57458218/NYBPWCA | G9: RENT | H9: ACCESS
B10: 6 | C10: 100000 | D10: JUNE | E10: 16/01/2025 | F10: 57457832/UWTNFLPA | G10: RENT | H10: ACCESS
B11: 7 | C11: 90000 | D11: JULY | E11: 16/01/2025 | F11: 57457370/DRPYJLXH | G11: RENT | H11: ACCESS
C13: =SUM(C5:C12) -> 1120000

Sheet Biz Premises 2023
C6: BUSINESS/OFFICE LOCATIONS OF TAX PAYER IN LAGOS
B9: S/N | C9: Office/Location Address | D9: Amount Due | E9: Amount Paid | F9: Period Covered | G9: Receipt NO
B10: 1 | C10: 20, OBAFEMI AWOLOWA WAY, IKEJA, LAGOS | D10: 5000 | E10: 5000 | F10: 2023 | G10: 54091900/VCPBKLDM

Sheet Biz Premises 2024
C6: BUSINESS/OFFICE LOCATIONS OF TAX PAYER IN LAGOS
B9: S/N | C9: Office/Location Address | D9: Amount Due | E9: Amount Paid | F9: Period Covered | G9: Receipt NO
B10: 1 | C10: 20, OBAFEMI AWOLOWA WAY, IKEJA, LAGOS | D10: 5000 | E10: 5000 | F10: 2024 | G10: 57512568/GYNHYVYI

Sheet Development Levy 2023
B3: Schedule of Development Levy Remittances LOCAL 2023
A6: S/N | B6: Amount Due | C6: Amount Paid | D6: Period Covered | E6: Date of Payment | F6: Receipt NO
A7: 1 | C7: 14000 | D7: 2023 | E7: 45505 | F7: 54023607/LAEGGADY
B15: Schedule of Development Levy Remittances EXPATRAITE 2023
A18: S/N | B18: Amount Due | C18: Amount Paid | D18: Period Covered | E18: Date of Payment | F18: Receipt NO
A19: 1 | D19: 2023

Sheet Development Levy 2024
B3: Schedule of Development Levy Remittances LOCAL 2024
A6: S/N | B6: Amount Due | C6: Amount Paid | D6: Period Covered | E6: Date of Payment | F6: Receipt NO
A7: 1 | C7: 10700 | D7: 2024 | E7: 21/01/2025 | F7: 57506423/SYVKXDFH
B14: Schedule of Development Levy Remittances EXPATRAITE 2024
A17: S/N | B17: Amount Due | C17: Amount Paid | D17: Period Covered | E17: Date of Payment | F17: Receipt NO
A18: 1 | B18: 500 | C18: 500 | D18: 2024 | E18: 21/01/2025 | F18: 57506990/WVNHMFVR

Sheet computation (local) 2021
A7: S/N | B7: NAME | C7: DESIGNATION | D7: ANNUAL TOTAL GROSS INCOME + BIK | E7: PENSION | F7: NET INCOME | G7: CRA | H7: TAXABLE INCOME | I7: ANNUAL TAX | J7: MONTHLY TAX | K7: MNTH | L7: PRO BY MNTH
A8: 1 | E8: =D8*0.08 -> 0 | F8: =D8-E8 -> 0 | G8: =IF(F8<=300000,0,IF(F8>=20000000,(F8*0.21),(F8*0.2)+200000)) -> 0 | H8: =+D8-G8-E8 -> 0 | I8: =IF(G8=0,(D8*0.01),IF(H8<=0,0.01*D8,IF(AND(H8>0,H8<=300000),H8*7%,IF(AND(H8>=300000,H8<600000),21000+(H8-300000)*11%,IF(AND(H8>=600000,H8<1100000),54000+(H8-600000)*15%,IF(AND(H8>=1100000,H8<1600000),129000+(H8-1100000)*19%,IF(AND(H8>=1600000,H8<3200000),224000+(H8-1600000)*21%,560000+(H8-3200000)*24%))))))) -> 0 | J8: =I8/12 -> 0 | K8: 12 | L8: =+J8*K8 -> 0
A9: 2 | D9: 0 | E9: =D9*0.08 -> 0 | F9: =D9-E9 -> 0 | G9: =IF(F9<=300000,0,IF(F9>=20000000,(F9*0.21),(F9*0.2)+200000)) -> 0 | H9: =+D9-G9-E9 -> 0 | I9: =IF(G9=0,(D9*0.01),IF(H9<=0,0.01*D9,IF(AND(H9>0,H9<=300000),H9*7%,IF(AND(H9>=300000,H9<600000),21000+(H9-300000)*11%,IF(AND(H9>=600000,H9<1100000),54000+(H9-600000)*15%,IF(AND(H9>=1100000,H9<1600000),129000+(H9-1100000)*19%,IF(AND(H9>=1600000,H9<3200000),224000+(H9-1600000)*21%,560000+(H9-3200000)*24%))))))) -> 0 | J9: =I9/12 -> 0 | K9: 0 | L9: =+J9*K9 -> 0
A10: 3 | D10: 0 | E10: =D10*0.08 -> 0 | F10: =D10-E10 -> 0 | G10: =IF(F10<=300000,0,IF(F10>=20000000,(F10*0.21),(F10*0.2)+200000)) -> 0 | H10: =+D10-G10-E10 -> 0 | I10: =IF(G10=0,(D10*0.01),IF(H10<=0,0.01*D10,IF(AND(H10>0,H10<=300000),H10*7%,IF(AND(H10>=300000,H10<600000),21000+(H10-300000)*11%,IF(AND(H10>=600000,H10<1100000),54000+(H10-600000)*15%,IF(AND(H10>=1100000,H10<1600000),129000+(H10-1100000)*19%,IF(AND(H10>=1600000,H10<3200000),224000+(H10-1600000)*21%,560000+(H10-3200000)*24%))))))) -> 0 | J10: =I10/12 -> 0 | K10: 0 | L10: =+J10*K10 -> 0
A11: 4 | D11: 0 | E11: =D11*0.08 -> 0 | F11: =D11-E11 -> 0 | G11: =IF(F11<=300000,0,IF(F11>=20000000,(F11*0.21),(F11*0.2)+200000)) -> 0 | H11: =+D11-G11-E11 -> 0 | I11: =IF(G11=0,(D11*0.01),IF(H11<=0,0.01*D11,IF(AND(H11>0,H11<=300000),H11*7%,IF(AND(H11>=300000,H11<600000),21000+(H11-300000)*11%,IF(AND(H11>=600000,H11<1100000),54000+(H11-600000)*15%,IF(AND(H11>=1100000,H11<1600000),129000+(H11-1100000)*19%,IF(AND(H11>=1600000,H11<3200000),224000+(H11-1600000)*21%,560000+(H11-3200000)*24%))))))) -> 0 | J11: =I11/12 -> 0 | K11: 0 | L11: =+J11*K11 -> 0
A12: 5 | D12: 0 | E12: =D12*0.08 -> 0 | F12: =D12-E12 -> 0 | G12: =IF(F12<=300000,0,IF(F12>=20000000,(F12*0.21),(F12*0.2)+200000)) -> 0 | H12: =+D12-G12-E12 -> 0 | I12: =IF(G12=0,(D12*0.01),IF(H12<=0,0.01*D12,IF(AND(H12>0,H12<=300000),H12*7%,IF(AND(H12>=300000,H12<600000),21000+(H12-300000)*11%,IF(AND(H12>=600000,H12<1100000),54000+(H12-600000)*15%,IF(AND(H12>=1100000,H12<1600000),129000+(H12-1100000)*19%,IF(AND(H12>=1600000,H12<3200000),224000+(H12-1600000)*21%,560000+(H12-3200000)*24%))))))) -> 0 | J12: =I12/12 -> 0 | K12: 0 | L12: =+J12*K12 -> 0
A13: 6 | D13: 0 | E13: =D13*0.08 -> 0 | F13: =D13-E13 -> 0 | G13: =IF(F13<=300000,0,IF(F13>=20000000,(F13*0.21),(F13*0.2)+200000)) -> 0 | H13: =+D13-G13-E13 -> 0 | I13: =IF(G13=0,(D13*0.01),IF(H13<=0,0.01*D13,IF(AND(H13>0,H13<=300000),H13*7%,IF(AND(H13>=300000,H13<600000),21000+(H13-300000)*11%,IF(AND(H13>=600000,H13<1100000),54000+(H13-600000)*15%,IF(AND(H13>=1100000,H13<1600000),129000+(H13-1100000)*19%,IF(AND(H13>=1600000,H13<3200000),224000+(H13-1600000)*21%,560000+(H13-3200000)*24%))))))) -> 0 | J13: =I13/12 -> 0 | K13: 0 | L13: =+J13*K13 -> 0
A14: 7 | D14: 0 | E14: =D14*0.08 -> 0 | F14: =D14-E14 -> 0 | G14: =IF(F14<=300000,0,IF(F14>=20000000,(F14*0.21),(F14*0.2)+200000)) -> 0 | H14: =+D14-G14-E14 -> 0 | I14: =IF(G14=0,(D14*0.01),IF(H14<=0,0.01*D14,IF(AND(H14>0,H14<=300000),H14*7%,IF(AND(H14>=300000,H14<600000),21000+(H14-300000)*11%,IF(AND(H14>=600000,H14<1100000),54000+(H14-600000)*15%,IF(AND(H14>=1100000,H14<1600000),129000+(H14-1100000)*19%,IF(AND(H14>=1600000,H14<3200000),224000+(H14-1600000)*21%,560000+(H14-3200000)*24%))))))) -> 0 | J14: =I14/12 -> 0 | K14: 0 | L14: =+J14*K14 -> 0
A15: 8 | D15: 0 | E15: =D15*0.08 -> 0 | F15: =D15-E15 -> 0 | G15: =IF(F15<=300000,0,IF(F15>=20000000,(F15*0.21),(F15*0.2)+200000)) -> 0 | H15: =+D15-G15-E15 -> 0 | I15: =IF(G15=0,(D15*0.01),IF(H15<=0,0.01*D15,IF(AND(H15>0,H15<=300000),H15*7%,IF(AND(H15>=300000,H15<600000),21000+(H15-300000)*11%,IF(AND(H15>=600000,H15<1100000),54000+(H15-600000)*15%,IF(AND(H15>=1100000,H15<1600000),129000+(H15-1100000)*19%,IF(AND(H15>=1600000,H15<3200000),224000+(H15-1600000)*21%,560000+(H15-3200000)*24%))))))) -> 0 | J15: =I15/12 -> 0 | K15: 0 | L15: =+J15*K15 -> 0
A16: 9 | D16: 0 | E16: =D16*0.08 -> 0 | F16: =D16-E16 -> 0 | G16: =IF(F16<=300000,0,IF(F16>=20000000,(F16*0.21),(F16*0.2)+200000)) -> 0 | H16: =+D16-G16-E16 -> 0 | I16: =IF(G16=0,(D16*0.01),IF(H16<=0,0.01*D16,IF(AND(H16>0,H16<=300000),H16*7%,IF(AND(H16>=300000,H16<600000),21000+(H16-300000)*11%,IF(AND(H16>=600000,H16<1100000),54000+(H16-600000)*15%,IF(AND(H16>=1100000,H16<1600000),129000+(H16-1100000)*19%,IF(AND(H16>=1600000,H16<3200000),224000+(H16-1600000)*21%,560000+(H16-3200000)*24%))))))) -> 0 | J16: =I16/12 -> 0 | K16: 0 | L16: =+J16*K16 -> 0
A17: 10 | D17: 0 | E17: =D17*0.08 -> 0 | F17: =D17-E17 -> 0 | G17: =IF(F17<=300000,0,IF(F17>=20000000,(F17*0.21),(F17*0.2)+200000)) -> 0 | H17: =+D17-G17-E17 -> 0 | I17: =IF(G17=0,(D17*0.01),IF(H17<=0,0.01*D17,IF(AND(H17>0,H17<=300000),H17*7%,IF(AND(H17>=300000,H17<600000),21000+(H17-300000)*11%,IF(AND(H17>=600000,H17<1100000),54000+(H17-600000)*15%,IF(AND(H17>=1100000,H17<1600000),129000+(H17-1100000)*19%,IF(AND(H17>=1600000,H17<3200000),224000+(H17-1600000)*21%,560000+(H17-3200000)*24%))))))) -> 0 | J17: =I17/12 -> 0 | K17: 0 | L17: =+J17*K17 -> 0
A18: 11 | D18: 0 | E18: =D18*0.08 -> 0 | F18: =D18-E18 -> 0 | G18: =IF(F18<=300000,0,IF(F18>=20000000,(F18*0.21),(F18*0.2)+200000)) -> 0 | H18: =+D18-G18-E18 -> 0 | I18: =IF(G18=0,(D18*0.01),IF(H18<=0,0.01*D18,IF(AND(H18>0,H18<=300000),H18*7%,IF(AND(H18>=300000,H18<600000),21000+(H18-300000)*11%,IF(AND(H18>=600000,H18<1100000),54000+(H18-600000)*15%,IF(AND(H18>=1100000,H18<1600000),129000+(H18-1100000)*19%,IF(AND(H18>=1600000,H18<3200000),224000+(H18-1600000)*21%,560000+(H18-3200000)*24%))))))) -> 0 | J18: =I18/12 -> 0 | K18: 0 | L18: =+J18*K18 -> 0
A19: 12 | D19: 0 | E19: =D19*0.08 -> 0 | F19: =D19-E19 -> 0 | G19: =IF(F19<=300000,0,IF(F19>=20000000,(F19*0.21),(F19*0.2)+200000)) -> 0 | H19: =+D19-G19-E19 -> 0 | I19: =IF(G19=0,(D19*0.01),IF(H19<=0,0.01*D19,IF(AND(H19>0,H19<=300000),H19*7%,IF(AND(H19>=300000,H19<600000),21000+(H19-300000)*11%,IF(AND(H19>=600000,H19<1100000),54000+(H19-600000)*15%,IF(AND(H19>=1100000,H19<1600000),129000+(H19-1100000)*19%,IF(AND(H19>=1600000,H19<3200000),224000+(H19-1600000)*21%,560000+(H19-3200000)*24%))))))) -> 0 | J19: =I19/12 -> 0 | K19: 0 | L19: =+J19*K19 -> 0
A20: 13 | D20: 0 | E20: =D20*0.08 -> 0 | F20: =D20-E20 -> 0 | G20: =IF(F20<=300000,0,IF(F20>=20000000,(F20*0.21),(F20*0.2)+200000)) -> 0 | H20: =+D20-G20-E20 -> 0 | I20: =IF(G20=0,(D20*0.01),IF(H20<=0,0.01*D20,IF(AND(H20>0,H20<=300000),H20*7%,IF(AND(H20>=300000,H20<600000),21000+(H20-300000)*11%,IF(AND(H20>=600000,H20<1100000),54000+(H20-600000)*15%,IF(AND(H20>=1100000,H20<1600000),129000+(H20-1100000)*19%,IF(AND(H20>=1600000,H20<3200000),224000+(H20-1600000)*21%,560000+(H20-3200000)*24%))))))) -> 0 | J20: =I20/12 -> 0 | K20: 0 | L20: =+J20*K20 -> 0
... A683: 676 | D683: 0 | E683: =D683*0.08 -> 0 | F683: =D683-E683 -> 0 | G683: =IF(F683<=300000,0,IF(F683>=20000000,(F683*0.21),(F683*0.2)+200000)) -> 0 | H683: =+D683-G683-E683 -> 0 | I683: =IF(G683=0,(D683*0.01),IF(H683<=0,0.01*D683,IF(AND(H683>0,H683<=300000),H683*7%,IF(AND(H683>=300000,H683<600000),21000+(H683-300000)*11%,IF(AND(H683>=600000,H683<1100000),54000+(H683-600000)*15%,IF(AND(H683>=1100000,H683<1600000),129000+(H683-1100000)*19%,IF(AND(H683>=1600000,H683<3200000),224000+(H683-1600000)*21%,560000+(H683-3200000)*24%))))))) -> 0 | J683: =I683/12 -> 0 | K683: 0 | L683: =+J683*K683 -> 0
D685: =SUM(D8:D683) -> 0 | G685: =SUM(G8:G683) -> 0 | H685: =SUM(H8:H683) -> 0 | I685: =SUM(I8:I683) -> 0 | J685: =SUM(J8:J683) -> 0 | L685: =SUM(L8:L683) -> 0

Sheet computation (expat) 2021
A7: S/N | B7: NAME | C7: DESIGNATION | D7: ANNUAL TOTAL GROSS INCOME + BIK | E7: CRA | F7: TAXABLE INCOME | G7: ANNUAL TAX | H7: MONTHLY TAX | I7: MNTH | J7: PRO BY MNTH
A8: 1 | D8: 0 | E8: =IF(D8<=300000,0,IF(D8>=20000000,(D8*0.21),(D8*0.2)+200000)) -> 0 | F8: =+D8-E8 -> 0 | G8: =IF(E8=0,(D8*0.01),IF(F8<=0,0.01*D8,IF(AND(F8>0,F8<=300000),F8*7%,IF(AND(F8>=300000,F8<600000),21000+(F8-300000)*11%,IF(AND(F8>=600000,F8<1100000),54000+(F8-600000)*15%,IF(AND(F8>=1100000,F8<1600000),129000+(F8-1100000)*19%,IF(AND(F8>=1600000,F8<3200000),224000+(F8-1600000)*21%,560000+(F8-3200000)*24%))))))) -> 0 | H8: =G8/12 -> 0 | I8: 12 | J8: =+H8*I8 -> 0
A9: 2 | D9: 0 | E9: =IF(D9<=300000,0,IF(D9>=20000000,(D9*0.21),(D9*0.2)+200000)) -> 0 | F9: =+D9-E9 -> 0 | G9: =IF(E9=0,(D9*0.01),IF(F9<=0,0.01*D9,IF(AND(F9>0,F9<=300000),F9*7%,IF(AND(F9>=300000,F9<600000),21000+(F9-300000)*11%,IF(AND(F9>=600000,F9<1100000),54000+(F9-600000)*15%,IF(AND(F9>=1100000,F9<1600000),129000+(F9-1100000)*19%,IF(AND(F9>=1600000,F9<3200000),224000+(F9-1600000)*21%,560000+(F9-3200000)*24%))))))) -> 0 | H9: =G9/12 -> 0 | I9: 0 | J9: =+H9*I9 -> 0
A10: 3 | D10: 0 | E10: =IF(D10<=300000,0,IF(D10>=20000000,(D10*0.21),(D10*0.2)+200000)) -> 0 | F10: =+D10-E10 -> 0 | G10: =IF(E10=0,(D10*0.01),IF(F10<=0,0.01*D10,IF(AND(F10>0,F10<=300000),F10*7%,IF(AND(F10>=300000,F10<600000),21000+(F10-300000)*11%,IF(AND(F10>=600000,F10<1100000),54000+(F10-600000)*15%,IF(AND(F10>=1100000,F10<1600000),129000+(F10-1100000)*19%,IF(AND(F10>=1600000,F10<3200000),224000+(F10-1600000)*21%,560000+(F10-3200000)*24%))))))) -> 0 | H10: =G10/12 -> 0 | I10: 0 | J10: =+H10*I10 -> 0
A11: 4 | D11: 0 | E11: =IF(D11<=300000,0,IF(D11>=20000000,(D11*0.21),(D11*0.2)+200000)) -> 0 | F11: =+D11-E11 -> 0 | G11: =IF(E11=0,(D11*0.01),IF(F11<=0,0.01*D11,IF(AND(F11>0,F11<=300000),F11*7%,IF(AND(F11>=300000,F11<600000),21000+(F11-300000)*11%,IF(AND(F11>=600000,F11<1100000),54000+(F11-600000)*15%,IF(AND(F11>=1100000,F11<1600000),129000+(F11-1100000)*19%,IF(AND(F11>=1600000,F11<3200000),224000+(F11-1600000)*21%,560000+(F11-3200000)*24%))))))) -> 0 | H11: =G11/12 -> 0 | I11: 0 | J11: =+H11*I11 -> 0
A12: 5 | D12: 0 | E12: =IF(D12<=300000,0,IF(D12>=20000000,(D12*0.21),(D12*0.2)+200000)) -> 0 | F12: =+D12-E12 -> 0 | G12: =IF(E12=0,(D12*0.01),IF(F12<=0,0.01*D12,IF(AND(F12>0,F12<=300000),F12*7%,IF(AND(F12>=300000,F12<600000),21000+(F12-300000)*11%,IF(AND(F12>=600000,F12<1100000),54000+(F12-600000)*15%,IF(AND(F12>=1100000,F12<1600000),129000+(F12-1100000)*19%,IF(AND(F12>=1600000,F12<3200000),224000+(F12-1600000)*21%,560000+(F12-3200000)*24%))))))) -> 0 | H12: =G12/12 -> 0 | I12: 0 | J12: =+H12*I12 -> 0
A13: 6 | D13: 0 | E13: =IF(D13<=300000,0,IF(D13>=20000000,(D13*0.21),(D13*0.2)+200000)) -> 0 | F13: =+D13-E13 -> 0 | G13: =IF(E13=0,(D13*0.01),IF(F13<=0,0.01*D13,IF(AND(F13>0,F13<=300000),F13*7%,IF(AND(F13>=300000,F13<600000),21000+(F13-300000)*11%,IF(AND(F13>=600000,F13<1100000),54000+(F13-600000)*15%,IF(AND(F13>=1100000,F13<1600000),129000+(F13-1100000)*19%,IF(AND(F13>=1600000,F13<3200000),224000+(F13-1600000)*21%,560000+(F13-3200000)*24%))))))) -> 0 | H13: =G13/12 -> 0 | I13: 0 | J13: =+H13*I13 -> 0
A14: 7 | D14: 0 | E14: =IF(D14<=300000,0,IF(D14>=20000000,(D14*0.21),(D14*0.2)+200000)) -> 0 | F14: =+D14-E14 -> 0 | G14: =IF(E14=0,(D14*0.01),IF(F14<=0,0.01*D14,IF(AND(F14>0,F14<=300000),F14*7%,IF(AND(F14>=300000,F14<600000),21000+(F14-300000)*11%,IF(AND(F14>=600000,F14<1100000),54000+(F14-600000)*15%,IF(AND(F14>=1100000,F14<1600000),129000+(F14-1100000)*19%,IF(AND(F14>=1600000,F14<3200000),224000+(F14-1600000)*21%,560000+(F14-3200000)*24%))))))) -> 0 | H14: =G14/12 -> 0 | I14: 0 | J14: =+H14*I14 -> 0
A15: 8 | D15: 0 | E15: =IF(D15<=300000,0,IF(D15>=20000000,(D15*0.21),(D15*0.2)+200000)) -> 0 | F15: =+D15-E15 -> 0 | G15: =IF(E15=0,(D15*0.01),IF(F15<=0,0.01*D15,IF(AND(F15>0,F15<=300000),F15*7%,IF(AND(F15>=300000,F15<600000),21000+(F15-300000)*11%,IF(AND(F15>=600000,F15<1100000),54000+(F15-600000)*15%,IF(AND(F15>=1100000,F15<1600000),129000+(F15-1100000)*19%,IF(AND(F15>=1600000,F15<3200000),224000+(F15-1600000)*21%,560000+(F15-3200000)*24%))))))) -> 0 | H15: =G15/12 -> 0 | I15: 0 | J15: =+H15*I15 -> 0
A16: 9 | D16: 0 | E16: =IF(D16<=300000,0,IF(D16>=20000000,(D16*0.21),(D16*0.2)+200000)) -> 0 | F16: =+D16-E16 -> 0 | G16: =IF(E16=0,(D16*0.01),IF(F16<=0,0.01*D16,IF(AND(F16>0,F16<=300000),F16*7%,IF(AND(F16>=300000,F16<600000),21000+(F16-300000)*11%,IF(AND(F16>=600000,F16<1100000),54000+(F16-600000)*15%,IF(AND(F16>=1100000,F16<1600000),129000+(F16-1100000)*19%,IF(AND(F16>=1600000,F16<3200000),224000+(F16-1600000)*21%,560000+(F16-3200000)*24%))))))) -> 0 | H16: =G16/12 -> 0 | I16: 0 | J16: =+H16*I16 -> 0
A17: 10 | D17: 0 | E17: =IF(D17<=300000,0,IF(D17>=20000000,(D17*0.21),(D17*0.2)+200000)) -> 0 | F17: =+D17-E17 -> 0 | G17: =IF(E17=0,(D17*0.01),IF(F17<=0,0.01*D17,IF(AND(F17>0,F17<=300000),F17*7%,IF(AND(F17>=300000,F17<600000),21000+(F17-300000)*11%,IF(AND(F17>=600000,F17<1100000),54000+(F17-600000)*15%,IF(AND(F17>=1100000,F17<1600000),129000+(F17-1100000)*19%,IF(AND(F17>=1600000,F17<3200000),224000+(F17-1600000)*21%,560000+(F17-3200000)*24%))))))) -> 0 | H17: =G17/12 -> 0 | I17: 0 | J17: =+H17*I17 -> 0
A18: 11 | D18: 0 | E18: =IF(D18<=300000,0,IF(D18>=20000000,(D18*0.21),(D18*0.2)+200000)) -> 0 | F18: =+D18-E18 -> 0 | G18: =IF(E18=0,(D18*0.01),IF(F18<=0,0.01*D18,IF(AND(F18>0,F18<=300000),F18*7%,IF(AND(F18>=300000,F18<600000),21000+(F18-300000)*11%,IF(AND(F18>=600000,F18<1100000),54000+(F18-600000)*15%,IF(AND(F18>=1100000,F18<1600000),129000+(F18-1100000)*19%,IF(AND(F18>=1600000,F18<3200000),224000+(F18-1600000)*21%,560000+(F18-3200000)*24%))))))) -> 0 | H18: =G18/12 -> 0 | I18: 0 | J18: =+H18*I18 -> 0
A19: 12 | D19: 0 | E19: =IF(D19<=300000,0,IF(D19>=20000000,(D19*0.21),(D19*0.2)+200000)) -> 0 | F19: =+D19-E19 -> 0 | G19: =IF(E19=0,(D19*0.01),IF(F19<=0,0.01*D19,IF(AND(F19>0,F19<=300000),F19*7%,IF(AND(F19>=300000,F19<600000),21000+(F19-300000)*11%,IF(AND(F19>=600000,F19<1100000),54000+(F19-600000)*15%,IF(AND(F19>=1100000,F19<1600000),129000+(F19-1100000)*19%,IF(AND(F19>=1600000,F19<3200000),224000+(F19-1600000)*21%,560000+(F19-3200000)*24%))))))) -> 0 | H19: =G19/12 -> 0 | I19: 0 | J19: =+H19*I19 -> 0
... A683: 676 | D683: 0 | E683: =IF(D683<=300000,0,IF(D683>=20000000,(D683*0.21),(D683*0.2)+200000)) -> 0 | F683: =+D683-E683 -> 0 | G683: =IF(E683=0,(D683*0.01),IF(F683<=0,0.01*D683,IF(AND(F683>0,F683<=300000),F683*7%,IF(AND(F683>=300000,F683<600000),21000+(F683-300000)*11%,IF(AND(F683>=600000,F683<1100000),54000+(F683-600000)*15%,IF(AND(F683>=1100000,F683<1600000),129000+(F683-1100000)*19%,IF(AND(F683>=1600000,F683<3200000),224000+(F683-1600000)*21%,560000+(F683-3200000)*24%))))))) -> 0 | H683: =G683/12 -> 0 | I683: 0 | J683: =+H683*I683 -> 0
D685: =SUM(D8:D683) -> 0 | E685: =SUM(E8:E683) -> 0 | F685: =SUM(F8:F683) -> 0 | G685: =SUM(G8:G683) -> 0 | H685: =SUM(H8:H683) -> 0 | J685: =SUM(J8:J683) -> 0

Sheet Tax Due (2)
B1: 3c
C3: 2023 | D3: 2024 | E3: TOTAL
B4: PAYE
B5: Tax Liability:
B6: Local | C6: =+'local 23'!U127 -> 3423008 | D6: =+'local 24'!T128 -> 3378841.6 | E6: =SUM(C6:D6) -> 6801849.6
B7: Expatriate | C7: =+'expat 2023'!R8 -> 5632000 | D7: =+'expat 2024 '!Q8 -> 6208000 | E7: =SUM(C7:D7) -> 11840000
B8: Total PAYE liability | C8: =C6+C7 -> 9055008 | D8: =D6+D7 -> 9586841.6 | E8: =SUM(C8:D8) -> 18641850
B10: Remittances
B11: Local & Exp. | C11: 7141077 | D11: 6753847.3 | E11: =SUM(C11:D11) -> 13894924
B12: Total Remittances | C12: =C11 -> 7141077 | D12: =D11 -> 6753847.3 | E12: =SUM(C12:D12) -> 13894924
B14: Total PAYE Outstand'g Remit'nces | C14: =C8-C12 -> 1913931 | D14: =D8-D12 -> 2832994.3 | E14: =SUM(C14:D14) -> 4746925.3
B16: WHT
B17: Directors' Fees | C17: 0 | D17: 0 | E17: =SUM(C17:D17) -> 0
B18: Rent | C18: =+'WHT SMRY 2024'!E27 -> 1120000 | D18: =+'WHT SMRY 2024'!I27 -> 2250000 | E18: =SUM(C18:D18) -> 3370000
B19: Services | C19: 0 | D19: 0 | E19: =SUM(C19:D19) -> 0
B20: Legal & Prof Fees | C20: =+'WHT SMRY 2024'!I15 -> 50000 | D20: 0 | E20: =SUM(C20:D20) -> 50000
B21: Audit Fees | C21: =+'WHT SMRY 2024'!I19 -> 100000 | D21: =+'WHT SMRY 2024'!E19 -> 150000 | E21: =SUM(C21:D21) -> 250000
B22: Contract & Supply | D22: 0 | E22: =SUM(C22:D22) -> 0
B23: Dividend | C23: 0 | D23: 0 | E23: =SUM(C23:D23) -> 0
B24: Commission | C24: ='[55]WHT SMRY'!E27 -> 0 | D24: ='[55]WHT SMRY'!H27 -> 0 | E24: =SUM(C24:D24) -> 0
B25: Sub-Total | C25: =SUM(C17:C24) -> 1270000 | D25: =SUM(D17:D24) -> 2400000 | E25: =SUM(C25:D25) -> 3670000
B26: Less: Remittances | C26: =+'WHT Remittance 2024'!C13 -> 1120000 | D26: =+'WHT Remittance 2023'!C12 -> 2250000 | E26: =SUM(C26:D26) -> 3370000
B27: Total WHT Outstanding | C27: =C25-C26 -> 150000 | D27: =D25-D26 -> 150000 | E27: =SUM(C27:D27) -> 300000
E28: =SUM(C28:D28) -> 0
B29: PAYE & WHT Outst'dg | C29: =C14+C27 -> 2063931 | D29: =D14+D27 -> 2982994.3 | E29: =SUM(C29:D29) -> 5046925.3
B30: Development Levy | C30: 0 | D30: 0 | E30: =SUM(C30:D30) -> 0
B31: Business Premises | C31: 0 | D31: 0 | E31: =SUM(C31:D31) -> 0
B32: Sub-Total | C32: =SUM(C29:C31) -> 2063931 | D32: =SUM(D29:D31) -> 2982994.3 | E32: =SUM(C32:D32) -> 5046925.3
B33: Add: 10% Penalty | C33: =IF(C32<0,0,(0.1*C32)) -> 206393.1 | D33: =IF(D32<0,0,(0.1*D32)) -> 298299.43 | E33: =SUM(C33:D33) -> 504692.53
C34: =SUM(C32:C33) -> 2270324.1 | D34: =SUM(D32:D33) -> 3281293.7 | E34: =SUM(C34:D34) -> 5551617.8
B35: Add: 12% Interest on WHT | C35: =0.12*C27 -> 18000 | D35: =0.12*D27 -> 18000 | E35: =SUM(C35:D35) -> 36000
B36: Add: 21% Interest | C36: =0.21*(C14+C30+C31) -> 401925.51 | D36: =0.21*(D14+D30+D31) -> 594928.79 | E36: =SUM(C36:D36) -> 996854.3
B37: TOTAL AMOUNT DUE | C37: =SUM(C34:C36) -> 2690249.6 | D37: =SUM(D34:D36) -> 3894222.5 | E37: =SUM(C37:D37) -> 6584472.1

Sheet local 23
A1: 3C HUB BRAND MANAGEMENT LIMITED
A2: ANNUAL PAYROLL FOR 2023
A3: NO OF EMPLOYEE | B3: Tax Payer Number | C3: Surname | D3: First Name | E3: Middle Name | F3: Designation | G3: No. of Months | H3: Gross Income | I3: Chargeable Income | J3: Development Levy | K3: Tax Paid | M3: ANNUAL TOTAL GROSS INCOME + BIK | N3: PENSION | O3: NET INCOME | P3: CRA | Q3: TAXABLE INCOME | R3: ANNUAL TAX | S3: MONTHLY TAX | T3: MNTH | U3: PRO BY MNTH
A4: 1 | B4: N-10811847 | C4: Ihezie | D4: Monica | F4: 020 Officer | G4: 12 | H4: 540000 | I4: 188800 | J4: 100 | K4: 13216 | M4: =H4 -> 540000 | N4: =M4*0.08 -> 43200 | O4: =M4-N4 -> 496800 | P4: =IF(O4<=300000,0,IF(O4>=20000000,(O4*0.21),(O4*0.2)+200000)) -> 299360 | Q4: =+M4-P4-N4 -> 197440 | R4: =IF(P4=0,(M4*0.01),IF(Q4<=0,0.01*M4,IF(AND(Q4>0,Q4<=300000),Q4*7%,IF(AND(Q4>=300000,Q4<600000),21000+(Q4-300000)*11%,IF(AND(Q4>=600000,Q4<1100000),54000+(Q4-600000)*15%,IF(AND(Q4>=1100000,Q4<1600000),129000+(Q4-1100000)*19%,IF(AND(Q4>=1600000,Q4<3200000),224000+(Q4-1600000)*21%,560000+(Q4-3200000)*24%))))))) -> 13820.8 | S4: =R4/12 -> 1151.7333 | T4: =G4 -> 12 | U4: =+S4*T4 -> 13820.8
A5: 2 | B5: N-2986347 | C5: Victor. | D5: N. | E5: Nwaoha | F5: Info Tech | G5: 12 | H5: 960000 | I5: 491200 | J5: 100 | K5: 42032 | M5: =H5 -> 960000 | N5: =M5*0.08 -> 76800 | O5: =M5-N5 -> 883200 | P5: =IF(O5<=300000,0,IF(O5>=20000000,(O5*0.21),(O5*0.2)+200000)) -> 376640 | Q5: =+M5-P5-N5 -> 506560 | R5: =IF(P5=0,(M5*0.01),IF(Q5<=0,0.01*M5,IF(AND(Q5>0,Q5<=300000),Q5*7%,IF(AND(Q5>=300000,Q5<600000),21000+(Q5-300000)*11%,IF(AND(Q5>=600000,Q5<1100000),54000+(Q5-600000)*15%,IF(AND(Q5>=1100000,Q5<1600000),129000+(Q5-1100000)*19%,IF(AND(Q5>=1600000,Q5<3200000),224000+(Q5-1600000)*21%,560000+(Q5-3200000)*24%))))))) -> 43721.6 | S5: =R5/12 -> 3643.4667 | T5: =G5 -> 12 | U5: =+S5*T5 -> 43721.6
A6: 3 | B6: N-4078857 | C6: Adesola | D6: Adeyinka | F6: Account officer | G6: 12 | H6: 660000 | I6: 275200 | J6: 100 | K6: 19264 | M6: =H6 -> 660000 | N6: =M6*0.08 -> 52800 | O6: =M6-N6 -> 607200 | P6: =IF(O6<=300000,0,IF(O6>=20000000,(O6*0.21),(O6*0.2)+200000)) -> 321440 | Q6: =+M6-P6-N6 -> 285760 | R6: =IF(P6=0,(M6*0.01),IF(Q6<=0,0.01*M6,IF(AND(Q6>0,Q6<=300000),Q6*7%,IF(AND(Q6>=300000,Q6<600000),21000+(Q6-300000)*11%,IF(AND(Q6>=600000,Q6<1100000),54000+(Q6-600000)*15%,IF(AND(Q6>=1100000,Q6<1600000),129000+(Q6-1100000)*19%,IF(AND(Q6>=1600000,Q6<3200000),224000+(Q6-1600000)*21%,560000+(Q6-3200000)*24%))))))) -> 20003.2 | S6: =R6/12 -> 1666.9333 | T6: =G6 -> 12 | U6: =+S6*T6 -> 20003.2
A7: 4 | B7: N-4081285 | C7: Egbuchulam | D7: Francis | F7: Electronics Aftersales Manager | G7: 12 | H7: 600000 | I7: 232000 | J7: 100 | K7: 16240 | M7: =H7 -> 600000 | N7: =M7*0.08 -> 48000 | O7: =M7-N7 -> 552000 | P7: =IF(O7<=300000,0,IF(O7>=20000000,(O7*0.21),(O7*0.2)+200000)) -> 310400 | Q7: =+M7-P7-N7 -> 241600 | R7: =IF(P7=0,(M7*0.01),IF(Q7<=0,0.01*M7,IF(AND(Q7>0,Q7<=300000),Q7*7%,IF(AND(Q7>=300000,Q7<600000),21000+(Q7-300000)*11%,IF(AND(Q7>=600000,Q7<1100000),54000+(Q7-600000)*15%,IF(AND(Q7>=1100000,Q7<1600000),129000+(Q7-1100000)*19%,IF(AND(Q7>=1600000,Q7<3200000),224000+(Q7-1600000)*21%,560000+(Q7-3200000)*24%))))))) -> 16912 | S7: =R7/12 -> 1409.3333 | T7: =G7 -> 12 | U7: =+S7*T7 -> 16912
A8: 5 | B8: N-4129622 | C8: Timothy | D8: O | E8: Ikponmwen | F8: Manager | G8: 12 | H8: 600000 | I8: 232000 | J8: 100 | K8: 16240 | M8: =H8 -> 600000 | N8: =M8*0.08 -> 48000 | O8: =M8-N8 -> 552000 | P8: =IF(O8<=300000,0,IF(O8>=20000000,(O8*0.21),(O8*0.2)+200000)) -> 310400 | Q8: =+M8-P8-N8 -> 241600 | R8: =IF(P8=0,(M8*0.01),IF(Q8<=0,0.01*M8,IF(AND(Q8>0,Q8<=300000),Q8*7%,IF(AND(Q8>=300000,Q8<600000),21000+(Q8-300000)*11%,IF(AND(Q8>=600000,Q8<1100000),54000+(Q8-600000)*15%,IF(AND(Q8>=1100000,Q8<1600000),129000+(Q8-1100000)*19%,IF(AND(Q8>=1600000,Q8<3200000),224000+(Q8-1600000)*21%,560000+(Q8-3200000)*24%))))))) -> 16912 | S8: =R8/12 -> 1409.3333 | T8: =G8 -> 12 | U8: =+S8*T8 -> 16912
A9: 6 | B9: N-4345599 | C9: Kolawole | D9: Opeyemi | F9: Material Officer | G9: 12 | H9: 420000 | I9: 102400 | J9: 100 | K9: 7168 | M9: =H9 -> 420000 | N9: =M9*0.08 -> 33600 | O9: =M9-N9 -> 386400 | P9: =IF(O9<=300000,0,IF(O9>=20000000,(O9*0.21),(O9*0.2)+200000)) -> 277280 | Q9: =+M9-P9-N9 -> 109120 | R9: =IF(P9=0,(M9*0.01),IF(Q9<=0,0.01*M9,IF(AND(Q9>0,Q9<=300000),Q9*7%,IF(AND(Q9>=300000,Q9<600000),21000+(Q9-300000)*11%,IF(AND(Q9>=600000,Q9<1100000),54000+(Q9-600000)*15%,IF(AND(Q9>=1100000,Q9<1600000),129000+(Q9-1100000)*19%,IF(AND(Q9>=1600000,Q9<3200000),224000+(Q9-1600000)*21%,560000+(Q9-3200000)*24%))))))) -> 7638.4 | S9: =R9/12 -> 636.53333 | T9: =G9 -> 12 | U9: =+S9*T9 -> 7638.4
A10: 7 | B10: N-4363325 | C10: Ginikanwa | D10: Darlington | E10: Uzoma | F10: Maintenance | G10: 12 | H10: 420000 | I10: 102400 | J10: 100 | K10: 7168 | M10: =H10 -> 420000 | N10: =M10*0.08 -> 33600 | O10: =M10-N10 -> 386400 | P10: =IF(O10<=300000,0,IF(O10>=20000000,(O10*0.21),(O10*0.2)+200000)) -> 277280 | Q10: =+M10-P10-N10 -> 109120 | R10: =IF(P10=0,(M10*0.01),IF(Q10<=0,0.01*M10,IF(AND(Q10>0,Q10<=300000),Q10*7%,IF(AND(Q10>=300000,Q10<600000),21000+(Q10-300000)*11%,IF(AND(Q10>=600000,Q10<1100000),54000+(Q10-600000)*15%,IF(AND(Q10>=1100000,Q10<1600000),129000+(Q10-1100000)*19%,IF(AND(Q10>=1600000,Q10<3200000),224000+(Q10-1600000)*21%,560000+(Q10-3200000)*24%))))))) -> 7638.4 | S10: =R10/12 -> 636.53333 | T10: =G10 -> 12 | U10: =+S10*T10 -> 7638.4
A11: 8 | B11: N-4363640 | C11: Kuponu | D11: Sesi | E11: Egbemimo | F11: Manager | G11: 12 | H11: 540000 | I11: 188800 | J11: 100 | K11: 13216 | M11: =H11 -> 540000 | N11: =M11*0.08 -> 43200 | O11: =M11-N11 -> 496800 | P11: =IF(O11<=300000,0,IF(O11>=20000000,(O11*0.21),(O11*0.2)+200000)) -> 299360 | Q11: =+M11-P11-N11 -> 197440 | R11: =IF(P11=0,(M11*0.01),IF(Q11<=0,0.01*M11,IF(AND(Q11>0,Q11<=300000),Q11*7%,IF(AND(Q11>=300000,Q11<600000),21000+(Q11-300000)*11%,IF(AND(Q11>=600000,Q11<1100000),54000+(Q11-600000)*15%,IF(AND(Q11>=1100000,Q11<1600000),129000+(Q11-1100000)*19%,IF(AND(Q11>=1600000,Q11<3200000),224000+(Q11-1600000)*21%,560000+(Q11-3200000)*24%))))))) -> 13820.8 | S11: =R11/12 -> 1151.7333 | T11: =G11 -> 12 | U11: =+S11*T11 -> 13820.8
A12: 9 | B12: N-4364503 | C12: Ayira | D12: Peace | F12: Cashier | G12: 12 | H12: 480000 | I12: 145600 | J12: 100 | K12: 10192 | M12: =H12 -> 480000 | N12: =M12*0.08 -> 38400 | O12: =M12-N12 -> 441600 | P12: =IF(O12<=300000,0,IF(O12>=20000000,(O12*0.21),(O12*0.2)+200000)) -> 288320 | Q12: =+M12-P12-N12 -> 153280 | R12: =IF(P12=0,(M12*0.01),IF(Q12<=0,0.01*M12,IF(AND(Q12>0,Q12<=300000),Q12*7%,IF(AND(Q12>=300000,Q12<600000),21000+(Q12-300000)*11%,IF(AND(Q12>=600000,Q12<1100000),54000+(Q12-600000)*15%,IF(AND(Q12>=1100000,Q12<1600000),129000+(Q12-1100000)*19%,IF(AND(Q12>=1600000,Q12<3200000),224000+(Q12-1600000)*21%,560000+(Q12-3200000)*24%))))))) -> 10729.6 | S12: =R12/12 -> 894.13333 | T12: =G12 -> 12 | U12: =+S12*T12 -> 10729.6
A13: 10 | B13: N-4364986 | C13: Kusagba | D13: Oluwakayode | F13: Stock Audior | G13: 12 | H13: 660000 | I13: 275200 | J13: 100 | K13: 19264 | M13: =H13 -> 660000 | N13: =M13*0.08 -> 52800 | O13: =M13-N13 -> 607200 | P13: =IF(O13<=300000,0,IF(O13>=20000000,(O13*0.21),(O13*0.2)+200000)) -> 321440 | Q13: =+M13-P13-N13 -> 285760 | R13: =IF(P13=0,(M13*0.01),IF(Q13<=0,0.01*M13,IF(AND(Q13>0,Q13<=300000),Q13*7%,IF(AND(Q13>=300000,Q13<600000),21000+(Q13-300000)*11%,IF(AND(Q13>=600000,Q13<1100000),54000+(Q13-600000)*15%,IF(AND(Q13>=1100000,Q13<1600000),129000+(Q13-1100000)*19%,IF(AND(Q13>=1600000,Q13<3200000),224000+(Q13-1600000)*21%,560000+(Q13-3200000)*24%))))))) -> 20003.2 | S13: =R13/12 -> 1666.9333 | T13: =G13 -> 12 | U13: =+S13*T13 -> 20003.2
A14: 11 | B14: N-4369098 | C14: Okoro | D14: Lilian | F14: Cashier | G14: 12 | H14: 480000 | I14: 145600 | J14: 100 | K14: 10192 | M14: =H14 -> 480000 | N14: =M14*0.08 -> 38400 | O14: =M14-N14 -> 441600 | P14: =IF(O14<=300000,0,IF(O14>=20000000,(O14*0.21),(O14*0.2)+200000)) -> 288320 | Q14: =+M14-P14-N14 -> 153280 | R14: =IF(P14=0,(M14*0.01),IF(Q14<=0,0.01*M14,IF(AND(Q14>0,Q14<=300000),Q14*7%,IF(AND(Q14>=300000,Q14<600000),21000+(Q14-300000)*11%,IF(AND(Q14>=600000,Q14<1100000),54000+(Q14-600000)*15%,IF(AND(Q14>=1100000,Q14<1600000),129000+(Q14-1100000)*19%,IF(AND(Q14>=1600000,Q14<3200000),224000+(Q14-1600000)*21%,560000+(Q14-3200000)*24%))))))) -> 10729.6 | S14: =R14/12 -> 894.13333 | T14: =G14 -> 12 | U14: =+S14*T14 -> 10729.6
A15: 12 | B15: N-4370821 | C15: Happiness | D15: Peace | F15: Store Supervisor | G15: 12 | H15: 540000 | I15: 188800 | J15: 100 | K15: 13216 | M15: =H15 -> 540000 | N15: =M15*0.08 -> 43200 | O15: =M15-N15 -> 496800 | P15: =IF(O15<=300000,0,IF(O15>=20000000,(O15*0.21),(O15*0.2)+200000)) -> 299360 | Q15: =+M15-P15-N15 -> 197440 | R15: =IF(P15=0,(M15*0.01),IF(Q15<=0,0.01*M15,IF(AND(Q15>0,Q15<=300000),Q15*7%,IF(AND(Q15>=300000,Q15<600000),21000+(Q15-300000)*11%,IF(AND(Q15>=600000,Q15<1100000),54000+(Q15-600000)*15%,IF(AND(Q15>=1100000,Q15<1600000),129000+(Q15-1100000)*19%,IF(AND(Q15>=1600000,Q15<3200000),224000+(Q15-1600000)*21%,560000+(Q15-3200000)*24%))))))) -> 13820.8 | S15: =R15/12 -> 1151.7333 | T15: =G15 -> 12 | U15: =+S15*T15 -> 13820.8
A16: 13 | B16: N-4374519 | C16: Ezioha | D16: Joel | E16: Ifeanyi | F16: Store Supervisor | G16: 12 | H16: 540000 | I16: 188800 | J16: 100 | K16: 13216 | M16: =H16 -> 540000 | N16: =M16*0.08 -> 43200 | O16: =M16-N16 -> 496800 | P16: =IF(O16<=300000,0,IF(O16>=20000000,(O16*0.21),(O16*0.2)+200000)) -> 299360 | Q16: =+M16-P16-N16 -> 197440 | R16: =IF(P16=0,(M16*0.01),IF(Q16<=0,0.01*M16,IF(AND(Q16>0,Q16<=300000),Q16*7%,IF(AND(Q16>=300000,Q16<600000),21000+(Q16-300000)*11%,IF(AND(Q16>=600000,Q16<1100000),54000+(Q16-600000)*15%,IF(AND(Q16>=1100000,Q16<1600000),129000+(Q16-1100000)*19%,IF(AND(Q16>=1600000,Q16<3200000),224000+(Q16-1600000)*21%,560000+(Q16-3200000)*24%))))))) -> 13820.8 | S16: =R16/12 -> 1151.7333 | T16: =G16 -> 12 | U16: =+S16*T16 -> 13820.8
A17: 14 | B17: N-4375382 | C17: Omolewa | D17: Mobolaji | F17: Cashier | G17: 12 | H17: 480000 | I17: 145600 | J17: 100 | K17: 10192 | M17: =H17 -> 480000 | N17: =M17*0.08 -> 38400 | O17: =M17-N17 -> 441600 | P17: =IF(O17<=300000,0,IF(O17>=20000000,(O17*0.21),(O17*0.2)+200000)) -> 288320 | Q17: =+M17-P17-N17 -> 153280 | R17: =IF(P17=0,(M17*0.01),IF(Q17<=0,0.01*M17,IF(AND(Q17>0,Q17<=300000),Q17*7%,IF(AND(Q17>=300000,Q17<600000),21000+(Q17-300000)*11%,IF(AND(Q17>=600000,Q17<1100000),54000+(Q17-600000)*15%,IF(AND(Q17>=1100000,Q17<1600000),129000+(Q17-1100000)*19%,IF(AND(Q17>=1600000,Q17<3200000),224000+(Q17-1600000)*21%,560000+(Q17-3200000)*24%))))))) -> 10729.6 | S17: =R17/12 -> 894.13333 | T17: =G17 -> 12 | U17: =+S17*T17 -> 10729.6
A18: 15 | B18: N-4377083 | C18: Oguh | D18: Chrysantus | E18: Ogadimma | F18: Maintainance | G18: 12 | H18: 420000 | I18: 102400 | J18: 100 | K18: 7168 | M18: =H18 -> 420000 | N18: =M18*0.08 -> 33600 | O18: =M18-N18 -> 386400 | P18: =IF(O18<=300000,0,IF(O18>=20000000,(O18*0.21),(O18*0.2)+200000)) -> 277280 | Q18: =+M18-P18-N18 -> 109120 | R18: =IF(P18=0,(M18*0.01),IF(Q18<=0,0.01*M18,IF(AND(Q18>0,Q18<=300000),Q18*7%,IF(AND(Q18>=300000,Q18<600000),21000+(Q18-300000)*11%,IF(AND(Q18>=600000,Q18<1100000),54000+(Q18-600000)*15%,IF(AND(Q18>=1100000,Q18<1600000),129000+(Q18-1100000)*19%,IF(AND(Q18>=1600000,Q18<3200000),224000+(Q18-1600000)*21%,560000+(Q18-3200000)*24%))))))) -> 7638.4 | S18: =R18/12 -> 636.53333 | T18: =G18 -> 12 | U18: =+S18*T18 -> 7638.4
A19: 16 | B19: N-4382660 | C19: Adetunji | D19: John | E19: Oluwatosin | F19: Manager | G19: 12 | H19: 540000 | I19: 188800 | J19: 100 | K19: 13216 | M19: =H19 -> 540000 | N19: =M19*0.08 -> 43200 | O19: =M19-N19 -> 496800 | P19: =IF(O19<=300000,0,IF(O19>=20000000,(O19*0.21),(O19*0.2)+200000)) -> 299360 | Q19: =+M19-P19-N19 -> 197440 | R19: =IF(P19=0,(M19*0.01),IF(Q19<=0,0.01*M19,IF(AND(Q19>0,Q19<=300000),Q19*7%,IF(AND(Q19>=300000,Q19<600000),21000+(Q19-300000)*11%,IF(AND(Q19>=600000,Q19<1100000),54000+(Q19-600000)*15%,IF(AND(Q19>=1100000,Q19<1600000),129000+(Q19-1100000)*19%,IF(AND(Q19>=1600000,Q19<3200000),224000+(Q19-1600000)*21%,560000+(Q19-3200000)*24%))))))) -> 13820.8 | S19: =R19/12 -> 1151.7333 | T19: =G19 -> 12 | U19: =+S19*T19 -> 13820.8
A20: 17 | B20: N-4398715 | C20: Otache | D20: Ruth | E20: Ene | F20: Cashier | G20: 12 | H20: 480000 | I20: 145600 | J20: 100 | K20: 10192 | M20: =H20 -> 480000 | N20: =M20*0.08 -> 38400 | O20: =M20-N20 -> 441600 | P20: =IF(O20<=300000,0,IF(O20>=20000000,(O20*0.21),(O20*0.2)+200000)) -> 288320 | Q20: =+M20-P20-N20 -> 153280 | R20: =IF(P20=0,(M20*0.01),IF(Q20<=0,0.01*M20,IF(AND(Q20>0,Q20<=300000),Q20*7%,IF(AND(Q20>=300000,Q20<600000),21000+(Q20-300000)*11%,IF(AND(Q20>=600000,Q20<1100000),54000+(Q20-600000)*15%,IF(AND(Q20>=1100000,Q20<1600000),129000+(Q20-1100000)*19%,IF(AND(Q20>=1600000,Q20<3200000),224000+(Q20-1600000)*21%,560000+(Q20-3200000)*24%))))))) -> 10729.6 | S20: =R20/12 -> 894.13333 | T20: =G20 -> 12 | U20: =+S20*T20 -> 10729.6
A21: 18 | B21: N-4398923 | C21: Roland | D21: Ebramieta | F21: Maintainance | G21: 12 | H21: 420000 | I21: 102400 | J21: 100 | K21: 7168 | M21: =H21 -> 420000 | N21: =M21*0.08 -> 33600 | O21: =M21-N21 -> 386400 | P21: =IF(O21<=300000,0,IF(O21>=20000000,(O21*0.21),(O21*0.2)+200000)) -> 277280 | Q21: =+M21-P21-N21 -> 109120 | R21: =IF(P21=0,(M21*0.01),IF(Q21<=0,0.01*M21,IF(AND(Q21>0,Q21<=300000),Q21*7%,IF(AND(Q21>=300000,Q21<600000),21000+(Q21-300000)*11%,IF(AND(Q21>=600000,Q21<1100000),54000+(Q21-600000)*15%,IF(AND(Q21>=1100000,Q21<1600000),129000+(Q21-1100000)*19%,IF(AND(Q21>=1600000,Q21<3200000),224000+(Q21-1600000)*21%,560000+(Q21-3200000)*24%))))))) -> 7638.4 | S21: =R21/12 -> 636.53333 | T21: =G21 -> 12 | U21: =+S21*T21 -> 7638.4
A22: 19 | B22: N-4399054 | C22: Adesina | D22: Olawole | E22: Daniel | F22: Maintenance | G22: 12 | H22: 420000 | I22: 102400 | J22: 100 | K22: 7168 | M22: =H22 -> 420000 | N22: =M22*0.08 -> 33600 | O22: =M22-N22 -> 386400 | P22: =IF(O22<=300000,0,IF(O22>=20000000,(O22*0.21),(O22*0.2)+200000)) -> 277280 | Q22: =+M22-P22-N22 -> 109120 | R22: =IF(P22=0,(M22*0.01),IF(Q22<=0,0.01*M22,IF(AND(Q22>0,Q22<=300000),Q22*7%,IF(AND(Q22>=300000,Q22<600000),21000+(Q22-300000)*11%,IF(AND(Q22>=600000,Q22<1100000),54000+(Q22-600000)*15%,IF(AND(Q22>=1100000,Q22<1600000),129000+(Q22-1100000)*19%,IF(AND(Q22>=1600000,Q22<3200000),224000+(Q22-1600000)*21%,560000+(Q22-3200000)*24%))))))) -> 7638.4 | S22: =R22/12 -> 636.53333 | T22: =G22 -> 12 | U22: =+S22*T22 -> 7638.4
A23: 20 | B23: N-4399142 | C23: Onyenoro | D23: Obinna | F23: Trainee Manager | G23: 12 | H23: 480000 | I23: 145600 | J23: 100 | K23: 10192 | M23: =H23 -> 480000 | N23: =M23*0.08 -> 38400 | O23: =M23-N23 -> 441600 | P23: =IF(O23<=300000,0,IF(O23>=20000000,(O23*0.21),(O23*0.2)+200000)) -> 288320 | Q23: =+M23-P23-N23 -> 153280 | R23: =IF(P23=0,(M23*0.01),IF(Q23<=0,0.01*M23,IF(AND(Q23>0,Q23<=300000),Q23*7%,IF(AND(Q23>=300000,Q23<600000),21000+(Q23-300000)*11%,IF(AND(Q23>=600000,Q23<1100000),54000+(Q23-600000)*15%,IF(AND(Q23>=1100000,Q23<1600000),129000+(Q23-1100000)*19%,IF(AND(Q23>=1600000,Q23<3200000),224000+(Q23-1600000)*21%,560000+(Q23-3200000)*24%))))))) -> 10729.6 | S23: =R23/12 -> 894.13333 | T23: =G23 -> 12 | U23: =+S23*T23 -> 10729.6
A24: 21 | B24: N-4405398 | C24: Olusola | D24: Odunayo | F24: Assistant Sales Manager | G24: 12 | H24: 540000 | I24: 188800 | J24: 100 | K24: 13216 | M24: =H24 -> 540000 | N24: =M24*0.08 -> 43200 | O24: =M24-N24 -> 496800 | P24: =IF(O24<=300000,0,IF(O24>=20000000,(O24*0.21),(O24*0.2)+200000)) -> 299360 | Q24: =+M24-P24-N24 -> 197440 | R24: =IF(P24=0,(M24*0.01),IF(Q24<=0,0.01*M24,IF(AND(Q24>0,Q24<=300000),Q24*7%,IF(AND(Q24>=300000,Q24<600000),21000+(Q24-300000)*11%,IF(AND(Q24>=600000,Q24<1100000),54000+(Q24-600000)*15%,IF(AND(Q24>=1100000,Q24<1600000),129000+(Q24-1100000)*19%,IF(AND(Q24>=1600000,Q24<3200000),224000+(Q24-1600000)*21%,560000+(Q24-3200000)*24%))))))) -> 13820.8 | S24: =R24/12 -> 1151.7333 | T24: =G24 -> 12 | U24: =+S24*T24 -> 13820.8
A25: 22 | B25: N-4409529 | C25: Olorunsina | D25: Kemi | F25: Cashier | G25: 12 | H25: 480000 | I25: 145600 | J25: 100 | K25: 10192 | M25: =H25 -> 480000 | N25: =M25*0.08 -> 38400 | O25: =M25-N25 -> 441600 | P25: =IF(O25<=300000,0,IF(O25>=20000000,(O25*0.21),(O25*0.2)+200000)) -> 288320 | Q25: =+M25-P25-N25 -> 153280 | R25: =IF(P25=0,(M25*0.01),IF(Q25<=0,0.01*M25,IF(AND(Q25>0,Q25<=300000),Q25*7%,IF(AND(Q25>=300000,Q25<600000),21000+(Q25-300000)*11%,IF(AND(Q25>=600000,Q25<1100000),54000+(Q25-600000)*15%,IF(AND(Q25>=1100000,Q25<1600000),129000+(Q25-1100000)*19%,IF(AND(Q25>=1600000,Q25<3200000),224000+(Q25-1600000)*21%,560000+(Q25-3200000)*24%))))))) -> 10729.6 | S25: =R25/12 -> 894.13333 | T25: =G25 -> 12 | U25: =+S25*T25 -> 10729.6
A26: 23 | B26: N-4410880 | C26: Moshood | D26: Rasheed | F26: Maintainance | G26: 12 | H26: 420000 | I26: 102400 | J26: 100 | K26: 7168 | M26: =H26 -> 420000 | N26: =M26*0.08 -> 33600 | O26: =M26-N26 -> 386400 | P26: =IF(O26<=300000,0,IF(O26>=20000000,(O26*0.21),(O26*0.2)+200000)) -> 277280 | Q26: =+M26-P26-N26 -> 109120 | R26: =IF(P26=0,(M26*0.01),IF(Q26<=0,0.01*M26,IF(AND(Q26>0,Q26<=300000),Q26*7%,IF(AND(Q26>=300000,Q26<600000),21000+(Q26-300000)*11%,IF(AND(Q26>=600000,Q26<1100000),54000+(Q26-600000)*15%,IF(AND(Q26>=1100000,Q26<1600000),129000+(Q26-1100000)*19%,IF(AND(Q26>=1600000,Q26<3200000),224000+(Q26-1600000)*21%,560000+(Q26-3200000)*24%))))))) -> 7638.4 | S26: =R26/12 -> 636.53333 | T26: =G26 -> 12 | U26: =+S26*T26 -> 7638.4
A27: 24 | B27: N-4411214 | C27: Babalola | D27: omolara | E27: A | F27: Cashier | G27: 12 | H27: 480000 | I27: 145600 | J27: 100 | K27: 10192 | M27: =H27 -> 480000 | N27: =M27*0.08 -> 38400 | O27: =M27-N27 -> 441600 | P27: =IF(O27<=300000,0,IF(O27>=20000000,(O27*0.21),(O27*0.2)+200000)) -> 288320 | Q27: =+M27-P27-N27 -> 153280 | R27: =IF(P27=0,(M27*0.01),IF(Q27<=0,0.01*M27,IF(AND(Q27>0,Q27<=300000),Q27*7%,IF(AND(Q27>=300000,Q27<600000),21000+(Q27-300000)*11%,IF(AND(Q27>=600000,Q27<1100000),54000+(Q27-600000)*15%,IF(AND(Q27>=1100000,Q27<1600000),129000+(Q27-1100000)*19%,IF(AND(Q27>=1600000,Q27<3200000),224000+(Q27-1600000)*21%,560000+(Q27-3200000)*24%))))))) -> 10729.6 | S27: =R27/12 -> 894.13333 | T27: =G27 -> 12 | U27: =+S27*T27 -> 10729.6
A28: 25 | B28: N-4421971 | C28: Ehiagwina | D28: E. | E28: Peter | F28: Manager | G28: 12 | H28: 660000 | I28: 275200 | J28: 100 | K28: 19264 | M28: =H28 -> 660000 | N28: =M28*0.08 -> 52800 | O28: =M28-N28 -> 607200 | P28: =IF(O28<=300000,0,IF(O28>=20000000,(O28*0.21),(O28*0.2)+200000)) -> 321440 | Q28: =+M28-P28-N28 -> 285760 | R28: =IF(P28=0,(M28*0.01),IF(Q28<=0,0.01*M28,IF(AND(Q28>0,Q28<=300000),Q28*7%,IF(AND(Q28>=300000,Q28<600000),21000+(Q28-300000)*11%,IF(AND(Q28>=600000,Q28<1100000),54000+(Q28-600000)*15%,IF(AND(Q28>=1100000,Q28<1600000),129000+(Q28-1100000)*19%,IF(AND(Q28>=1600000,Q28<3200000),224000+(Q28-1600000)*21%,560000+(Q28-3200000)*24%))))))) -> 20003.2 | S28: =R28/12 -> 1666.9333 | T28: =G28 -> 12 | U28: =+S28*T28 -> 20003.2
A29: 26 | B29: N-4423754 | C29: Oduyebo | D29: Samuel | F29: Manager | G29: 12 | H29: 540000 | I29: 188800 | J29: 100 | K29: 13216 | M29: =H29 -> 540000 | N29: =M29*0.08 -> 43200 | O29: =M29-N29 -> 496800 | P29: =IF(O29<=300000,0,IF(O29>=20000000,(O29*0.21),(O29*0.2)+200000)) -> 299360 | Q29: =+M29-P29-N29 -> 197440 | R29: =IF(P29=0,(M29*0.01),IF(Q29<=0,0.01*M29,IF(AND(Q29>0,Q29<=300000),Q29*7%,IF(AND(Q29>=300000,Q29<600000),21000+(Q29-300000)*11%,IF(AND(Q29>=600000,Q29<1100000),54000+(Q29-600000)*15%,IF(AND(Q29>=1100000,Q29<1600000),129000+(Q29-1100000)*19%,IF(AND(Q29>=1600000,Q29<3200000),224000+(Q29-1600000)*21%,560000+(Q29-3200000)*24%))))))) -> 13820.8 | S29: =R29/12 -> 1151.7333 | T29: =G29 -> 12 | U29: =+S29*T29 -> 13820.8
A30: 27 | B30: N-4443819 | C30: Ndukuba | D30: Uzoamaka | F30: Logistics Assistant 1 | G30: 12 | H30: 540000 | I30: 188800 | J30: 100 | K30: 13216 | M30: =H30 -> 540000 | N30: =M30*0.08 -> 43200 | O30: =M30-N30 -> 496800 | P30: =IF(O30<=300000,0,IF(O30>=20000000,(O30*0.21),(O30*0.2)+200000)) -> 299360 | Q30: =+M30-P30-N30 -> 197440 | R30: =IF(P30=0,(M30*0.01),IF(Q30<=0,0.01*M30,IF(AND(Q30>0,Q30<=300000),Q30*7%,IF(AND(Q30>=300000,Q30<600000),21000+(Q30-300000)*11%,IF(AND(Q30>=600000,Q30<1100000),54000+(Q30-600000)*15%,IF(AND(Q30>=1100000,Q30<1600000),129000+(Q30-1100000)*19%,IF(AND(Q30>=1600000,Q30<3200000),224000+(Q30-1600000)*21%,560000+(Q30-3200000)*24%))))))) -> 13820.8 | S30: =R30/12 -> 1151.7333 | T30: =G30 -> 12 | U30: =+S30*T30 -> 13820.8
A31: 28 | B31: N-4443831 | C31: Ajayi | D31: Olasunkanmi | E31: Tunde | F31: Purchase Assistant | G31: 12 | H31: 960000 | I31: 491200 | J31: 100 | K31: 42032 | M31: =H31 -> 960000 | N31: =M31*0.08 -> 76800 | O31: =M31-N31 -> 883200 | P31: =IF(O31<=300000,0,IF(O31>=20000000,(O31*0.21),(O31*0.2)+200000)) -> 376640 | Q31: =+M31-P31-N31 -> 506560 | R31: =IF(P31=0,(M31*0.01),IF(Q31<=0,0.01*M31,IF(AND(Q31>0,Q31<=300000),Q31*7%,IF(AND(Q31>=300000,Q31<600000),21000+(Q31-300000)*11%,IF(AND(Q31>=600000,Q31<1100000),54000+(Q31-600000)*15%,IF(AND(Q31>=1100000,Q31<1600000),129000+(Q31-1100000)*19%,IF(AND(Q31>=1600000,Q31<3200000),224000+(Q31-1600000)*21%,560000+(Q31-3200000)*24%))))))) -> 43721.6 | S31: =R31/12 -> 3643.4667 | T31: =G31 -> 12 | U31: =+S31*T31 -> 43721.6
A32: 29 | B32: N-4443874 | C32: Jolayemi | D32: Solomon | E32: Oluwaseun | F32: Instock & Transfer | G32: 12 | H32: 660000 | I32: 275200 | J32: 100 | K32: 19264 | M32: =H32 -> 660000 | N32: =M32*0.08 -> 52800 | O32: =M32-N32 -> 607200 | P32: =IF(O32<=300000,0,IF(O32>=20000000,(O32*0.21),(O32*0.2)+200000)) -> 321440 | Q32: =+M32-P32-N32 -> 285760 | R32: =IF(P32=0,(M32*0.01),IF(Q32<=0,0.01*M32,IF(AND(Q32>0,Q32<=300000),Q32*7%,IF(AND(Q32>=300000,Q32<600000),21000+(Q32-300000)*11%,IF(AND(Q32>=600000,Q32<1100000),54000+(Q32-600000)*15%,IF(AND(Q32>=1100000,Q32<1600000),129000+(Q32-1100000)*19%,IF(AND(Q32>=1600000,Q32<3200000),224000+(Q32-1600000)*21%,560000+(Q32-3200000)*24%))))))) -> 20003.2 | S32: =R32/12 -> 1666.9333 | T32: =G32 -> 12 | U32: =+S32*T32 -> 20003.2
A33: 30 | B33: N-4444058 | C33: Okpeahior | D33: Foster | F33: Accessory & Transfer | G33: 12 | H33: 660000 | I33: 275200 | J33: 100 | K33: 19264 | M33: =H33 -> 660000 | N33: =M33*0.08 -> 52800 | O33: =M33-N33 -> 607200 | P33: =IF(O33<=300000,0,IF(O33>=20000000,(O33*0.21),(O33*0.2)+200000)) -> 321440 | Q33: =+M33-P33-N33 -> 285760 | R33: =IF(P33=0,(M33*0.01),IF(Q33<=0,0.01*M33,IF(AND(Q33>0,Q33<=300000),Q33*7%,IF(AND(Q33>=300000,Q33<600000),21000+(Q33-300000)*11%,IF(AND(Q33>=600000,Q33<1100000),54000+(Q33-600000)*15%,IF(AND(Q33>=1100000,Q33<1600000),129000+(Q33-1100000)*19%,IF(AND(Q33>=1600000,Q33<3200000),224000+(Q33-1600000)*21%,560000+(Q33-3200000)*24%))))))) -> 20003.2 | S33: =R33/12 -> 1666.9333 | T33: =G33 -> 12 | U33: =+S33*T33 -> 20003.2
A34: 31 | B34: N-4444065 | C34: Alongo | D34: Babatunde | F34: Maintainance | G34: 12 | H34: 420000 | I34: 102400 | J34: 100 | K34: 7168 | M34: =H34 -> 420000 | N34: =M34*0.08 -> 33600 | O34: =M34-N34 -> 386400 | P34: =IF(O34<=300000,0,IF(O34>=20000000,(O34*0.21),(O34*0.2)+200000)) -> 277280 | Q34: =+M34-P34-N34 -> 109120 | R34: =IF(P34=0,(M34*0.01),IF(Q34<=0,0.01*M34,IF(AND(Q34>0,Q34<=300000),Q34*7%,IF(AND(Q34>=300000,Q34<600000),21000+(Q34-300000)*11%,IF(AND(Q34>=600000,Q34<1100000),54000+(Q34-600000)*15%,IF(AND(Q34>=1100000,Q34<1600000),129000+(Q34-1100000)*19%,IF(AND(Q34>=1600000,Q34<3200000),224000+(Q34-1600000)*21%,560000+(Q34-3200000)*24%))))))) -> 7638.4 | S34: =R34/12 -> 636.53333 | T34: =G34 -> 12 | U34: =+S34*T34 -> 7638.4
A35: 32 | B35: N-4525256 | C35: Gbamire | D35: Sunday | F35: Decoration officer | G35: 12 | H35: 600000 | I35: 232000 | J35: 100 | K35: 16240 | M35: =H35 -> 600000 | N35: =M35*0.08 -> 48000 | O35: =M35-N35 -> 552000 | P35: =IF(O35<=300000,0,IF(O35>=20000000,(O35*0.21),(O35*0.2)+200000)) -> 310400 | Q35: =+M35-P35-N35 -> 241600 | R35: =IF(P35=0,(M35*0.01),IF(Q35<=0,0.01*M35,IF(AND(Q35>0,Q35<=300000),Q35*7%,IF(AND(Q35>=300000,Q35<600000),21000+(Q35-300000)*11%,IF(AND(Q35>=600000,Q35<1100000),54000+(Q35-600000)*15%,IF(AND(Q35>=1100000,Q35<1600000),129000+(Q35-1100000)*19%,IF(AND(Q35>=1600000,Q35<3200000),224000+(Q35-1600000)*21%,560000+(Q35-3200000)*24%))))))) -> 16912 | S35: =R35/12 -> 1409.3333 | T35: =G35 -> 12 | U35: =+S35*T35 -> 16912
A36: 33 | B36: N-5351453 | C36: Aregbesola | D36: Joshua | F36: Transfer Assistant | G36: 12 | H36: 660000 | I36: 275200 | J36: 100 | K36: 19264 | M36: =H36 -> 660000 | N36: =M36*0.08 -> 52800 | O36: =M36-N36 -> 607200 | P36: =IF(O36<=300000,0,IF(O36>=20000000,(O36*0.21),(O36*0.2)+200000)) -> 321440 | Q36: =+M36-P36-N36 -> 285760 | R36: =IF(P36=0,(M36*0.01),IF(Q36<=0,0.01*M36,IF(AND(Q36>0,Q36<=300000),Q36*7%,IF(AND(Q36>=300000,Q36<600000),21000+(Q36-300000)*11%,IF(AND(Q36>=600000,Q36<1100000),54000+(Q36-600000)*15%,IF(AND(Q36>=1100000,Q36<1600000),129000+(Q36-1100000)*19%,IF(AND(Q36>=1600000,Q36<3200000),224000+(Q36-1600000)*21%,560000+(Q36-3200000)*24%))))))) -> 20003.2 | S36: =R36/12 -> 1666.9333 | T36: =G36 -> 12 | U36: =+S36*T36 -> 20003.2
A37: 34 | B37: N-5358663 | C37: Onayemi | D37: Olatunde | E37: Olalekan | F37: Regional Manager | G37: 12 | H37: 960000 | I37: 491200 | J37: 100 | K37: 42032 | M37: =H37 -> 960000 | N37: =M37*0.08 -> 76800 | O37: =M37-N37 -> 883200 | P37: =IF(O37<=300000,0,IF(O37>=20000000,(O37*0.21),(O37*0.2)+200000)) -> 376640 | Q37: =+M37-P37-N37 -> 506560 | R37: =IF(P37=0,(M37*0.01),IF(Q37<=0,0.01*M37,IF(AND(Q37>0,Q37<=300000),Q37*7%,IF(AND(Q37>=300000,Q37<600000),21000+(Q37-300000)*11%,IF(AND(Q37>=600000,Q37<1100000),54000+(Q37-600000)*15%,IF(AND(Q37>=1100000,Q37<1600000),129000+(Q37-1100000)*19%,IF(AND(Q37>=1600000,Q37<3200000),224000+(Q37-1600000)*21%,560000+(Q37-3200000)*24%))))))) -> 43721.6 | S37: =R37/12 -> 3643.4667 | T37: =G37 -> 12 | U37: =+S37*T37 -> 43721.6
A38: 35 | B38: N-5358807 | C38: Ifeanyi | D38: Osuji | E38: Franklin | F38: Store Supervisor | G38: 12 | H38: 540000 | I38: 188800 | J38: 100 | K38: 13216 | M38: =H38 -> 540000 | N38: =M38*0.08 -> 43200 | O38: =M38-N38 -> 496800 | P38: =IF(O38<=300000,0,IF(O38>=20000000,(O38*0.21),(O38*0.2)+200000)) -> 299360 | Q38: =+M38-P38-N38 -> 197440 | R38: =IF(P38=0,(M38*0.01),IF(Q38<=0,0.01*M38,IF(AND(Q38>0,Q38<=300000),Q38*7%,IF(AND(Q38>=300000,Q38<600000),21000+(Q38-300000)*11%,IF(AND(Q38>=600000,Q38<1100000),54000+(Q38-600000)*15%,IF(AND(Q38>=1100000,Q38<1600000),129000+(Q38-1100000)*19%,IF(AND(Q38>=1600000,Q38<3200000),224000+(Q38-1600000)*21%,560000+(Q38-3200000)*24%))))))) -> 13820.8 | S38: =R38/12 -> 1151.7333 | T38: =G38 -> 12 | U38: =+S38*T38 -> 13820.8
A39: 36 | B39: N-5359619 | C39: Gloria | D39: Awele | E39: Okonmah | F39: Manager | G39: 12 | H39: 540000 | I39: 188800 | J39: 100 | K39: 13216 | M39: =H39 -> 540000 | N39: =M39*0.08 -> 43200 | O39: =M39-N39 -> 496800 | P39: =IF(O39<=300000,0,IF(O39>=20000000,(O39*0.21),(O39*0.2)+200000)) -> 299360 | Q39: =+M39-P39-N39 -> 197440 | R39: =IF(P39=0,(M39*0.01),IF(Q39<=0,0.01*M39,IF(AND(Q39>0,Q39<=300000),Q39*7%,IF(AND(Q39>=300000,Q39<600000),21000+(Q39-300000)*11%,IF(AND(Q39>=600000,Q39<1100000),54000+(Q39-600000)*15%,IF(AND(Q39>=1100000,Q39<1600000),129000+(Q39-1100000)*19%,IF(AND(Q39>=1600000,Q39<3200000),224000+(Q39-1600000)*21%,560000+(Q39-3200000)*24%))))))) -> 13820.8 | S39: =R39/12 -> 1151.7333 | T39: =G39 -> 12 | U39: =+S39*T39 -> 13820.8
A40: 37 | B40: N-5361699 | C40: Adewunmi | D40: Ayomi | E40: Tunde | F40: Store Supervisor | G40: 12 | H40: 540000 | I40: 188800 | J40: 100 | K40: 13216 | M40: =H40 -> 540000 | N40: =M40*0.08 -> 43200 | O40: =M40-N40 -> 496800 | P40: =IF(O40<=300000,0,IF(O40>=20000000,(O40*0.21),(O40*0.2)+200000)) -> 299360 | Q40: =+M40-P40-N40 -> 197440 | R40: =IF(P40=0,(M40*0.01),IF(Q40<=0,0.01*M40,IF(AND(Q40>0,Q40<=300000),Q40*7%,IF(AND(Q40>=300000,Q40<600000),21000+(Q40-300000)*11%,IF(AND(Q40>=600000,Q40<1100000),54000+(Q40-600000)*15%,IF(AND(Q40>=1100000,Q40<1600000),129000+(Q40-1100000)*19%,IF(AND(Q40>=1600000,Q40<3200000),224000+(Q40-1600000)*21%,560000+(Q40-3200000)*24%))))))) -> 13820.8 | S40: =R40/12 -> 1151.7333 | T40: =G40 -> 12 | U40: =+S40*T40 -> 13820.8
A41: 38 | B41: N-5361861 | C41: ALICE | D41: GLORIA | E41: IDOBOGBE | F41: Cashier | G41: 12 | H41: 480000 | I41: 145600 | J41: 100 | K41: 10192 | M41: =H41 -> 480000 | N41: =M41*0.08 -> 38400 | O41: =M41-N41 -> 441600 | P41: =IF(O41<=300000,0,IF(O41>=20000000,(O41*0.21),(O41*0.2)+200000)) -> 288320 | Q41: =+M41-P41-N41 -> 153280 | R41: =IF(P41=0,(M41*0.01),IF(Q41<=0,0.01*M41,IF(AND(Q41>0,Q41<=300000),Q41*7%,IF(AND(Q41>=300000,Q41<600000),21000+(Q41-300000)*11%,IF(AND(Q41>=600000,Q41<1100000),54000+(Q41-600000)*15%,IF(AND(Q41>=1100000,Q41<1600000),129000+(Q41-1100000)*19%,IF(AND(Q41>=1600000,Q41<3200000),224000+(Q41-1600000)*21%,560000+(Q41-3200000)*24%))))))) -> 10729.6 | S41: =R41/12 -> 894.13333 | T41: =G41 -> 12 | U41: =+S41*T41 -> 10729.6
A42: 39 | B42: N-5362749 | C42: Iwalokun | D42: oluwatobi | F42: Cashier | G42: 12 | H42: 480000 | I42: 145600 | J42: 100 | K42: 10192 | M42: =H42 -> 480000 | N42: =M42*0.08 -> 38400 | O42: =M42-N42 -> 441600 | P42: =IF(O42<=300000,0,IF(O42>=20000000,(O42*0.21),(O42*0.2)+200000)) -> 288320 | Q42: =+M42-P42-N42 -> 153280 | R42: =IF(P42=0,(M42*0.01),IF(Q42<=0,0.01*M42,IF(AND(Q42>0,Q42<=300000),Q42*7%,IF(AND(Q42>=300000,Q42<600000),21000+(Q42-300000)*11%,IF(AND(Q42>=600000,Q42<1100000),54000+(Q42-600000)*15%,IF(AND(Q42>=1100000,Q42<1600000),129000+(Q42-1100000)*19%,IF(AND(Q42>=1600000,Q42<3200000),224000+(Q42-1600000)*21%,560000+(Q42-3200000)*24%))))))) -> 10729.6 | S42: =R42/12 -> 894.13333 | T42: =G42 -> 12 | U42: =+S42*T42 -> 10729.6
A43: 40 | B43: N-5374604 | C43: Olawuyi | D43: Damilola | F43: Electronics FSM | G43: 12 | H43: 420000 | I43: 102400 | J43: 100 | K43: 7168 | M43: =H43 -> 420000 | N43: =M43*0.08 -> 33600 | O43: =M43-N43 -> 386400 | P43: =IF(O43<=300000,0,IF(O43>=20000000,(O43*0.21),(O43*0.2)+200000)) -> 277280 | Q43: =+M43-P43-N43 -> 109120 | R43: =IF(P43=0,(M43*0.01),IF(Q43<=0,0.01*M43,IF(AND(Q43>0,Q43<=300000),Q43*7%,IF(AND(Q43>=300000,Q43<600000),21000+(Q43-300000)*11%,IF(AND(Q43>=600000,Q43<1100000),54000+(Q43-600000)*15%,IF(AND(Q43>=1100000,Q43<1600000),129000+(Q43-1100000)*19%,IF(AND(Q43>=1600000,Q43<3200000),224000+(Q43-1600000)*21%,560000+(Q43-3200000)*24%))))))) -> 7638.4 | S43: =R43/12 -> 636.53333 | T43: =G43 -> 12 | U43: =+S43*T43 -> 7638.4
A44: 41 | B44: N-5374794 | C44: Okparaku | D44: Chinonso | F44: Maintenance Assistant | G44: 12 | H44: 420000 | I44: 102400 | J44: 100 | K44: 7168 | M44: =H44 -> 420000 | N44: =M44*0.08 -> 33600 | O44: =M44-N44 -> 386400 | P44: =IF(O44<=300000,0,IF(O44>=20000000,(O44*0.21),(O44*0.2)+200000)) -> 277280 | Q44: =+M44-P44-N44 -> 109120 | R44: =IF(P44=0,(M44*0.01),IF(Q44<=0,0.01*M44,IF(AND(Q44>0,Q44<=300000),Q44*7%,IF(AND(Q44>=300000,Q44<600000),21000+(Q44-300000)*11%,IF(AND(Q44>=600000,Q44<1100000),54000+(Q44-600000)*15%,IF(AND(Q44>=1100000,Q44<1600000),129000+(Q44-1100000)*19%,IF(AND(Q44>=1600000,Q44<3200000),224000+(Q44-1600000)*21%,560000+(Q44-3200000)*24%))))))) -> 7638.4 | S44: =R44/12 -> 636.53333 | T44: =G44 -> 12 | U44: =+S44*T44 -> 7638.4
A45: 42 | B45: N-5375221 | C45: Odeyemi | D45: Grace. | E45: K. | F45: Cashier | G45: 12 | H45: 480000 | I45: 145600 | J45: 100 | K45: 10192 | M45: =H45 -> 480000 | N45: =M45*0.08 -> 38400 | O45: =M45-N45 -> 441600 | P45: =IF(O45<=300000,0,IF(O45>=20000000,(O45*0.21),(O45*0.2)+200000)) -> 288320 | Q45: =+M45-P45-N45 -> 153280 | R45: =IF(P45=0,(M45*0.01),IF(Q45<=0,0.01*M45,IF(AND(Q45>0,Q45<=300000),Q45*7%,IF(AND(Q45>=300000,Q45<600000),21000+(Q45-300000)*11%,IF(AND(Q45>=600000,Q45<1100000),54000+(Q45-600000)*15%,IF(AND(Q45>=1100000,Q45<1600000),129000+(Q45-1100000)*19%,IF(AND(Q45>=1600000,Q45<3200000),224000+(Q45-1600000)*21%,560000+(Q45-3200000)*24%))))))) -> 10729.6 | S45: =R45/12 -> 894.13333 | T45: =G45 -> 12 | U45: =+S45*T45 -> 10729.6
A46: 43 | B46: N-5378640 | C46: Sanni | D46: Oluwatoyin | F46: Franchise Officer-general | G46: 12 | H46: 480000 | I46: 145600 | J46: 100 | K46: 10192 | M46: =H46 -> 480000 | N46: =M46*0.08 -> 38400 | O46: =M46-N46 -> 441600 | P46: =IF(O46<=300000,0,IF(O46>=20000000,(O46*0.21),(O46*0.2)+200000)) -> 288320 | Q46: =+M46-P46-N46 -> 153280 | R46: =IF(P46=0,(M46*0.01),IF(Q46<=0,0.01*M46,IF(AND(Q46>0,Q46<=300000),Q46*7%,IF(AND(Q46>=300000,Q46<600000),21000+(Q46-300000)*11%,IF(AND(Q46>=600000,Q46<1100000),54000+(Q46-600000)*15%,IF(AND(Q46>=1100000,Q46<1600000),129000+(Q46-1100000)*19%,IF(AND(Q46>=1600000,Q46<3200000),224000+(Q46-1600000)*21%,560000+(Q46-3200000)*24%))))))) -> 10729.6 | S46: =R46/12 -> 894.13333 | T46: =G46 -> 12 | U46: =+S46*T46 -> 10729.6
A47: 44 | B47: N-5378662 | C47: Oguntola | D47: Tunji | F47: Store Management | G47: 12 | H47: 600000 | I47: 232000 | J47: 100 | K47: 16240 | M47: =H47 -> 600000 | N47: =M47*0.08 -> 48000 | O47: =M47-N47 -> 552000 | P47: =IF(O47<=300000,0,IF(O47>=20000000,(O47*0.21),(O47*0.2)+200000)) -> 310400 | Q47: =+M47-P47-N47 -> 241600 | R47: =IF(P47=0,(M47*0.01),IF(Q47<=0,0.01*M47,IF(AND(Q47>0,Q47<=300000),Q47*7%,IF(AND(Q47>=300000,Q47<600000),21000+(Q47-300000)*11%,IF(AND(Q47>=600000,Q47<1100000),54000+(Q47-600000)*15%,IF(AND(Q47>=1100000,Q47<1600000),129000+(Q47-1100000)*19%,IF(AND(Q47>=1600000,Q47<3200000),224000+(Q47-1600000)*21%,560000+(Q47-3200000)*24%))))))) -> 16912 | S47: =R47/12 -> 1409.3333 | T47: =G47 -> 12 | U47: =+S47*T47 -> 16912
A48: 45 | B48: N-5381851 | C48: Adegbite | D48: Fatai | F48: Store Supervisor | G48: 12 | H48: 540000 | I48: 188800 | J48: 100 | K48: 13216 | M48: =H48 -> 540000 | N48: =M48*0.08 -> 43200 | O48: =M48-N48 -> 496800 | P48: =IF(O48<=300000,0,IF(O48>=20000000,(O48*0.21),(O48*0.2)+200000)) -> 299360 | Q48: =+M48-P48-N48 -> 197440 | R48: =IF(P48=0,(M48*0.01),IF(Q48<=0,0.01*M48,IF(AND(Q48>0,Q48<=300000),Q48*7%,IF(AND(Q48>=300000,Q48<600000),21000+(Q48-300000)*11%,IF(AND(Q48>=600000,Q48<1100000),54000+(Q48-600000)*15%,IF(AND(Q48>=1100000,Q48<1600000),129000+(Q48-1100000)*19%,IF(AND(Q48>=1600000,Q48<3200000),224000+(Q48-1600000)*21%,560000+(Q48-3200000)*24%))))))) -> 13820.8 | S48: =R48/12 -> 1151.7333 | T48: =G48 -> 12 | U48: =+S48*T48 -> 13820.8
A49: 46 | B49: N-5382358 | C49: Dairo | D49: Gloria | E49: Temitope | F49: Manager | G49: 12 | H49: 540000 | I49: 188800 | J49: 100 | K49: 13216 | M49: =H49 -> 540000 | N49: =M49*0.08 -> 43200 | O49: =M49-N49 -> 496800 | P49: =IF(O49<=300000,0,IF(O49>=20000000,(O49*0.21),(O49*0.2)+200000)) -> 299360 | Q49: =+M49-P49-N49 -> 197440 | R49: =IF(P49=0,(M49*0.01),IF(Q49<=0,0.01*M49,IF(AND(Q49>0,Q49<=300000),Q49*7%,IF(AND(Q49>=300000,Q49<600000),21000+(Q49-300000)*11%,IF(AND(Q49>=600000,Q49<1100000),54000+(Q49-600000)*15%,IF(AND(Q49>=1100000,Q49<1600000),129000+(Q49-1100000)*19%,IF(AND(Q49>=1600000,Q49<3200000),224000+(Q49-1600000)*21%,560000+(Q49-3200000)*24%))))))) -> 13820.8 | S49: =R49/12 -> 1151.7333 | T49: =G49 -> 12 | U49: =+S49*T49 -> 13820.8
A50: 47 | B50: N-5382387 | C50: Njoku | D50: Doris | E50: Oluchi | F50: HR | G50: 12 | H50: 1560000 | I50: 923200 | J50: 100 | K50: 102480 | M50: =H50 -> 1560000 | N50: =M50*0.08 -> 124800 | O50: =M50-N50 -> 1435200 | P50: =IF(O50<=300000,0,IF(O50>=20000000,(O50*0.21),(O50*0.2)+200000)) -> 487040 | Q50: =+M50-P50-N50 -> 948160 | R50: =IF(P50=0,(M50*0.01),IF(Q50<=0,0.01*M50,IF(AND(Q50>0,Q50<=300000),Q50*7%,IF(AND(Q50>=300000,Q50<600000),21000+(Q50-300000)*11%,IF(AND(Q50>=600000,Q50<1100000),54000+(Q50-600000)*15%,IF(AND(Q50>=1100000,Q50<1600000),129000+(Q50-1100000)*19%,IF(AND(Q50>=1600000,Q50<3200000),224000+(Q50-1600000)*21%,560000+(Q50-3200000)*24%))))))) -> 106224 | S50: =R50/12 -> 8852 | T50: =G50 -> 12 | U50: =+S50*T50 -> 106224
A51: 48 | B51: N-5392329 | C51: Ogungboye | D51: Bukola | E51: Ganiyat | F51: Store Supervisor | G51: 12 | H51: 540000 | I51: 188800 | J51: 100 | K51: 13216 | M51: =H51 -> 540000 | N51: =M51*0.08 -> 43200 | O51: =M51-N51 -> 496800 | P51: =IF(O51<=300000,0,IF(O51>=20000000,(O51*0.21),(O51*0.2)+200000)) -> 299360 | Q51: =+M51-P51-N51 -> 197440 | R51: =IF(P51=0,(M51*0.01),IF(Q51<=0,0.01*M51,IF(AND(Q51>0,Q51<=300000),Q51*7%,IF(AND(Q51>=300000,Q51<600000),21000+(Q51-300000)*11%,IF(AND(Q51>=600000,Q51<1100000),54000+(Q51-600000)*15%,IF(AND(Q51>=1100000,Q51<1600000),129000+(Q51-1100000)*19%,IF(AND(Q51>=1600000,Q51<3200000),224000+(Q51-1600000)*21%,560000+(Q51-3200000)*24%))))))) -> 13820.8 | S51: =R51/12 -> 1151.7333 | T51: =G51 -> 12 | U51: =+S51*T51 -> 13820.8
A52: 49 | B52: N-5402513 | C52: Rafiu | D52: Abiola | E52: Sodiq | F52: Logistics Officer | G52: 12 | H52: 840000 | I52: 404800 | J52: 100 | K52: 32528 | M52: =H52 -> 840000 | N52: =M52*0.08 -> 67200 | O52: =M52-N52 -> 772800 | P52: =IF(O52<=300000,0,IF(O52>=20000000,(O52*0.21),(O52*0.2)+200000)) -> 354560 | Q52: =+M52-P52-N52 -> 418240 | R52: =IF(P52=0,(M52*0.01),IF(Q52<=0,0.01*M52,IF(AND(Q52>0,Q52<=300000),Q52*7%,IF(AND(Q52>=300000,Q52<600000),21000+(Q52-300000)*11%,IF(AND(Q52>=600000,Q52<1100000),54000+(Q52-600000)*15%,IF(AND(Q52>=1100000,Q52<1600000),129000+(Q52-1100000)*19%,IF(AND(Q52>=1600000,Q52<3200000),224000+(Q52-1600000)*21%,560000+(Q52-3200000)*24%))))))) -> 34006.4 | S52: =R52/12 -> 2833.8667 | T52: =G52 -> 12 | U52: =+S52*T52 -> 34006.4
A53: 50 | B53: N-5940920 | C53: Abdulkadir | D53: Idoko | E53: Haruna | F53: Regional Manager | G53: 12 | H53: 960000 | I53: 491200 | J53: 100 | K53: 42032 | M53: =H53 -> 960000 | N53: =M53*0.08 -> 76800 | O53: =M53-N53 -> 883200 | P53: =IF(O53<=300000,0,IF(O53>=20000000,(O53*0.21),(O53*0.2)+200000)) -> 376640 | Q53: =+M53-P53-N53 -> 506560 | R53: =IF(P53=0,(M53*0.01),IF(Q53<=0,0.01*M53,IF(AND(Q53>0,Q53<=300000),Q53*7%,IF(AND(Q53>=300000,Q53<600000),21000+(Q53-300000)*11%,IF(AND(Q53>=600000,Q53<1100000),54000+(Q53-600000)*15%,IF(AND(Q53>=1100000,Q53<1600000),129000+(Q53-1100000)*19%,IF(AND(Q53>=1600000,Q53<3200000),224000+(Q53-1600000)*21%,560000+(Q53-3200000)*24%))))))) -> 43721.6 | S53: =R53/12 -> 3643.4667 | T53: =G53 -> 12 | U53: =+S53*T53 -> 43721.6
A54: 51 | B54: N-6029271 | C54: Jonathan | D54: Yesufu | E54: Afekorioh | F54: Security Officer | G54: 12 | H54: 660000 | I54: 275200 | J54: 100 | K54: 19264 | M54: =H54 -> 660000 | N54: =M54*0.08 -> 52800 | O54: =M54-N54 -> 607200 | P54: =IF(O54<=300000,0,IF(O54>=20000000,(O54*0.21),(O54*0.2)+200000)) -> 321440 | Q54: =+M54-P54-N54 -> 285760 | R54: =IF(P54=0,(M54*0.01),IF(Q54<=0,0.01*M54,IF(AND(Q54>0,Q54<=300000),Q54*7%,IF(AND(Q54>=300000,Q54<600000),21000+(Q54-300000)*11%,IF(AND(Q54>=600000,Q54<1100000),54000+(Q54-600000)*15%,IF(AND(Q54>=1100000,Q54<1600000),129000+(Q54-1100000)*19%,IF(AND(Q54>=1600000,Q54<3200000),224000+(Q54-1600000)*21%,560000+(Q54-3200000)*24%))))))) -> 20003.2 | S54: =R54/12 -> 1666.9333 | T54: =G54 -> 12 | U54: =+S54*T54 -> 20003.2
A55: 52 | B55: N-6037119 | C55: Nwachukwu | D55: Wisdom | F55: Driver | G55: 12 | H55: 480000 | I55: 145600 | J55: 100 | K55: 10192 | M55: =H55 -> 480000 | N55: =M55*0.08 -> 38400 | O55: =M55-N55 -> 441600 | P55: =IF(O55<=300000,0,IF(O55>=20000000,(O55*0.21),(O55*0.2)+200000)) -> 288320 | Q55: =+M55-P55-N55 -> 153280 | R55: =IF(P55=0,(M55*0.01),IF(Q55<=0,0.01*M55,IF(AND(Q55>0,Q55<=300000),Q55*7%,IF(AND(Q55>=300000,Q55<600000),21000+(Q55-300000)*11%,IF(AND(Q55>=600000,Q55<1100000),54000+(Q55-600000)*15%,IF(AND(Q55>=1100000,Q55<1600000),129000+(Q55-1100000)*19%,IF(AND(Q55>=1600000,Q55<3200000),224000+(Q55-1600000)*21%,560000+(Q55-3200000)*24%))))))) -> 10729.6 | S55: =R55/12 -> 894.13333 | T55: =G55 -> 12 | U55: =+S55*T55 -> 10729.6
A56: 53 | B56: N-6110894 | C56: Vivian | D56: Duruzor | E56: Ugbe | F56: Cashier | G56: 12 | H56: 480000 | I56: 145600 | J56: 100 | K56: 10192 | M56: =H56 -> 480000 | N56: =M56*0.08 -> 38400 | O56: =M56-N56 -> 441600 | P56: =IF(O56<=300000,0,IF(O56>=20000000,(O56*0.21),(O56*0.2)+200000)) -> 288320 | Q56: =+M56-P56-N56 -> 153280 | R56: =IF(P56=0,(M56*0.01),IF(Q56<=0,0.01*M56,IF(AND(Q56>0,Q56<=300000),Q56*7%,IF(AND(Q56>=300000,Q56<600000),21000+(Q56-300000)*11%,IF(AND(Q56>=600000,Q56<1100000),54000+(Q56-600000)*15%,IF(AND(Q56>=1100000,Q56<1600000),129000+(Q56-1100000)*19%,IF(AND(Q56>=1600000,Q56<3200000),224000+(Q56-1600000)*21%,560000+(Q56-3200000)*24%))))))) -> 10729.6 | S56: =R56/12 -> 894.13333 | T56: =G56 -> 12 | U56: =+S56*T56 -> 10729.6
A57: 54 | B57: N-6714505 | C57: John | D57: Oreva | E57: Ikokide | F57: Manager | G57: 12 | H57: 540000 | I57: 188800 | J57: 100 | K57: 13216 | M57: =H57 -> 540000 | N57: =M57*0.08 -> 43200 | O57: =M57-N57 -> 496800 | P57: =IF(O57<=300000,0,IF(O57>=20000000,(O57*0.21),(O57*0.2)+200000)) -> 299360 | Q57: =+M57-P57-N57 -> 197440 | R57: =IF(P57=0,(M57*0.01),IF(Q57<=0,0.01*M57,IF(AND(Q57>0,Q57<=300000),Q57*7%,IF(AND(Q57>=300000,Q57<600000),21000+(Q57-300000)*11%,IF(AND(Q57>=600000,Q57<1100000),54000+(Q57-600000)*15%,IF(AND(Q57>=1100000,Q57<1600000),129000+(Q57-1100000)*19%,IF(AND(Q57>=1600000,Q57<3200000),224000+(Q57-1600000)*21%,560000+(Q57-3200000)*24%))))))) -> 13820.8 | S57: =R57/12 -> 1151.7333 | T57: =G57 -> 12 | U57: =+S57*T57 -> 13820.8
A58: 55 | B58: N-6816740 | C58: Emuze | D58: Smart | E58: Osas | F58: Data Analyst | G58: 12 | H58: 480000 | I58: 145600 | J58: 100 | K58: 10192 | M58: =H58 -> 480000 | N58: =M58*0.08 -> 38400 | O58: =M58-N58 -> 441600 | P58: =IF(O58<=300000,0,IF(O58>=20000000,(O58*0.21),(O58*0.2)+200000)) -> 288320 | Q58: =+M58-P58-N58 -> 153280 | R58: =IF(P58=0,(M58*0.01),IF(Q58<=0,0.01*M58,IF(AND(Q58>0,Q58<=300000),Q58*7%,IF(AND(Q58>=300000,Q58<600000),21000+(Q58-300000)*11%,IF(AND(Q58>=600000,Q58<1100000),54000+(Q58-600000)*15%,IF(AND(Q58>=1100000,Q58<1600000),129000+(Q58-1100000)*19%,IF(AND(Q58>=1600000,Q58<3200000),224000+(Q58-1600000)*21%,560000+(Q58-3200000)*24%))))))) -> 10729.6 | S58: =R58/12 -> 894.13333 | T58: =G58 -> 12 | U58: =+S58*T58 -> 10729.6
A59: 56 | B59: N-6930031 | C59: Otunuga | D59: Williams | F59: Purchase Assistant | G59: 12 | H59: 660000 | I59: 275200 | J59: 100 | K59: 19264 | M59: =H59 -> 660000 | N59: =M59*0.08 -> 52800 | O59: =M59-N59 -> 607200 | P59: =IF(O59<=300000,0,IF(O59>=20000000,(O59*0.21),(O59*0.2)+200000)) -> 321440 | Q59: =+M59-P59-N59 -> 285760 | R59: =IF(P59=0,(M59*0.01),IF(Q59<=0,0.01*M59,IF(AND(Q59>0,Q59<=300000),Q59*7%,IF(AND(Q59>=300000,Q59<600000),21000+(Q59-300000)*11%,IF(AND(Q59>=600000,Q59<1100000),54000+(Q59-600000)*15%,IF(AND(Q59>=1100000,Q59<1600000),129000+(Q59-1100000)*19%,IF(AND(Q59>=1600000,Q59<3200000),224000+(Q59-1600000)*21%,560000+(Q59-3200000)*24%))))))) -> 20003.2 | S59: =R59/12 -> 1666.9333 | T59: =G59 -> 12 | U59: =+S59*T59 -> 20003.2
A60: 57 | B60: N-7011328 | C60: Dada | D60: Israel | F60: Manager | G60: 12 | H60: 660000 | I60: 275200 | J60: 100 | K60: 19264 | M60: =H60 -> 660000 | N60: =M60*0.08 -> 52800 | O60: =M60-N60 -> 607200 | P60: =IF(O60<=300000,0,IF(O60>=20000000,(O60*0.21),(O60*0.2)+200000)) -> 321440 | Q60: =+M60-P60-N60 -> 285760 | R60: =IF(P60=0,(M60*0.01),IF(Q60<=0,0.01*M60,IF(AND(Q60>0,Q60<=300000),Q60*7%,IF(AND(Q60>=300000,Q60<600000),21000+(Q60-300000)*11%,IF(AND(Q60>=600000,Q60<1100000),54000+(Q60-600000)*15%,IF(AND(Q60>=1100000,Q60<1600000),129000+(Q60-1100000)*19%,IF(AND(Q60>=1600000,Q60<3200000),224000+(Q60-1600000)*21%,560000+(Q60-3200000)*24%))))))) -> 20003.2 | S60: =R60/12 -> 1666.9333 | T60: =G60 -> 12 | U60: =+S60*T60 -> 20003.2
A61: 58 | B61: N-7131566 | C61: Chidiebere | D61: Emeka | E61: .O. | F61: Maintainance | G61: 12 | H61: 420000 | I61: 102400 | J61: 100 | K61: 7168 | M61: =H61 -> 420000 | N61: =M61*0.08 -> 33600 | O61: =M61-N61 -> 386400 | P61: =IF(O61<=300000,0,IF(O61>=20000000,(O61*0.21),(O61*0.2)+200000)) -> 277280 | Q61: =+M61-P61-N61 -> 109120 | R61: =IF(P61=0,(M61*0.01),IF(Q61<=0,0.01*M61,IF(AND(Q61>0,Q61<=300000),Q61*7%,IF(AND(Q61>=300000,Q61<600000),21000+(Q61-300000)*11%,IF(AND(Q61>=600000,Q61<1100000),54000+(Q61-600000)*15%,IF(AND(Q61>=1100000,Q61<1600000),129000+(Q61-1100000)*19%,IF(AND(Q61>=1600000,Q61<3200000),224000+(Q61-1600000)*21%,560000+(Q61-3200000)*24%))))))) -> 7638.4 | S61: =R61/12 -> 636.53333 | T61: =G61 -> 12 | U61: =+S61*T61 -> 7638.4
A62: 59 | B62: N-7134048 | C62: Ajibola | D62: Rasaq | E62: Akin | F62: Aftersales Officer | G62: 12 | H62: 480000 | I62: 145600 | J62: 100 | K62: 10192 | M62: =H62 -> 480000 | N62: =M62*0.08 -> 38400 | O62: =M62-N62 -> 441600 | P62: =IF(O62<=300000,0,IF(O62>=20000000,(O62*0.21),(O62*0.2)+200000)) -> 288320 | Q62: =+M62-P62-N62 -> 153280 | R62: =IF(P62=0,(M62*0.01),IF(Q62<=0,0.01*M62,IF(AND(Q62>0,Q62<=300000),Q62*7%,IF(AND(Q62>=300000,Q62<600000),21000+(Q62-300000)*11%,IF(AND(Q62>=600000,Q62<1100000),54000+(Q62-600000)*15%,IF(AND(Q62>=1100000,Q62<1600000),129000+(Q62-1100000)*19%,IF(AND(Q62>=1600000,Q62<3200000),224000+(Q62-1600000)*21%,560000+(Q62-3200000)*24%))))))) -> 10729.6 | S62: =R62/12 -> 894.13333 | T62: =G62 -> 12 | U62: =+S62*T62 -> 10729.6
A63: 60 | B63: N-7398981 | C63: Victoria | D63: John | F63: Account officer | G63: 12 | H63: 660000 | I63: 275200 | J63: 100 | K63: 19264 | M63: =H63 -> 660000 | N63: =M63*0.08 -> 52800 | O63: =M63-N63 -> 607200 | P63: =IF(O63<=300000,0,IF(O63>=20000000,(O63*0.21),(O63*0.2)+200000)) -> 321440 | Q63: =+M63-P63-N63 -> 285760 | R63: =IF(P63=0,(M63*0.01),IF(Q63<=0,0.01*M63,IF(AND(Q63>0,Q63<=300000),Q63*7%,IF(AND(Q63>=300000,Q63<600000),21000+(Q63-300000)*11%,IF(AND(Q63>=600000,Q63<1100000),54000+(Q63-600000)*15%,IF(AND(Q63>=1100000,Q63<1600000),129000+(Q63-1100000)*19%,IF(AND(Q63>=1600000,Q63<3200000),224000+(Q63-1600000)*21%,560000+(Q63-3200000)*24%))))))) -> 20003.2 | S63: =R63/12 -> 1666.9333 | T63: =G63 -> 12 | U63: =+S63*T63 -> 20003.2
A64: 61 | B64: N-7464421 | C64: Taiwo | D64: Mathew | F64: Store Supervisor | G64: 12 | H64: 540000 | I64: 188800 | J64: 100 | K64: 13216 | M64: =H64 -> 540000 | N64: =M64*0.08 -> 43200 | O64: =M64-N64 -> 496800 | P64: =IF(O64<=300000,0,IF(O64>=20000000,(O64*0.21),(O64*0.2)+200000)) -> 299360 | Q64: =+M64-P64-N64 -> 197440 | R64: =IF(P64=0,(M64*0.01),IF(Q64<=0,0.01*M64,IF(AND(Q64>0,Q64<=300000),Q64*7%,IF(AND(Q64>=300000,Q64<600000),21000+(Q64-300000)*11%,IF(AND(Q64>=600000,Q64<1100000),54000+(Q64-600000)*15%,IF(AND(Q64>=1100000,Q64<1600000),129000+(Q64-1100000)*19%,IF(AND(Q64>=1600000,Q64<3200000),224000+(Q64-1600000)*21%,560000+(Q64-3200000)*24%))))))) -> 13820.8 | S64: =R64/12 -> 1151.7333 | T64: =G64 -> 12 | U64: =+S64*T64 -> 13820.8
A65: 62 | B65: N-7605586 | C65: Olasunkanmi | D65: Isaac | E65: Abiodun | F65: Manager | G65: 12 | H65: 540000 | I65: 188800 | J65: 100 | K65: 13216 | M65: =H65 -> 540000 | N65: =M65*0.08 -> 43200 | O65: =M65-N65 -> 496800 | P65: =IF(O65<=300000,0,IF(O65>=20000000,(O65*0.21),(O65*0.2)+200000)) -> 299360 | Q65: =+M65-P65-N65 -> 197440 | R65: =IF(P65=0,(M65*0.01),IF(Q65<=0,0.01*M65,IF(AND(Q65>0,Q65<=300000),Q65*7%,IF(AND(Q65>=300000,Q65<600000),21000+(Q65-300000)*11%,IF(AND(Q65>=600000,Q65<1100000),54000+(Q65-600000)*15%,IF(AND(Q65>=1100000,Q65<1600000),129000+(Q65-1100000)*19%,IF(AND(Q65>=1600000,Q65<3200000),224000+(Q65-1600000)*21%,560000+(Q65-3200000)*24%))))))) -> 13820.8 | S65: =R65/12 -> 1151.7333 | T65: =G65 -> 12 | U65: =+S65*T65 -> 13820.8
A66: 63 | B66: N- 4090287 | C66: Adeola | D66: A.Openaike | F66: Material Officer | G66: 12 | H66: 540000 | I66: 188800 | J66: 100 | K66: 13216 | M66: =H66 -> 540000 | N66: =M66*0.08 -> 43200 | O66: =M66-N66 -> 496800 | P66: =IF(O66<=300000,0,IF(O66>=20000000,(O66*0.21),(O66*0.2)+200000)) -> 299360 | Q66: =+M66-P66-N66 -> 197440 | R66: =IF(P66=0,(M66*0.01),IF(Q66<=0,0.01*M66,IF(AND(Q66>0,Q66<=300000),Q66*7%,IF(AND(Q66>=300000,Q66<600000),21000+(Q66-300000)*11%,IF(AND(Q66>=600000,Q66<1100000),54000+(Q66-600000)*15%,IF(AND(Q66>=1100000,Q66<1600000),129000+(Q66-1100000)*19%,IF(AND(Q66>=1600000,Q66<3200000),224000+(Q66-1600000)*21%,560000+(Q66-3200000)*24%))))))) -> 13820.8 | S66: =R66/12 -> 1151.7333 | T66: =G66 -> 12 | U66: =+S66*T66 -> 13820.8
A67: 64 | B67: N-3826304 | C67: Banuso | D67: Michael | F67: Franchise Officer-general | G67: 12 | H67: 540000 | I67: 188800 | J67: 100 | K67: 13216 | M67: =H67 -> 540000 | N67: =M67*0.08 -> 43200 | O67: =M67-N67 -> 496800 | P67: =IF(O67<=300000,0,IF(O67>=20000000,(O67*0.21),(O67*0.2)+200000)) -> 299360 | Q67: =+M67-P67-N67 -> 197440 | R67: =IF(P67=0,(M67*0.01),IF(Q67<=0,0.01*M67,IF(AND(Q67>0,Q67<=300000),Q67*7%,IF(AND(Q67>=300000,Q67<600000),21000+(Q67-300000)*11%,IF(AND(Q67>=600000,Q67<1100000),54000+(Q67-600000)*15%,IF(AND(Q67>=1100000,Q67<1600000),129000+(Q67-1100000)*19%,IF(AND(Q67>=1600000,Q67<3200000),224000+(Q67-1600000)*21%,560000+(Q67-3200000)*24%))))))) -> 13820.8 | S67: =R67/12 -> 1151.7333 | T67: =G67 -> 12 | U67: =+S67*T67 -> 13820.8
A68: 65 | B68: N-3826304 | C68: Musbau | D68: Salam | F68: Project Manager | G68: 12 | H68: 1200000 | I68: 664000 | J68: 100 | K68: 63600 | M68: =H68 -> 1200000 | N68: =M68*0.08 -> 96000 | O68: =M68-N68 -> 1104000 | P68: =IF(O68<=300000,0,IF(O68>=20000000,(O68*0.21),(O68*0.2)+200000)) -> 420800 | Q68: =+M68-P68-N68 -> 683200 | R68: =IF(P68=0,(M68*0.01),IF(Q68<=0,0.01*M68,IF(AND(Q68>0,Q68<=300000),Q68*7%,IF(AND(Q68>=300000,Q68<600000),21000+(Q68-300000)*11%,IF(AND(Q68>=600000,Q68<1100000),54000+(Q68-600000)*15%,IF(AND(Q68>=1100000,Q68<1600000),129000+(Q68-1100000)*19%,IF(AND(Q68>=1600000,Q68<3200000),224000+(Q68-1600000)*21%,560000+(Q68-3200000)*24%))))))) -> 66480 | S68: =R68/12 -> 5540 | T68: =G68 -> 12 | U68: =+S68*T68 -> 66480
A69: 66 | B69: N-1199913 | C69: Adalemo | D69: Babatope | F69: Store Supervisor | G69: 12 | H69: 540000 | I69: 188800 | J69: 100 | K69: 13216 | M69: =H69 -> 540000 | N69: =M69*0.08 -> 43200 | O69: =M69-N69 -> 496800 | P69: =IF(O69<=300000,0,IF(O69>=20000000,(O69*0.21),(O69*0.2)+200000)) -> 299360 | Q69: =+M69-P69-N69 -> 197440 | R69: =IF(P69=0,(M69*0.01),IF(Q69<=0,0.01*M69,IF(AND(Q69>0,Q69<=300000),Q69*7%,IF(AND(Q69>=300000,Q69<600000),21000+(Q69-300000)*11%,IF(AND(Q69>=600000,Q69<1100000),54000+(Q69-600000)*15%,IF(AND(Q69>=1100000,Q69<1600000),129000+(Q69-1100000)*19%,IF(AND(Q69>=1600000,Q69<3200000),224000+(Q69-1600000)*21%,560000+(Q69-3200000)*24%))))))) -> 13820.8 | S69: =R69/12 -> 1151.7333 | T69: =G69 -> 12 | U69: =+S69*T69 -> 13820.8
A70: 67 | B70: N-797883 | C70: Alex | D70: Aleburu | F70: Maintainance | G70: 12 | H70: 420000 | I70: 102400 | J70: 100 | K70: 7168 | M70: =H70 -> 420000 | N70: =M70*0.08 -> 33600 | O70: =M70-N70 -> 386400 | P70: =IF(O70<=300000,0,IF(O70>=20000000,(O70*0.21),(O70*0.2)+200000)) -> 277280 | Q70: =+M70-P70-N70 -> 109120 | R70: =IF(P70=0,(M70*0.01),IF(Q70<=0,0.01*M70,IF(AND(Q70>0,Q70<=300000),Q70*7%,IF(AND(Q70>=300000,Q70<600000),21000+(Q70-300000)*11%,IF(AND(Q70>=600000,Q70<1100000),54000+(Q70-600000)*15%,IF(AND(Q70>=1100000,Q70<1600000),129000+(Q70-1100000)*19%,IF(AND(Q70>=1600000,Q70<3200000),224000+(Q70-1600000)*21%,560000+(Q70-3200000)*24%))))))) -> 7638.4 | S70: =R70/12 -> 636.53333 | T70: =G70 -> 12 | U70: =+S70*T70 -> 7638.4
A71: 68 | B71: N-5351595 | C71: Oyeniyi | D71: Samson | E71: Olayiwole | F71: Legal Adviser | G71: 12 | H71: 1800000 | I71: 1096000 | J71: 100 | K71: 128400 | M71: =I71 -> 1096000 | N71: =M71*0.08 -> 87680 | O71: =M71-N71 -> 1008320 | P71: =IF(O71<=300000,0,IF(O71>=20000000,(O71*0.21),(O71*0.2)+200000)) -> 401664 | Q71: =+M71-P71-N71 -> 606656 | R71: =IF(P71=0,(M71*0.01),IF(Q71<=0,0.01*M71,IF(AND(Q71>0,Q71<=300000),Q71*7%,IF(AND(Q71>=300000,Q71<600000),21000+(Q71-300000)*11%,IF(AND(Q71>=600000,Q71<1100000),54000+(Q71-600000)*15%,IF(AND(Q71>=1100000,Q71<1600000),129000+(Q71-1100000)*19%,IF(AND(Q71>=1600000,Q71<3200000),224000+(Q71-1600000)*21%,560000+(Q71-3200000)*24%))))))) -> 54998.4 | S71: =R71/12 -> 4583.2 | T71: =G71 -> 12 | U71: =+S71*T71 -> 54998.4
A72: 69 | B72: N-1221404 | C72: Adeboye | D72: Adewale | F72: Store keeper | G72: 12 | H72: 480000 | I72: 145600 | J72: 100 | K72: 10192 | M72: =H72 -> 480000 | N72: =M72*0.08 -> 38400 | O72: =M72-N72 -> 441600 | P72: =IF(O72<=300000,0,IF(O72>=20000000,(O72*0.21),(O72*0.2)+200000)) -> 288320 | Q72: =+M72-P72-N72 -> 153280 | R72: =IF(P72=0,(M72*0.01),IF(Q72<=0,0.01*M72,IF(AND(Q72>0,Q72<=300000),Q72*7%,IF(AND(Q72>=300000,Q72<600000),21000+(Q72-300000)*11%,IF(AND(Q72>=600000,Q72<1100000),54000+(Q72-600000)*15%,IF(AND(Q72>=1100000,Q72<1600000),129000+(Q72-1100000)*19%,IF(AND(Q72>=1600000,Q72<3200000),224000+(Q72-1600000)*21%,560000+(Q72-3200000)*24%))))))) -> 10729.6 | S72: =R72/12 -> 894.13333 | T72: =G72 -> 12 | U72: =+S72*T72 -> 10729.6
A73: 70 | B73: N-1199850 | C73: Adekunle | D73: David | F73: Store Supervisor | G73: 12 | H73: 540000 | I73: 188800 | J73: 100 | K73: 13216 | M73: =H73 -> 540000 | N73: =M73*0.08 -> 43200 | O73: =M73-N73 -> 496800 | P73: =IF(O73<=300000,0,IF(O73>=20000000,(O73*0.21),(O73*0.2)+200000)) -> 299360 | Q73: =+M73-P73-N73 -> 197440 | R73: =IF(P73=0,(M73*0.01),IF(Q73<=0,0.01*M73,IF(AND(Q73>0,Q73<=300000),Q73*7%,IF(AND(Q73>=300000,Q73<600000),21000+(Q73-300000)*11%,IF(AND(Q73>=600000,Q73<1100000),54000+(Q73-600000)*15%,IF(AND(Q73>=1100000,Q73<1600000),129000+(Q73-1100000)*19%,IF(AND(Q73>=1600000,Q73<3200000),224000+(Q73-1600000)*21%,560000+(Q73-3200000)*24%))))))) -> 13820.8 | S73: =R73/12 -> 1151.7333 | T73: =G73 -> 12 | U73: =+S73*T73 -> 13820.8
A74: 71 | B74: N-1198969 | C74: Adeleye | D74: Adeola | F74: Cashier | G74: 12 | H74: 480000 | I74: 145600 | J74: 100 | K74: 10192 | M74: =H74 -> 480000 | N74: =M74*0.08 -> 38400 | O74: =M74-N74 -> 441600 | P74: =IF(O74<=300000,0,IF(O74>=20000000,(O74*0.21),(O74*0.2)+200000)) -> 288320 | Q74: =+M74-P74-N74 -> 153280 | R74: =IF(P74=0,(M74*0.01),IF(Q74<=0,0.01*M74,IF(AND(Q74>0,Q74<=300000),Q74*7%,IF(AND(Q74>=300000,Q74<600000),21000+(Q74-300000)*11%,IF(AND(Q74>=600000,Q74<1100000),54000+(Q74-600000)*15%,IF(AND(Q74>=1100000,Q74<1600000),129000+(Q74-1100000)*19%,IF(AND(Q74>=1600000,Q74<3200000),224000+(Q74-1600000)*21%,560000+(Q74-3200000)*24%))))))) -> 10729.6 | S74: =R74/12 -> 894.13333 | T74: =G74 -> 12 | U74: =+S74*T74 -> 10729.6
A75: 72 | B75: N-1502391 | C75: Adeleye | D75: Kayode | E75: Daniel | F75: Accessories Manager | G75: 12 | H75: 1020000 | I75: 534400 | J75: 100 | K75: 46784 | M75: =H75 -> 1020000 | N75: =M75*0.08 -> 81600 | O75: =M75-N75 -> 938400 | P75: =IF(O75<=300000,0,IF(O75>=20000000,(O75*0.21),(O75*0.2)+200000)) -> 387680 | Q75: =+M75-P75-N75 -> 550720 | R75: =IF(P75=0,(M75*0.01),IF(Q75<=0,0.01*M75,IF(AND(Q75>0,Q75<=300000),Q75*7%,IF(AND(Q75>=300000,Q75<600000),21000+(Q75-300000)*11%,IF(AND(Q75>=600000,Q75<1100000),54000+(Q75-600000)*15%,IF(AND(Q75>=1100000,Q75<1600000),129000+(Q75-1100000)*19%,IF(AND(Q75>=1600000,Q75<3200000),224000+(Q75-1600000)*21%,560000+(Q75-3200000)*24%))))))) -> 48579.2 | S75: =R75/12 -> 4048.2667 | T75: =G75 -> 12 | U75: =+S75*T75 -> 48579.2
A76: 73 | B76: N-1679286 | C76: Adeniyi | D76: Adetokunbo | F76: Store Supervisor | G76: 12 | H76: 540000 | I76: 188800 | J76: 100 | K76: 13216 | M76: =H76 -> 540000 | N76: =M76*0.08 -> 43200 | O76: =M76-N76 -> 496800 | P76: =IF(O76<=300000,0,IF(O76>=20000000,(O76*0.21),(O76*0.2)+200000)) -> 299360 | Q76: =+M76-P76-N76 -> 197440 | R76: =IF(P76=0,(M76*0.01),IF(Q76<=0,0.01*M76,IF(AND(Q76>0,Q76<=300000),Q76*7%,IF(AND(Q76>=300000,Q76<600000),21000+(Q76-300000)*11%,IF(AND(Q76>=600000,Q76<1100000),54000+(Q76-600000)*15%,IF(AND(Q76>=1100000,Q76<1600000),129000+(Q76-1100000)*19%,IF(AND(Q76>=1600000,Q76<3200000),224000+(Q76-1600000)*21%,560000+(Q76-3200000)*24%))))))) -> 13820.8 | S76: =R76/12 -> 1151.7333 | T76: =G76 -> 12 | U76: =+S76*T76 -> 13820.8
A77: 74 | B77: N-3955784 | C77: Adesanya | D77: Oghoho | E77: Happiness | F77: Warehouse Supervisor | G77: 12 | H77: 660000 | I77: 275200 | J77: 100 | K77: 19264 | M77: =H77 -> 660000 | N77: =M77*0.08 -> 52800 | O77: =M77-N77 -> 607200 | P77: =IF(O77<=300000,0,IF(O77>=20000000,(O77*0.21),(O77*0.2)+200000)) -> 321440 | Q77: =+M77-P77-N77 -> 285760 | R77: =IF(P77=0,(M77*0.01),IF(Q77<=0,0.01*M77,IF(AND(Q77>0,Q77<=300000),Q77*7%,IF(AND(Q77>=300000,Q77<600000),21000+(Q77-300000)*11%,IF(AND(Q77>=600000,Q77<1100000),54000+(Q77-600000)*15%,IF(AND(Q77>=1100000,Q77<1600000),129000+(Q77-1100000)*19%,IF(AND(Q77>=1600000,Q77<3200000),224000+(Q77-1600000)*21%,560000+(Q77-3200000)*24%))))))) -> 20003.2 | S77: =R77/12 -> 1666.9333 | T77: =G77 -> 12 | U77: =+S77*T77 -> 20003.2
A78: 75 | B78: N-1679131 | C78: Adisa | D78: Saheed | E78: Abolore | F78: Driver | G78: 12 | H78: 480000 | I78: 145600 | J78: 100 | K78: 10192 | M78: =H78 -> 480000 | N78: =M78*0.08 -> 38400 | O78: =M78-N78 -> 441600 | P78: =IF(O78<=300000,0,IF(O78>=20000000,(O78*0.21),(O78*0.2)+200000)) -> 288320 | Q78: =+M78-P78-N78 -> 153280 | R78: =IF(P78=0,(M78*0.01),IF(Q78<=0,0.01*M78,IF(AND(Q78>0,Q78<=300000),Q78*7%,IF(AND(Q78>=300000,Q78<600000),21000+(Q78-300000)*11%,IF(AND(Q78>=600000,Q78<1100000),54000+(Q78-600000)*15%,IF(AND(Q78>=1100000,Q78<1600000),129000+(Q78-1100000)*19%,IF(AND(Q78>=1600000,Q78<3200000),224000+(Q78-1600000)*21%,560000+(Q78-3200000)*24%))))))) -> 10729.6 | S78: =R78/12 -> 894.13333 | T78: =G78 -> 12 | U78: =+S78*T78 -> 10729.6
A79: 76 | B79: N-1803117 | C79: Ajayi | D79: Dolapo | F79: Manager | G79: 12 | H79: 600000 | I79: 232000 | J79: 100 | K79: 16240 | M79: =H79 -> 600000 | N79: =M79*0.08 -> 48000 | O79: =M79-N79 -> 552000 | P79: =IF(O79<=300000,0,IF(O79>=20000000,(O79*0.21),(O79*0.2)+200000)) -> 310400 | Q79: =+M79-P79-N79 -> 241600 | R79: =IF(P79=0,(M79*0.01),IF(Q79<=0,0.01*M79,IF(AND(Q79>0,Q79<=300000),Q79*7%,IF(AND(Q79>=300000,Q79<600000),21000+(Q79-300000)*11%,IF(AND(Q79>=600000,Q79<1100000),54000+(Q79-600000)*15%,IF(AND(Q79>=1100000,Q79<1600000),129000+(Q79-1100000)*19%,IF(AND(Q79>=1600000,Q79<3200000),224000+(Q79-1600000)*21%,560000+(Q79-3200000)*24%))))))) -> 16912 | S79: =R79/12 -> 1409.3333 | T79: =G79 -> 12 | U79: =+S79*T79 -> 16912
A80: 77 | B80: N-5303415 | C80: Akinyemi | D80: Ibukun | F80: Maintainance | G80: 12 | H80: 420000 | I80: 102400 | J80: 100 | K80: 7168 | M80: =H80 -> 420000 | N80: =M80*0.08 -> 33600 | O80: =M80-N80 -> 386400 | P80: =IF(O80<=300000,0,IF(O80>=20000000,(O80*0.21),(O80*0.2)+200000)) -> 277280 | Q80: =+M80-P80-N80 -> 109120 | R80: =IF(P80=0,(M80*0.01),IF(Q80<=0,0.01*M80,IF(AND(Q80>0,Q80<=300000),Q80*7%,IF(AND(Q80>=300000,Q80<600000),21000+(Q80-300000)*11%,IF(AND(Q80>=600000,Q80<1100000),54000+(Q80-600000)*15%,IF(AND(Q80>=1100000,Q80<1600000),129000+(Q80-1100000)*19%,IF(AND(Q80>=1600000,Q80<3200000),224000+(Q80-1600000)*21%,560000+(Q80-3200000)*24%))))))) -> 7638.4 | S80: =R80/12 -> 636.53333 | T80: =G80 -> 12 | U80: =+S80*T80 -> 7638.4
A81: 78 | B81: N-1955860 | C81: Alaka | D81: Oluwaseun | E81: Micheal | F81: Manager | G81: 12 | H81: 540000 | I81: 188800 | J81: 100 | K81: 13216 | M81: =H81 -> 540000 | N81: =M81*0.08 -> 43200 | O81: =M81-N81 -> 496800 | P81: =IF(O81<=300000,0,IF(O81>=20000000,(O81*0.21),(O81*0.2)+200000)) -> 299360 | Q81: =+M81-P81-N81 -> 197440 | R81: =IF(P81=0,(M81*0.01),IF(Q81<=0,0.01*M81,IF(AND(Q81>0,Q81<=300000),Q81*7%,IF(AND(Q81>=300000,Q81<600000),21000+(Q81-300000)*11%,IF(AND(Q81>=600000,Q81<1100000),54000+(Q81-600000)*15%,IF(AND(Q81>=1100000,Q81<1600000),129000+(Q81-1100000)*19%,IF(AND(Q81>=1600000,Q81<3200000),224000+(Q81-1600000)*21%,560000+(Q81-3200000)*24%))))))) -> 13820.8 | S81: =R81/12 -> 1151.7333 | T81: =G81 -> 12 | U81: =+S81*T81 -> 13820.8
A82: 79 | B82: N-7759056 | C82: Alfonso | D82: Oladimeji | F82: Manager | G82: 12 | H82: 540000 | I82: 188800 | J82: 100 | K82: 13216 | M82: =H82 -> 540000 | N82: =M82*0.08 -> 43200 | O82: =M82-N82 -> 496800 | P82: =IF(O82<=300000,0,IF(O82>=20000000,(O82*0.21),(O82*0.2)+200000)) -> 299360 | Q82: =+M82-P82-N82 -> 197440 | R82: =IF(P82=0,(M82*0.01),IF(Q82<=0,0.01*M82,IF(AND(Q82>0,Q82<=300000),Q82*7%,IF(AND(Q82>=300000,Q82<600000),21000+(Q82-300000)*11%,IF(AND(Q82>=600000,Q82<1100000),54000+(Q82-600000)*15%,IF(AND(Q82>=1100000,Q82<1600000),129000+(Q82-1100000)*19%,IF(AND(Q82>=1600000,Q82<3200000),224000+(Q82-1600000)*21%,560000+(Q82-3200000)*24%))))))) -> 13820.8 | S82: =R82/12 -> 1151.7333 | T82: =G82 -> 12 | U82: =+S82*T82 -> 13820.8
A83: 80 | B83: N-2981688 | C83: Alimi | D83: Olanrewaju | F83: Accessory Officer | G83: 12 | H83: 480000 | I83: 145600 | J83: 100 | K83: 10192 | M83: =H83 -> 480000 | N83: =M83*0.08 -> 38400 | O83: =M83-N83 -> 441600 | P83: =IF(O83<=300000,0,IF(O83>=20000000,(O83*0.21),(O83*0.2)+200000)) -> 288320 | Q83: =+M83-P83-N83 -> 153280 | R83: =IF(P83=0,(M83*0.01),IF(Q83<=0,0.01*M83,IF(AND(Q83>0,Q83<=300000),Q83*7%,IF(AND(Q83>=300000,Q83<600000),21000+(Q83-300000)*11%,IF(AND(Q83>=600000,Q83<1100000),54000+(Q83-600000)*15%,IF(AND(Q83>=1100000,Q83<1600000),129000+(Q83-1100000)*19%,IF(AND(Q83>=1600000,Q83<3200000),224000+(Q83-1600000)*21%,560000+(Q83-3200000)*24%))))))) -> 10729.6 | S83: =R83/12 -> 894.13333 | T83: =G83 -> 12 | U83: =+S83*T83 -> 10729.6
A84: 81 | B84: N-1955757 | C84: Aliu | D84: Yakub | F84: Maintenance | G84: 12 | H84: 420000 | I84: 102400 | J84: 100 | K84: 7168 | M84: =H84 -> 420000 | N84: =M84*0.08 -> 33600 | O84: =M84-N84 -> 386400 | P84: =IF(O84<=300000,0,IF(O84>=20000000,(O84*0.21),(O84*0.2)+200000)) -> 277280 | Q84: =+M84-P84-N84 -> 109120 | R84: =IF(P84=0,(M84*0.01),IF(Q84<=0,0.01*M84,IF(AND(Q84>0,Q84<=300000),Q84*7%,IF(AND(Q84>=300000,Q84<600000),21000+(Q84-300000)*11%,IF(AND(Q84>=600000,Q84<1100000),54000+(Q84-600000)*15%,IF(AND(Q84>=1100000,Q84<1600000),129000+(Q84-1100000)*19%,IF(AND(Q84>=1600000,Q84<3200000),224000+(Q84-1600000)*21%,560000+(Q84-3200000)*24%))))))) -> 7638.4 | S84: =R84/12 -> 636.53333 | T84: =G84 -> 12 | U84: =+S84*T84 -> 7638.4
A85: 82 | B85: N-385931 | C85: Ayang | D85: Mathias | E85: Adomi | F85: Maintaince | G85: 12 | H85: 420000 | I85: 102400 | J85: 100 | K85: 7168 | M85: =H85 -> 420000 | N85: =M85*0.08 -> 33600 | O85: =M85-N85 -> 386400 | P85: =IF(O85<=300000,0,IF(O85>=20000000,(O85*0.21),(O85*0.2)+200000)) -> 277280 | Q85: =+M85-P85-N85 -> 109120 | R85: =IF(P85=0,(M85*0.01),IF(Q85<=0,0.01*M85,IF(AND(Q85>0,Q85<=300000),Q85*7%,IF(AND(Q85>=300000,Q85<600000),21000+(Q85-300000)*11%,IF(AND(Q85>=600000,Q85<1100000),54000+(Q85-600000)*15%,IF(AND(Q85>=1100000,Q85<1600000),129000+(Q85-1100000)*19%,IF(AND(Q85>=1600000,Q85<3200000),224000+(Q85-1600000)*21%,560000+(Q85-3200000)*24%))))))) -> 7638.4 | S85: =R85/12 -> 636.53333 | T85: =G85 -> 12 | U85: =+S85*T85 -> 7638.4
A86: 83 | B86: N-2981128 | C86: Ayeyo | D86: Oluwasegun | F86: Manager | G86: 12 | H86: 540000 | I86: 188800 | J86: 100 | K86: 13216 | M86: =H86 -> 540000 | N86: =M86*0.08 -> 43200 | O86: =M86-N86 -> 496800 | P86: =IF(O86<=300000,0,IF(O86>=20000000,(O86*0.21),(O86*0.2)+200000)) -> 299360 | Q86: =+M86-P86-N86 -> 197440 | R86: =IF(P86=0,(M86*0.01),IF(Q86<=0,0.01*M86,IF(AND(Q86>0,Q86<=300000),Q86*7%,IF(AND(Q86>=300000,Q86<600000),21000+(Q86-300000)*11%,IF(AND(Q86>=600000,Q86<1100000),54000+(Q86-600000)*15%,IF(AND(Q86>=1100000,Q86<1600000),129000+(Q86-1100000)*19%,IF(AND(Q86>=1600000,Q86<3200000),224000+(Q86-1600000)*21%,560000+(Q86-3200000)*24%))))))) -> 13820.8 | S86: =R86/12 -> 1151.7333 | T86: =G86 -> 12 | U86: =+S86*T86 -> 13820.8
A87: 84 | B87: N-7033446 | C87: Bonioly | D87: Adetayo | E87: Ayobami | F87: Accessory Assistant | G87: 12 | H87: 600000 | I87: 232000 | J87: 100 | K87: 16240 | M87: =H87 -> 600000 | N87: =M87*0.08 -> 48000 | O87: =M87-N87 -> 552000 | P87: =IF(O87<=300000,0,IF(O87>=20000000,(O87*0.21),(O87*0.2)+200000)) -> 310400 | Q87: =+M87-P87-N87 -> 241600 | R87: =IF(P87=0,(M87*0.01),IF(Q87<=0,0.01*M87,IF(AND(Q87>0,Q87<=300000),Q87*7%,IF(AND(Q87>=300000,Q87<600000),21000+(Q87-300000)*11%,IF(AND(Q87>=600000,Q87<1100000),54000+(Q87-600000)*15%,IF(AND(Q87>=1100000,Q87<1600000),129000+(Q87-1100000)*19%,IF(AND(Q87>=1600000,Q87<3200000),224000+(Q87-1600000)*21%,560000+(Q87-3200000)*24%))))))) -> 16912 | S87: =R87/12 -> 1409.3333 | T87: =G87 -> 12 | U87: =+S87*T87 -> 16912
A88: 85 | B88: N-580351 | C88: Chidiebere | D88: Peter | F88: Maintainance | G88: 12 | H88: 420000 | I88: 102400 | J88: 100 | K88: 7168 | M88: =H88 -> 420000 | N88: =M88*0.08 -> 33600 | O88: =M88-N88 -> 386400 | P88: =IF(O88<=300000,0,IF(O88>=20000000,(O88*0.21),(O88*0.2)+200000)) -> 277280 | Q88: =+M88-P88-N88 -> 109120 | R88: =IF(P88=0,(M88*0.01),IF(Q88<=0,0.01*M88,IF(AND(Q88>0,Q88<=300000),Q88*7%,IF(AND(Q88>=300000,Q88<600000),21000+(Q88-300000)*11%,IF(AND(Q88>=600000,Q88<1100000),54000+(Q88-600000)*15%,IF(AND(Q88>=1100000,Q88<1600000),129000+(Q88-1100000)*19%,IF(AND(Q88>=1600000,Q88<3200000),224000+(Q88-1600000)*21%,560000+(Q88-3200000)*24%))))))) -> 7638.4 | S88: =R88/12 -> 636.53333 | T88: =G88 -> 12 | U88: =+S88*T88 -> 7638.4
A89: 86 | B89: N-570446 | C89: Dennis | D89: Anna | F89: Electronics FSM | G89: 12 | H89: 420000 | I89: 102400 | J89: 100 | K89: 7168 | M89: =H89 -> 420000 | N89: =M89*0.08 -> 33600 | O89: =M89-N89 -> 386400 | P89: =IF(O89<=300000,0,IF(O89>=20000000,(O89*0.21),(O89*0.2)+200000)) -> 277280 | Q89: =+M89-P89-N89 -> 109120 | R89: =IF(P89=0,(M89*0.01),IF(Q89<=0,0.01*M89,IF(AND(Q89>0,Q89<=300000),Q89*7%,IF(AND(Q89>=300000,Q89<600000),21000+(Q89-300000)*11%,IF(AND(Q89>=600000,Q89<1100000),54000+(Q89-600000)*15%,IF(AND(Q89>=1100000,Q89<1600000),129000+(Q89-1100000)*19%,IF(AND(Q89>=1600000,Q89<3200000),224000+(Q89-1600000)*21%,560000+(Q89-3200000)*24%))))))) -> 7638.4 | S89: =R89/12 -> 636.53333 | T89: =G89 -> 12 | U89: =+S89*T89 -> 7638.4
A90: 87 | B90: N-2330418 | C90: Edet | D90: Lucky | F90: Decoration officer | G90: 12 | H90: 420000 | I90: 102400 | J90: 100 | K90: 7168 | M90: =H90 -> 420000 | N90: =M90*0.08 -> 33600 | O90: =M90-N90 -> 386400 | P90: =IF(O90<=300000,0,IF(O90>=20000000,(O90*0.21),(O90*0.2)+200000)) -> 277280 | Q90: =+M90-P90-N90 -> 109120 | R90: =IF(P90=0,(M90*0.01),IF(Q90<=0,0.01*M90,IF(AND(Q90>0,Q90<=300000),Q90*7%,IF(AND(Q90>=300000,Q90<600000),21000+(Q90-300000)*11%,IF(AND(Q90>=600000,Q90<1100000),54000+(Q90-600000)*15%,IF(AND(Q90>=1100000,Q90<1600000),129000+(Q90-1100000)*19%,IF(AND(Q90>=1600000,Q90<3200000),224000+(Q90-1600000)*21%,560000+(Q90-3200000)*24%))))))) -> 7638.4 | S90: =R90/12 -> 636.53333 | T90: =G90 -> 12 | U90: =+S90*T90 -> 7638.4
A91: 88 | B91: N-570487 | C91: Ehighalua | D91: Blessing | F91: Cashier | G91: 12 | H91: 480000 | I91: 145600 | J91: 100 | K91: 10192 | M91: =H91 -> 480000 | N91: =M91*0.08 -> 38400 | O91: =M91-N91 -> 441600 | P91: =IF(O91<=300000,0,IF(O91>=20000000,(O91*0.21),(O91*0.2)+200000)) -> 288320 | Q91: =+M91-P91-N91 -> 153280 | R91: =IF(P91=0,(M91*0.01),IF(Q91<=0,0.01*M91,IF(AND(Q91>0,Q91<=300000),Q91*7%,IF(AND(Q91>=300000,Q91<600000),21000+(Q91-300000)*11%,IF(AND(Q91>=600000,Q91<1100000),54000+(Q91-600000)*15%,IF(AND(Q91>=1100000,Q91<1600000),129000+(Q91-1100000)*19%,IF(AND(Q91>=1600000,Q91<3200000),224000+(Q91-1600000)*21%,560000+(Q91-3200000)*24%))))))) -> 10729.6 | S91: =R91/12 -> 894.13333 | T91: =G91 -> 12 | U91: =+S91*T91 -> 10729.6
A92: 89 | B92: N-4839578 | C92: Ejikemenwa | D92: Chinyere | F92: Cashier | G92: 12 | H92: 480000 | I92: 145600 | J92: 100 | K92: 10192 | M92: =H92 -> 480000 | N92: =M92*0.08 -> 38400 | O92: =M92-N92 -> 441600 | P92: =IF(O92<=300000,0,IF(O92>=20000000,(O92*0.21),(O92*0.2)+200000)) -> 288320 | Q92: =+M92-P92-N92 -> 153280 | R92: =IF(P92=0,(M92*0.01),IF(Q92<=0,0.01*M92,IF(AND(Q92>0,Q92<=300000),Q92*7%,IF(AND(Q92>=300000,Q92<600000),21000+(Q92-300000)*11%,IF(AND(Q92>=600000,Q92<1100000),54000+(Q92-600000)*15%,IF(AND(Q92>=1100000,Q92<1600000),129000+(Q92-1100000)*19%,IF(AND(Q92>=1600000,Q92<3200000),224000+(Q92-1600000)*21%,560000+(Q92-3200000)*24%))))))) -> 10729.6 | S92: =R92/12 -> 894.13333 | T92: =G92 -> 12 | U92: =+S92*T92 -> 10729.6
A93: 90 | B93: N-2981068 | C93: Elimian | D93: Okojie | E93: Omozokpa | F93: Manager | G93: 12 | H93: 540000 | I93: 188800 | J93: 100 | K93: 13216 | M93: =H93 -> 540000 | N93: =M93*0.08 -> 43200 | O93: =M93-N93 -> 496800 | P93: =IF(O93<=300000,0,IF(O93>=20000000,(O93*0.21),(O93*0.2)+200000)) -> 299360 | Q93: =+M93-P93-N93 -> 197440 | R93: =IF(P93=0,(M93*0.01),IF(Q93<=0,0.01*M93,IF(AND(Q93>0,Q93<=300000),Q93*7%,IF(AND(Q93>=300000,Q93<600000),21000+(Q93-300000)*11%,IF(AND(Q93>=600000,Q93<1100000),54000+(Q93-600000)*15%,IF(AND(Q93>=1100000,Q93<1600000),129000+(Q93-1100000)*19%,IF(AND(Q93>=1600000,Q93<3200000),224000+(Q93-1600000)*21%,560000+(Q93-3200000)*24%))))))) -> 13820.8 | S93: =R93/12 -> 1151.7333 | T93: =G93 -> 12 | U93: =+S93*T93 -> 13820.8
A94: 91 | B94: N-1328257 | C94: Elvis | D94: Uche | E94: Nkwocha | F94: Maintainance | G94: 12 | H94: 420000 | I94: 102400 | J94: 100 | K94: 7168 | M94: =H94 -> 420000 | N94: =M94*0.08 -> 33600 | O94: =M94-N94 -> 386400 | P94: =IF(O94<=300000,0,IF(O94>=20000000,(O94*0.21),(O94*0.2)+200000)) -> 277280 | Q94: =+M94-P94-N94 -> 109120 | R94: =IF(P94=0,(M94*0.01),IF(Q94<=0,0.01*M94,IF(AND(Q94>0,Q94<=300000),Q94*7%,IF(AND(Q94>=300000,Q94<600000),21000+(Q94-300000)*11%,IF(AND(Q94>=600000,Q94<1100000),54000+(Q94-600000)*15%,IF(AND(Q94>=1100000,Q94<1600000),129000+(Q94-1100000)*19%,IF(AND(Q94>=1600000,Q94<3200000),224000+(Q94-1600000)*21%,560000+(Q94-3200000)*24%))))))) -> 7638.4 | S94: =R94/12 -> 636.53333 | T94: =G94 -> 12 | U94: =+S94*T94 -> 7638.4
A95: 92 | B95: N-2131122 | C95: Emetoh | D95: Chizoba | E95: Genevieve | F95: Cashier | G95: 12 | H95: 480000 | I95: 145600 | J95: 100 | K95: 10192 | M95: =H95 -> 480000 | N95: =M95*0.08 -> 38400 | O95: =M95-N95 -> 441600 | P95: =IF(O95<=300000,0,IF(O95>=20000000,(O95*0.21),(O95*0.2)+200000)) -> 288320 | Q95: =+M95-P95-N95 -> 153280 | R95: =IF(P95=0,(M95*0.01),IF(Q95<=0,0.01*M95,IF(AND(Q95>0,Q95<=300000),Q95*7%,IF(AND(Q95>=300000,Q95<600000),21000+(Q95-300000)*11%,IF(AND(Q95>=600000,Q95<1100000),54000+(Q95-600000)*15%,IF(AND(Q95>=1100000,Q95<1600000),129000+(Q95-1100000)*19%,IF(AND(Q95>=1600000,Q95<3200000),224000+(Q95-1600000)*21%,560000+(Q95-3200000)*24%))))))) -> 10729.6 | S95: =R95/12 -> 894.13333 | T95: =G95 -> 12 | U95: =+S95*T95 -> 10729.6
A96: 93 | B96: N-2330409 | C96: Evborokhai | D96: Aigboje | E96: Courage | F96: Warehouse Supervisor | G96: 12 | H96: 600000 | I96: 232000 | J96: 100 | K96: 16240 | M96: =H96 -> 600000 | N96: =M96*0.08 -> 48000 | O96: =M96-N96 -> 552000 | P96: =IF(O96<=300000,0,IF(O96>=20000000,(O96*0.21),(O96*0.2)+200000)) -> 310400 | Q96: =+M96-P96-N96 -> 241600 | R96: =IF(P96=0,(M96*0.01),IF(Q96<=0,0.01*M96,IF(AND(Q96>0,Q96<=300000),Q96*7%,IF(AND(Q96>=300000,Q96<600000),21000+(Q96-300000)*11%,IF(AND(Q96>=600000,Q96<1100000),54000+(Q96-600000)*15%,IF(AND(Q96>=1100000,Q96<1600000),129000+(Q96-1100000)*19%,IF(AND(Q96>=1600000,Q96<3200000),224000+(Q96-1600000)*21%,560000+(Q96-3200000)*24%))))))) -> 16912 | S96: =R96/12 -> 1409.3333 | T96: =G96 -> 12 | U96: =+S96*T96 -> 16912
A97: 94 | B97: N-3519433 | C97: Gbadamosi | D97: Gabriel | F97: Store Supervior | G97: 12 | H97: 540000 | I97: 188800 | J97: 100 | K97: 13216 | M97: =H97 -> 540000 | N97: =M97*0.08 -> 43200 | O97: =M97-N97 -> 496800 | P97: =IF(O97<=300000,0,IF(O97>=20000000,(O97*0.21),(O97*0.2)+200000)) -> 299360 | Q97: =+M97-P97-N97 -> 197440 | R97: =IF(P97=0,(M97*0.01),IF(Q97<=0,0.01*M97,IF(AND(Q97>0,Q97<=300000),Q97*7%,IF(AND(Q97>=300000,Q97<600000),21000+(Q97-300000)*11%,IF(AND(Q97>=600000,Q97<1100000),54000+(Q97-600000)*15%,IF(AND(Q97>=1100000,Q97<1600000),129000+(Q97-1100000)*19%,IF(AND(Q97>=1600000,Q97<3200000),224000+(Q97-1600000)*21%,560000+(Q97-3200000)*24%))))))) -> 13820.8 | S97: =R97/12 -> 1151.7333 | T97: =G97 -> 12 | U97: =+S97*T97 -> 13820.8
A98: 95 | B98: N-2330446 | C98: Hassan | D98: Isah | F98: Wood worker | G98: 12 | H98: 720000 | I98: 318400 | J98: 100 | K98: 23024 | M98: =H98 -> 720000 | N98: =M98*0.08 -> 57600 | O98: =M98-N98 -> 662400 | P98: =IF(O98<=300000,0,IF(O98>=20000000,(O98*0.21),(O98*0.2)+200000)) -> 332480 | Q98: =+M98-P98-N98 -> 329920 | R98: =IF(P98=0,(M98*0.01),IF(Q98<=0,0.01*M98,IF(AND(Q98>0,Q98<=300000),Q98*7%,IF(AND(Q98>=300000,Q98<600000),21000+(Q98-300000)*11%,IF(AND(Q98>=600000,Q98<1100000),54000+(Q98-600000)*15%,IF(AND(Q98>=1100000,Q98<1600000),129000+(Q98-1100000)*19%,IF(AND(Q98>=1600000,Q98<3200000),224000+(Q98-1600000)*21%,560000+(Q98-3200000)*24%))))))) -> 24291.2 | S98: =R98/12 -> 2024.2667 | T98: =G98 -> 12 | U98: =+S98*T98 -> 24291.2
A99: 96 | B99: N-7976162 | C99: Henry | D99: Ugbah | F99: Accessories Manager | G99: 12 | H99: 1260000 | I99: 707200 | J99: 100 | K99: 70080 | M99: =H99 -> 1260000 | N99: =M99*0.08 -> 100800 | O99: =M99-N99 -> 1159200 | P99: =IF(O99<=300000,0,IF(O99>=20000000,(O99*0.21),(O99*0.2)+200000)) -> 431840 | Q99: =+M99-P99-N99 -> 727360 | R99: =IF(P99=0,(M99*0.01),IF(Q99<=0,0.01*M99,IF(AND(Q99>0,Q99<=300000),Q99*7%,IF(AND(Q99>=300000,Q99<600000),21000+(Q99-300000)*11%,IF(AND(Q99>=600000,Q99<1100000),54000+(Q99-600000)*15%,IF(AND(Q99>=1100000,Q99<1600000),129000+(Q99-1100000)*19%,IF(AND(Q99>=1600000,Q99<3200000),224000+(Q99-1600000)*21%,560000+(Q99-3200000)*24%))))))) -> 73104 | S99: =R99/12 -> 6092 | T99: =G99 -> 12 | U99: =+S99*T99 -> 73104
A100: 97 | B100: N-2084472 | C100: Ifionu | D100: Louisa | E100: Blessing | F100: FSM | G100: 12 | H100: 420000 | I100: 102400 | J100: 100 | K100: 7168 | M100: =H100 -> 420000 | N100: =M100*0.08 -> 33600 | O100: =M100-N100 -> 386400 | P100: =IF(O100<=300000,0,IF(O100>=20000000,(O100*0.21),(O100*0.2)+200000)) -> 277280 | Q100: =+M100-P100-N100 -> 109120 | R100: =IF(P100=0,(M100*0.01),IF(Q100<=0,0.01*M100,IF(AND(Q100>0,Q100<=300000),Q100*7%,IF(AND(Q100>=300000,Q100<600000),21000+(Q100-300000)*11%,IF(AND(Q100>=600000,Q100<1100000),54000+(Q100-600000)*15%,IF(AND(Q100>=1100000,Q100<1600000),129000+(Q100-1100000)*19%,IF(AND(Q100>=1600000,Q100<3200000),224000+(Q100-1600000)*21%,560000+(Q100-3200000)*24%))))))) -> 7638.4 | S100: =R100/12 -> 636.53333 | T100: =G100 -> 12 | U100: =+S100*T100 -> 7638.4
...

Sheet local 24
A1: 3C HUB BRAND MANAGEMENT LIMITED
A2: ANNUAL PAYROLL FOR 2024
A4: SN | B4: Surname | C4: First Name | D4: Middle Name | E4: Designation | G4: Gross Income | H4: Chargeable Income | I4: Development Levy | J4: Tax Paid | L4: ANNUAL TOTAL GROSS INCOME + BIK | M4: PENSION | N4: NET INCOME | O4: CRA | P4: TAXABLE INCOME | Q4: ANNUAL TAX | R4: MONTHLY TAX | S4: MNTH | T4: PRO BY MNTH
A5: 1 | B5: Ihezie | C5: Monica | E5: 020 Officer | F5: 12 | G5: 540000 | H5: 188800 | I5: 100 | J5: 13216 | L5: =G5 -> 540000 | M5: =L5*0.08 -> 43200 | N5: =L5-M5 -> 496800 | O5: =IF(N5<=300000,0,IF(N5>=20000000,(N5*0.21),(N5*0.2)+200000)) -> 299360 | P5: =+L5-O5-M5 -> 197440 | Q5: =IF(O5=0,(L5*0.01),IF(P5<=0,0.01*L5,IF(AND(P5>0,P5<=300000),P5*7%,IF(AND(P5>=300000,P5<600000),21000+(P5-300000)*11%,IF(AND(P5>=600000,P5<1100000),54000+(P5-600000)*15%,IF(AND(P5>=1100000,P5<1600000),129000+(P5-1100000)*19%,IF(AND(P5>=1600000,P5<3200000),224000+(P5-1600000)*21%,560000+(P5-3200000)*24%))))))) -> 13820.8 | R5: =Q5/12 -> 1151.7333 | S5: =F5 -> 12 | T5: =+R5*S5 -> 13820.8
A6: 2 | B6: Victor. | C6: N. | D6: Nwaoha | E6: Info Tech | F6: 12 | G6: 960000 | H6: 491200 | I6: 100 | J6: 42032 | L6: =G6 -> 960000 | M6: =L6*0.08 -> 76800 | N6: =L6-M6 -> 883200 | O6: =IF(N6<=300000,0,IF(N6>=20000000,(N6*0.21),(N6*0.2)+200000)) -> 376640 | P6: =+L6-O6-M6 -> 506560 | Q6: =IF(O6=0,(L6*0.01),IF(P6<=0,0.01*L6,IF(AND(P6>0,P6<=300000),P6*7%,IF(AND(P6>=300000,P6<600000),21000+(P6-300000)*11%,IF(AND(P6>=600000,P6<1100000),54000+(P6-600000)*15%,IF(AND(P6>=1100000,P6<1600000),129000+(P6-1100000)*19%,IF(AND(P6>=1600000,P6<3200000),224000+(P6-1600000)*21%,560000+(P6-3200000)*24%))))))) -> 43721.6 | R6: =Q6/12 -> 3643.4667 | S6: =F6 -> 12 | T6: =+R6*S6 -> 43721.6
A7: 3 | B7: Adesola | C7: Adeyinka | E7: Account officer | F7: 12 | G7: 660000 | H7: 275200 | I7: 100 | J7: 19264 | L7: =G7 -> 660000 | M7: =L7*0.08 -> 52800 | N7: =L7-M7 -> 607200 | O7: =IF(N7<=300000,0,IF(N7>=20000000,(N7*0.21),(N7*0.2)+200000)) -> 321440 | P7: =+L7-O7-M7 -> 285760 | Q7: =IF(O7=0,(L7*0.01),IF(P7<=0,0.01*L7,IF(AND(P7>0,P7<=300000),P7*7%,IF(AND(P7>=300000,P7<600000),21000+(P7-300000)*11%,IF(AND(P7>=600000,P7<1100000),54000+(P7-600000)*15%,IF(AND(P7>=1100000,P7<1600000),129000+(P7-1100000)*19%,IF(AND(P7>=1600000,P7<3200000),224000+(P7-1600000)*21%,560000+(P7-3200000)*24%))))))) -> 20003.2 | R7: =Q7/12 -> 1666.9333 | S7: =F7 -> 12 | T7: =+R7*S7 -> 20003.2
A8: 4 | B8: Egbuchulam | C8: Francis | E8: Electronics Aftersales Manager | F8: 12 | G8: 600000 | H8: 232000 | I8: 100 | J8: 16240 | L8: =G8 -> 600000 | M8: =L8*0.08 -> 48000 | N8: =L8-M8 -> 552000 | O8: =IF(N8<=300000,0,IF(N8>=20000000,(N8*0.21),(N8*0.2)+200000)) -> 310400 | P8: =+L8-O8-M8 -> 241600 | Q8: =IF(O8=0,(L8*0.01),IF(P8<=0,0.01*L8,IF(AND(P8>0,P8<=300000),P8*7%,IF(AND(P8>=300000,P8<600000),21000+(P8-300000)*11%,IF(AND(P8>=600000,P8<1100000),54000+(P8-600000)*15%,IF(AND(P8>=1100000,P8<1600000),129000+(P8-1100000)*19%,IF(AND(P8>=1600000,P8<3200000),224000+(P8-1600000)*21%,560000+(P8-3200000)*24%))))))) -> 16912 | R8: =Q8/12 -> 1409.3333 | S8: =F8 -> 12 | T8: =+R8*S8 -> 16912
A9: 5 | B9: Timothy | C9: O | D9: Ikponmwen | E9: Manager | F9: 12 | G9: 600000 | H9: 232000 | I9: 100 | J9: 16240 | L9: =G9 -> 600000 | M9: =L9*0.08 -> 48000 | N9: =L9-M9 -> 552000 | O9: =IF(N9<=300000,0,IF(N9>=20000000,(N9*0.21),(N9*0.2)+200000)) -> 310400 | P9: =+L9-O9-M9 -> 241600 | Q9: =IF(O9=0,(L9*0.01),IF(P9<=0,0.01*L9,IF(AND(P9>0,P9<=300000),P9*7%,IF(AND(P9>=300000,P9<600000),21000+(P9-300000)*11%,IF(AND(P9>=600000,P9<1100000),54000+(P9-600000)*15%,IF(AND(P9>=1100000,P9<1600000),129000+(P9-1100000)*19%,IF(AND(P9>=1600000,P9<3200000),224000+(P9-1600000)*21%,560000+(P9-3200000)*24%))))))) -> 16912 | R9: =Q9/12 -> 1409.3333 | S9: =F9 -> 12 | T9: =+R9*S9 -> 16912
A10: 6 | B10: Kolawole | C10: Opeyemi | E10: Material Officer | F10: 12 | G10: 420000 | H10: 102400 | I10: 100 | J10: 7168 | L10: =G10 -> 420000 | M10: =L10*0.08 -> 33600 | N10: =L10-M10 -> 386400 | O10: =IF(N10<=300000,0,IF(N10>=20000000,(N10*0.21),(N10*0.2)+200000)) -> 277280 | P10: =+L10-O10-M10 -> 109120 | Q10: =IF(O10=0,(L10*0.01),IF(P10<=0,0.01*L10,IF(AND(P10>0,P10<=300000),P10*7%,IF(AND(P10>=300000,P10<600000),21000+(P10-300000)*11%,IF(AND(P10>=600000,P10<1100000),54000+(P10-600000)*15%,IF(AND(P10>=1100000,P10<1600000),129000+(P10-1100000)*19%,IF(AND(P10>=1600000,P10<3200000),224000+(P10-1600000)*21%,560000+(P10-3200000)*24%))))))) -> 7638.4 | R10: =Q10/12 -> 636.53333 | S10: =F10 -> 12 | T10: =+R10*S10 -> 7638.4
A11: 7 | B11: Ginikanwa | C11: Darlington | D11: Uzoma | E11: Maintenance | F11: 12 | G11: 420000 | H11: 102400 | I11: 100 | J11: 7168 | L11: =G11 -> 420000 | M11: =L11*0.08 -> 33600 | N11: =L11-M11 -> 386400 | O11: =IF(N11<=300000,0,IF(N11>=20000000,(N11*0.21),(N11*0.2)+200000)) -> 277280 | P11: =+L11-O11-M11 -> 109120 | Q11: =IF(O11=0,(L11*0.01),IF(P11<=0,0.01*L11,IF(AND(P11>0,P11<=300000),P11*7%,IF(AND(P11>=300000,P11<600000),21000+(P11-300000)*11%,IF(AND(P11>=600000,P11<1100000),54000+(P11-600000)*15%,IF(AND(P11>=1100000,P11<1600000),129000+(P11-1100000)*19%,IF(AND(P11>=1600000,P11<3200000),224000+(P11-1600000)*21%,560000+(P11-3200000)*24%))))))) -> 7638.4 | R11: =Q11/12 -> 636.53333 | S11: =F11 -> 12 | T11: =+R11*S11 -> 7638.4
A12: 8 | B12: Kuponu | C12: Sesi | D12: Egbemimo | E12: Manager | F12: 12 | G12: 540000 | H12: 188800 | I12: 100 | J12: 13216 | L12: =G12 -> 540000 | M12: =L12*0.08 -> 43200 | N12: =L12-M12 -> 496800 | O12: =IF(N12<=300000,0,IF(N12>=20000000,(N12*0.21),(N12*0.2)+200000)) -> 299360 | P12: =+L12-O12-M12 -> 197440 | Q12: =IF(O12=0,(L12*0.01),IF(P12<=0,0.01*L12,IF(AND(P12>0,P12<=300000),P12*7%,IF(AND(P12>=300000,P12<600000),21000+(P12-300000)*11%,IF(AND(P12>=600000,P12<1100000),54000+(P12-600000)*15%,IF(AND(P12>=1100000,P12<1600000),129000+(P12-1100000)*19%,IF(AND(P12>=1600000,P12<3200000),224000+(P12-1600000)*21%,560000+(P12-3200000)*24%))))))) -> 13820.8 | R12: =Q12/12 -> 1151.7333 | S12: =F12 -> 12 | T12: =+R12*S12 -> 13820.8
A13: 9 | B13: Ayira | C13: Peace | E13: Cashier | F13: 12 | G13: 480000 | H13: 145600 | I13: 100 | J13: 10192 | L13: =G13 -> 480000 | M13: =L13*0.08 -> 38400 | N13: =L13-M13 -> 441600 | O13: =IF(N13<=300000,0,IF(N13>=20000000,(N13*0.21),(N13*0.2)+200000)) -> 288320 | P13: =+L13-O13-M13 -> 153280 | Q13: =IF(O13=0,(L13*0.01),IF(P13<=0,0.01*L13,IF(AND(P13>0,P13<=300000),P13*7%,IF(AND(P13>=300000,P13<600000),21000+(P13-300000)*11%,IF(AND(P13>=600000,P13<1100000),54000+(P13-600000)*15%,IF(AND(P13>=1100000,P13<1600000),129000+(P13-1100000)*19%,IF(AND(P13>=1600000,P13<3200000),224000+(P13-1600000)*21%,560000+(P13-3200000)*24%))))))) -> 10729.6 | R13: =Q13/12 -> 894.13333 | S13: =F13 -> 12 | T13: =+R13*S13 -> 10729.6
A14: 10 | B14: Kusagba | C14: Oluwakayode | E14: Stock Audior | F14: 12 | G14: 660000 | H14: 275200 | I14: 100 | J14: 19264 | L14: =G14 -> 660000 | M14: =L14*0.08 -> 52800 | N14: =L14-M14 -> 607200 | O14: =IF(N14<=300000,0,IF(N14>=20000000,(N14*0.21),(N14*0.2)+200000)) -> 321440 | P14: =+L14-O14-M14 -> 285760 | Q14: =IF(O14=0,(L14*0.01),IF(P14<=0,0.01*L14,IF(AND(P14>0,P14<=300000),P14*7%,IF(AND(P14>=300000,P14<600000),21000+(P14-300000)*11%,IF(AND(P14>=600000,P14<1100000),54000+(P14-600000)*15%,IF(AND(P14>=1100000,P14<1600000),129000+(P14-1100000)*19%,IF(AND(P14>=1600000,P14<3200000),224000+(P14-1600000)*21%,560000+(P14-3200000)*24%))))))) -> 20003.2 | R14: =Q14/12 -> 1666.9333 | S14: =F14 -> 12 | T14: =+R14*S14 -> 20003.2
A15: 11 | B15: Okoro | C15: Lilian | E15: Cashier | F15: 12 | G15: 480000 | H15: 145600 | I15: 100 | J15: 10192 | L15: =G15 -> 480000 | M15: =L15*0.08 -> 38400 | N15: =L15-M15 -> 441600 | O15: =IF(N15<=300000,0,IF(N15>=20000000,(N15*0.21),(N15*0.2)+200000)) -> 288320 | P15: =+L15-O15-M15 -> 153280 | Q15: =IF(O15=0,(L15*0.01),IF(P15<=0,0.01*L15,IF(AND(P15>0,P15<=300000),P15*7%,IF(AND(P15>=300000,P15<600000),21000+(P15-300000)*11%,IF(AND(P15>=600000,P15<1100000),54000+(P15-600000)*15%,IF(AND(P15>=1100000,P15<1600000),129000+(P15-1100000)*19%,IF(AND(P15>=1600000,P15<3200000),224000+(P15-1600000)*21%,560000+(P15-3200000)*24%))))))) -> 10729.6 | R15: =Q15/12 -> 894.13333 | S15: =F15 -> 12 | T15: =+R15*S15 -> 10729.6
A16: 12 | B16: Happiness | C16: Peace | E16: Store Supervisor | F16: 12 | G16: 540000 | H16: 188800 | I16: 100 | J16: 13216 | L16: =G16 -> 540000 | M16: =L16*0.08 -> 43200 | N16: =L16-M16 -> 496800 | O16: =IF(N16<=300000,0,IF(N16>=20000000,(N16*0.21),(N16*0.2)+200000)) -> 299360 | P16: =+L16-O16-M16 -> 197440 | Q16: =IF(O16=0,(L16*0.01),IF(P16<=0,0.01*L16,IF(AND(P16>0,P16<=300000),P16*7%,IF(AND(P16>=300000,P16<600000),21000+(P16-300000)*11%,IF(AND(P16>=600000,P16<1100000),54000+(P16-600000)*15%,IF(AND(P16>=1100000,P16<1600000),129000+(P16-1100000)*19%,IF(AND(P16>=1600000,P16<3200000),224000+(P16-1600000)*21%,560000+(P16-3200000)*24%))))))) -> 13820.8 | R16: =Q16/12 -> 1151.7333 | S16: =F16 -> 12 | T16: =+R16*S16 -> 13820.8
A17: 13 | B17: Ezioha | C17: Joel | D17: Ifeanyi | E17: Store Supervisor | F17: 12 | G17: 540000 | H17: 188800 | I17: 100 | J17: 13216 | L17: =G17 -> 540000 | M17: =L17*0.08 -> 43200 | N17: =L17-M17 -> 496800 | O17: =IF(N17<=300000,0,IF(N17>=20000000,(N17*0.21),(N17*0.2)+200000)) -> 299360 | P17: =+L17-O17-M17 -> 197440 | Q17: =IF(O17=0,(L17*0.01),IF(P17<=0,0.01*L17,IF(AND(P17>0,P17<=300000),P17*7%,IF(AND(P17>=300000,P17<600000),21000+(P17-300000)*11%,IF(AND(P17>=600000,P17<1100000),54000+(P17-600000)*15%,IF(AND(P17>=1100000,P17<1600000),129000+(P17-1100000)*19%,IF(AND(P17>=1600000,P17<3200000),224000+(P17-1600000)*21%,560000+(P17-3200000)*24%))))))) -> 13820.8 | R17: =Q17/12 -> 1151.7333 | S17: =F17 -> 12 | T17: =+R17*S17 -> 13820.8
A18: 14 | B18: Omolewa | C18: Mobolaji | E18: Cashier | F18: 12 | G18: 480000 | H18: 145600 | I18: 100 | J18: 10192 | L18: =G18 -> 480000 | M18: =L18*0.08 -> 38400 | N18: =L18-M18 -> 441600 | O18: =IF(N18<=300000,0,IF(N18>=20000000,(N18*0.21),(N18*0.2)+200000)) -> 288320 | P18: =+L18-O18-M18 -> 153280 | Q18: =IF(O18=0,(L18*0.01),IF(P18<=0,0.01*L18,IF(AND(P18>0,P18<=300000),P18*7%,IF(AND(P18>=300000,P18<600000),21000+(P18-300000)*11%,IF(AND(P18>=600000,P18<1100000),54000+(P18-600000)*15%,IF(AND(P18>=1100000,P18<1600000),129000+(P18-1100000)*19%,IF(AND(P18>=1600000,P18<3200000),224000+(P18-1600000)*21%,560000+(P18-3200000)*24%))))))) -> 10729.6 | R18: =Q18/12 -> 894.13333 | S18: =F18 -> 12 | T18: =+R18*S18 -> 10729.6
A19: 15 | B19: Oguh | C19: Chrysantus | D19: Ogadimma | E19: Maintainance | F19: 12 | G19: 420000 | H19: 102400 | I19: 100 | J19: 7168 | L19: =G19 -> 420000 | M19: =L19*0.08 -> 33600 | N19: =L19-M19 -> 386400 | O19: =IF(N19<=300000,0,IF(N19>=20000000,(N19*0.21),(N19*0.2)+200000)) -> 277280 | P19: =+L19-O19-M19 -> 109120 | Q19: =IF(O19=0,(L19*0.01),IF(P19<=0,0.01*L19,IF(AND(P19>0,P19<=300000),P19*7%,IF(AND(P19>=300000,P19<600000),21000+(P19-300000)*11%,IF(AND(P19>=600000,P19<1100000),54000+(P19-600000)*15%,IF(AND(P19>=1100000,P19<1600000),129000+(P19-1100000)*19%,IF(AND(P19>=1600000,P19<3200000),224000+(P19-1600000)*21%,560000+(P19-3200000)*24%))))))) -> 7638.4 | R19: =Q19/12 -> 636.53333 | S19: =F19 -> 12 | T19: =+R19*S19 -> 7638.4
A20: 16 | B20: Adetunji | C20: John | D20: Oluwatosin | E20: Manager | F20: 12 | G20: 540000 | H20: 188800 | I20: 100 | J20: 13216 | L20: =G20 -> 540000 | M20: =L20*0.08 -> 43200 | N20: =L20-M20 -> 496800 | O20: =IF(N20<=300000,0,IF(N20>=20000000,(N20*0.21),(N20*0.2)+200000)) -> 299360 | P20: =+L20-O20-M20 -> 197440 | Q20: =IF(O20=0,(L20*0.01),IF(P20<=0,0.01*L20,IF(AND(P20>0,P20<=300000),P20*7%,IF(AND(P20>=300000,P20<600000),21000+(P20-300000)*11%,IF(AND(P20>=600000,P20<1100000),54000+(P20-600000)*15%,IF(AND(P20>=1100000,P20<1600000),129000+(P20-1100000)*19%,IF(AND(P20>=1600000,P20<3200000),224000+(P20-1600000)*21%,560000+(P20-3200000)*24%))))))) -> 13820.8 | R20: =Q20/12 -> 1151.7333 | S20: =F20 -> 12 | T20: =+R20*S20 -> 13820.8
A21: 17 | B21: Otache | C21: Ruth | D21: Ene | E21: Cashier | F21: 12 | G21: 480000 | H21: 145600 | I21: 100 | J21: 10192 | L21: =G21 -> 480000 | M21: =L21*0.08 -> 38400 | N21: =L21-M21 -> 441600 | O21: =IF(N21<=300000,0,IF(N21>=20000000,(N21*0.21),(N21*0.2)+200000)) -> 288320 | P21: =+L21-O21-M21 -> 153280 | Q21: =IF(O21=0,(L21*0.01),IF(P21<=0,0.01*L21,IF(AND(P21>0,P21<=300000),P21*7%,IF(AND(P21>=300000,P21<600000),21000+(P21-300000)*11%,IF(AND(P21>=600000,P21<1100000),54000+(P21-600000)*15%,IF(AND(P21>=1100000,P21<1600000),129000+(P21-1100000)*19%,IF(AND(P21>=1600000,P21<3200000),224000+(P21-1600000)*21%,560000+(P21-3200000)*24%))))))) -> 10729.6 | R21: =Q21/12 -> 894.13333 | S21: =F21 -> 12 | T21: =+R21*S21 -> 10729.6
A22: 18 | B22: Roland | C22: Ebramieta | E22: Maintainance | F22: 12 | G22: 420000 | H22: 102400 | I22: 100 | J22: 7168 | L22: =G22 -> 420000 | M22: =L22*0.08 -> 33600 | N22: =L22-M22 -> 386400 | O22: =IF(N22<=300000,0,IF(N22>=20000000,(N22*0.21),(N22*0.2)+200000)) -> 277280 | P22: =+L22-O22-M22 -> 109120 | Q22: =IF(O22=0,(L22*0.01),IF(P22<=0,0.01*L22,IF(AND(P22>0,P22<=300000),P22*7%,IF(AND(P22>=300000,P22<600000),21000+(P22-300000)*11%,IF(AND(P22>=600000,P22<1100000),54000+(P22-600000)*15%,IF(AND(P22>=1100000,P22<1600000),129000+(P22-1100000)*19%,IF(AND(P22>=1600000,P22<3200000),224000+(P22-1600000)*21%,560000+(P22-3200000)*24%))))))) -> 7638.4 | R22: =Q22/12 -> 636.53333 | S22: =F22 -> 12 | T22: =+R22*S22 -> 7638.4
A23: 19 | B23: Adesina | C23: Olawole | D23: Daniel | E23: Maintenance | F23: 12 | G23: 420000 | H23: 102400 | I23: 100 | J23: 7168 | L23: =G23 -> 420000 | M23: =L23*0.08 -> 33600 | N23: =L23-M23 -> 386400 | O23: =IF(N23<=300000,0,IF(N23>=20000000,(N23*0.21),(N23*0.2)+200000)) -> 277280 | P23: =+L23-O23-M23 -> 109120 | Q23: =IF(O23=0,(L23*0.01),IF(P23<=0,0.01*L23,IF(AND(P23>0,P23<=300000),P23*7%,IF(AND(P23>=300000,P23<600000),21000+(P23-300000)*11%,IF(AND(P23>=600000,P23<1100000),54000+(P23-600000)*15%,IF(AND(P23>=1100000,P23<1600000),129000+(P23-1100000)*19%,IF(AND(P23>=1600000,P23<3200000),224000+(P23-1600000)*21%,560000+(P23-3200000)*24%))))))) -> 7638.4 | R23: =Q23/12 -> 636.53333 | S23: =F23 -> 12 | T23: =+R23*S23 -> 7638.4
A24: 20 | B24: Onyenoro | C24: Obinna | E24: Trainee Manager | F24: 12 | G24: 480000 | H24: 145600 | I24: 100 | J24: 10192 | L24: =G24 -> 480000 | M24: =L24*0.08 -> 38400 | N24: =L24-M24 -> 441600 | O24: =IF(N24<=300000,0,IF(N24>=20000000,(N24*0.21),(N24*0.2)+200000)) -> 288320 | P24: =+L24-O24-M24 -> 153280 | Q24: =IF(O24=0,(L24*0.01),IF(P24<=0,0.01*L24,IF(AND(P24>0,P24<=300000),P24*7%,IF(AND(P24>=300000,P24<600000),21000+(P24-300000)*11%,IF(AND(P24>=600000,P24<1100000),54000+(P24-600000)*15%,IF(AND(P24>=1100000,P24<1600000),129000+(P24-1100000)*19%,IF(AND(P24>=1600000,P24<3200000),224000+(P24-1600000)*21%,560000+(P24-3200000)*24%))))))) -> 10729.6 | R24: =Q24/12 -> 894.13333 | S24: =F24 -> 12 | T24: =+R24*S24 -> 10729.6
A25: 21 | B25: Olusola | C25: Odunayo | E25: Assistant Sales Manager | F25: 12 | G25: 540000 | H25: 188800 | I25: 100 | J25: 13216 | L25: =G25 -> 540000 | M25: =L25*0.08 -> 43200 | N25: =L25-M25 -> 496800 | O25: =IF(N25<=300000,0,IF(N25>=20000000,(N25*0.21),(N25*0.2)+200000)) -> 299360 | P25: =+L25-O25-M25 -> 197440 | Q25: =IF(O25=0,(L25*0.01),IF(P25<=0,0.01*L25,IF(AND(P25>0,P25<=300000),P25*7%,IF(AND(P25>=300000,P25<600000),21000+(P25-300000)*11%,IF(AND(P25>=600000,P25<1100000),54000+(P25-600000)*15%,IF(AND(P25>=1100000,P25<1600000),129000+(P25-1100000)*19%,IF(AND(P25>=1600000,P25<3200000),224000+(P25-1600000)*21%,560000+(P25-3200000)*24%))))))) -> 13820.8 | R25: =Q25/12 -> 1151.7333 | S25: =F25 -> 12 | T25: =+R25*S25 -> 13820.8
A26: 22 | B26: Olorunsina | C26: Kemi | E26: Cashier | F26: 12 | G26: 480000 | H26: 145600 | I26: 100 | J26: 10192 | L26: =G26 -> 480000 | M26: =L26*0.08 -> 38400 | N26: =L26-M26 -> 441600 | O26: =IF(N26<=300000,0,IF(N26>=20000000,(N26*0.21),(N26*0.2)+200000)) -> 288320 | P26: =+L26-O26-M26 -> 153280 | Q26: =IF(O26=0,(L26*0.01),IF(P26<=0,0.01*L26,IF(AND(P26>0,P26<=300000),P26*7%,IF(AND(P26>=300000,P26<600000),21000+(P26-300000)*11%,IF(AND(P26>=600000,P26<1100000),54000+(P26-600000)*15%,IF(AND(P26>=1100000,P26<1600000),129000+(P26-1100000)*19%,IF(AND(P26>=1600000,P26<3200000),224000+(P26-1600000)*21%,560000+(P26-3200000)*24%))))))) -> 10729.6 | R26: =Q26/12 -> 894.13333 | S26: =F26 -> 12 | T26: =+R26*S26 -> 10729.6
A27: 23 | B27: Moshood | C27: Rasheed | E27: Maintainance | F27: 12 | G27: 420000 | H27: 102400 | I27: 100 | J27: 7168 | L27: =G27 -> 420000 | M27: =L27*0.08 -> 33600 | N27: =L27-M27 -> 386400 | O27: =IF(N27<=300000,0,IF(N27>=20000000,(N27*0.21),(N27*0.2)+200000)) -> 277280 | P27: =+L27-O27-M27 -> 109120 | Q27: =IF(O27=0,(L27*0.01),IF(P27<=0,0.01*L27,IF(AND(P27>0,P27<=300000),P27*7%,IF(AND(P27>=300000,P27<600000),21000+(P27-300000)*11%,IF(AND(P27>=600000,P27<1100000),54000+(P27-600000)*15%,IF(AND(P27>=1100000,P27<1600000),129000+(P27-1100000)*19%,IF(AND(P27>=1600000,P27<3200000),224000+(P27-1600000)*21%,560000+(P27-3200000)*24%))))))) -> 7638.4 | R27: =Q27/12 -> 636.53333 | S27: =F27 -> 12 | T27: =+R27*S27 -> 7638.4
A28: 24 | B28: Babalola | C28: omolara | D28: A | E28: Cashier | F28: 12 | G28: 480000 | H28: 145600 | I28: 100 | J28: 10192 | L28: =G28 -> 480000 | M28: =L28*0.08 -> 38400 | N28: =L28-M28 -> 441600 | O28: =IF(N28<=300000,0,IF(N28>=20000000,(N28*0.21),(N28*0.2)+200000)) -> 288320 | P28: =+L28-O28-M28 -> 153280 | Q28: =IF(O28=0,(L28*0.01),IF(P28<=0,0.01*L28,IF(AND(P28>0,P28<=300000),P28*7%,IF(AND(P28>=300000,P28<600000),21000+(P28-300000)*11%,IF(AND(P28>=600000,P28<1100000),54000+(P28-600000)*15%,IF(AND(P28>=1100000,P28<1600000),129000+(P28-1100000)*19%,IF(AND(P28>=1600000,P28<3200000),224000+(P28-1600000)*21%,560000+(P28-3200000)*24%))))))) -> 10729.6 | R28: =Q28/12 -> 894.13333 | S28: =F28 -> 12 | T28: =+R28*S28 -> 10729.6
A29: 25 | B29: Ehiagwina | C29: E. | D29: Peter | E29: Manager | F29: 12 | G29: 660000 | H29: 275200 | I29: 100 | J29: 19264 | L29: =G29 -> 660000 | M29: =L29*0.08 -> 52800 | N29: =L29-M29 -> 607200 | O29: =IF(N29<=300000,0,IF(N29>=20000000,(N29*0.21),(N29*0.2)+200000)) -> 321440 | P29: =+L29-O29-M29 -> 285760 | Q29: =IF(O29=0,(L29*0.01),IF(P29<=0,0.01*L29,IF(AND(P29>0,P29<=300000),P29*7%,IF(AND(P29>=300000,P29<600000),21000+(P29-300000)*11%,IF(AND(P29>=600000,P29<1100000),54000+(P29-600000)*15%,IF(AND(P29>=1100000,P29<1600000),129000+(P29-1100000)*19%,IF(AND(P29>=1600000,P29<3200000),224000+(P29-1600000)*21%,560000+(P29-3200000)*24%))))))) -> 20003.2 | R29: =Q29/12 -> 1666.9333 | S29: =F29 -> 12 | T29: =+R29*S29 -> 20003.2
A30: 26 | B30: Oduyebo | C30: Samuel | E30: Manager | F30: 12 | G30: 540000 | H30: 188800 | I30: 100 | J30: 13216 | L30: =G30 -> 540000 | M30: =L30*0.08 -> 43200 | N30: =L30-M30 -> 496800 | O30: =IF(N30<=300000,0,IF(N30>=20000000,(N30*0.21),(N30*0.2)+200000)) -> 299360 | P30: =+L30-O30-M30 -> 197440 | Q30: =IF(O30=0,(L30*0.01),IF(P30<=0,0.01*L30,IF(AND(P30>0,P30<=300000),P30*7%,IF(AND(P30>=300000,P30<600000),21000+(P30-300000)*11%,IF(AND(P30>=600000,P30<1100000),54000+(P30-600000)*15%,IF(AND(P30>=1100000,P30<1600000),129000+(P30-1100000)*19%,IF(AND(P30>=1600000,P30<3200000),224000+(P30-1600000)*21%,560000+(P30-3200000)*24%))))))) -> 13820.8 | R30: =Q30/12 -> 1151.7333 | S30: =F30 -> 12 | T30: =+R30*S30 -> 13820.8
A31: 27 | B31: Ndukuba | C31: Uzoamaka | E31: Logistics Assistant 1 | F31: 12 | G31: 540000 | H31: 188800 | I31: 100 | J31: 13216 | L31: =G31 -> 540000 | M31: =L31*0.08 -> 43200 | N31: =L31-M31 -> 496800 | O31: =IF(N31<=300000,0,IF(N31>=20000000,(N31*0.21),(N31*0.2)+200000)) -> 299360 | P31: =+L31-O31-M31 -> 197440 | Q31: =IF(O31=0,(L31*0.01),IF(P31<=0,0.01*L31,IF(AND(P31>0,P31<=300000),P31*7%,IF(AND(P31>=300000,P31<600000),21000+(P31-300000)*11%,IF(AND(P31>=600000,P31<1100000),54000+(P31-600000)*15%,IF(AND(P31>=1100000,P31<1600000),129000+(P31-1100000)*19%,IF(AND(P31>=1600000,P31<3200000),224000+(P31-1600000)*21%,560000+(P31-3200000)*24%))))))) -> 13820.8 | R31: =Q31/12 -> 1151.7333 | S31: =F31 -> 12 | T31: =+R31*S31 -> 13820.8
A32: 28 | B32: Ajayi | C32: Olasunkanmi | D32: Tunde | E32: Purchase Assistant | F32: 12 | G32: 960000 | H32: 491200 | I32: 100 | J32: 42032 | L32: =G32 -> 960000 | M32: =L32*0.08 -> 76800 | N32: =L32-M32 -> 883200 | O32: =IF(N32<=300000,0,IF(N32>=20000000,(N32*0.21),(N32*0.2)+200000)) -> 376640 | P32: =+L32-O32-M32 -> 506560 | Q32: =IF(O32=0,(L32*0.01),IF(P32<=0,0.01*L32,IF(AND(P32>0,P32<=300000),P32*7%,IF(AND(P32>=300000,P32<600000),21000+(P32-300000)*11%,IF(AND(P32>=600000,P32<1100000),54000+(P32-600000)*15%,IF(AND(P32>=1100000,P32<1600000),129000+(P32-1100000)*19%,IF(AND(P32>=1600000,P32<3200000),224000+(P32-1600000)*21%,560000+(P32-3200000)*24%))))))) -> 43721.6 | R32: =Q32/12 -> 3643.4667 | S32: =F32 -> 12 | T32: =+R32*S32 -> 43721.6
A33: 29 | B33: Jolayemi | C33: Solomon | D33: Oluwaseun | E33: Instock & Transfer | F33: 12 | G33: 660000 | H33: 275200 | I33: 100 | J33: 19264 | L33: =G33 -> 660000 | M33: =L33*0.08 -> 52800 | N33: =L33-M33 -> 607200 | O33: =IF(N33<=300000,0,IF(N33>=20000000,(N33*0.21),(N33*0.2)+200000)) -> 321440 | P33: =+L33-O33-M33 -> 285760 | Q33: =IF(O33=0,(L33*0.01),IF(P33<=0,0.01*L33,IF(AND(P33>0,P33<=300000),P33*7%,IF(AND(P33>=300000,P33<600000),21000+(P33-300000)*11%,IF(AND(P33>=600000,P33<1100000),54000+(P33-600000)*15%,IF(AND(P33>=1100000,P33<1600000),129000+(P33-1100000)*19%,IF(AND(P33>=1600000,P33<3200000),224000+(P33-1600000)*21%,560000+(P33-3200000)*24%))))))) -> 20003.2 | R33: =Q33/12 -> 1666.9333 | S33: =F33 -> 12 | T33: =+R33*S33 -> 20003.2
A34: 30 | B34: Okpeahior | C34: Foster | E34: Accessory & Transfer | F34: 12 | G34: 660000 | H34: 275200 | I34: 100 | J34: 19264 | L34: =G34 -> 660000 | M34: =L34*0.08 -> 52800 | N34: =L34-M34 -> 607200 | O34: =IF(N34<=300000,0,IF(N34>=20000000,(N34*0.21),(N34*0.2)+200000)) -> 321440 | P34: =+L34-O34-M34 -> 285760 | Q34: =IF(O34=0,(L34*0.01),IF(P34<=0,0.01*L34,IF(AND(P34>0,P34<=300000),P34*7%,IF(AND(P34>=300000,P34<600000),21000+(P34-300000)*11%,IF(AND(P34>=600000,P34<1100000),54000+(P34-600000)*15%,IF(AND(P34>=1100000,P34<1600000),129000+(P34-1100000)*19%,IF(AND(P34>=1600000,P34<3200000),224000+(P34-1600000)*21%,560000+(P34-3200000)*24%))))))) -> 20003.2 | R34: =Q34/12 -> 1666.9333 | S34: =F34 -> 12 | T34: =+R34*S34 -> 20003.2
A35: 31 | B35: Alongo | C35: Babatunde | E35: Maintainance | F35: 12 | G35: 420000 | H35: 102400 | I35: 100 | J35: 7168 | L35: =G35 -> 420000 | M35: =L35*0.08 -> 33600 | N35: =L35-M35 -> 386400 | O35: =IF(N35<=300000,0,IF(N35>=20000000,(N35*0.21),(N35*0.2)+200000)) -> 277280 | P35: =+L35-O35-M35 -> 109120 | Q35: =IF(O35=0,(L35*0.01),IF(P35<=0,0.01*L35,IF(AND(P35>0,P35<=300000),P35*7%,IF(AND(P35>=300000,P35<600000),21000+(P35-300000)*11%,IF(AND(P35>=600000,P35<1100000),54000+(P35-600000)*15%,IF(AND(P35>=1100000,P35<1600000),129000+(P35-1100000)*19%,IF(AND(P35>=1600000,P35<3200000),224000+(P35-1600000)*21%,560000+(P35-3200000)*24%))))))) -> 7638.4 | R35: =Q35/12 -> 636.53333 | S35: =F35 -> 12 | T35: =+R35*S35 -> 7638.4
A36: 32 | B36: Gbamire | C36: Sunday | E36: Decoration officer | F36: 12 | G36: 600000 | H36: 232000 | I36: 100 | J36: 16240 | L36: =G36 -> 600000 | M36: =L36*0.08 -> 48000 | N36: =L36-M36 -> 552000 | O36: =IF(N36<=300000,0,IF(N36>=20000000,(N36*0.21),(N36*0.2)+200000)) -> 310400 | P36: =+L36-O36-M36 -> 241600 | Q36: =IF(O36=0,(L36*0.01),IF(P36<=0,0.01*L36,IF(AND(P36>0,P36<=300000),P36*7%,IF(AND(P36>=300000,P36<600000),21000+(P36-300000)*11%,IF(AND(P36>=600000,P36<1100000),54000+(P36-600000)*15%,IF(AND(P36>=1100000,P36<1600000),129000+(P36-1100000)*19%,IF(AND(P36>=1600000,P36<3200000),224000+(P36-1600000)*21%,560000+(P36-3200000)*24%))))))) -> 16912 | R36: =Q36/12 -> 1409.3333 | S36: =F36 -> 12 | T36: =+R36*S36 -> 16912
A37: 33 | B37: Aregbesola | C37: Joshua | E37: Transfer Assistant | F37: 12 | G37: 660000 | H37: 275200 | I37: 100 | J37: 19264 | L37: =G37 -> 660000 | M37: =L37*0.08 -> 52800 | N37: =L37-M37 -> 607200 | O37: =IF(N37<=300000,0,IF(N37>=20000000,(N37*0.21),(N37*0.2)+200000)) -> 321440 | P37: =+L37-O37-M37 -> 285760 | Q37: =IF(O37=0,(L37*0.01),IF(P37<=0,0.01*L37,IF(AND(P37>0,P37<=300000),P37*7%,IF(AND(P37>=300000,P37<600000),21000+(P37-300000)*11%,IF(AND(P37>=600000,P37<1100000),54000+(P37-600000)*15%,IF(AND(P37>=1100000,P37<1600000),129000+(P37-1100000)*19%,IF(AND(P37>=1600000,P37<3200000),224000+(P37-1600000)*21%,560000+(P37-3200000)*24%))))))) -> 20003.2 | R37: =Q37/12 -> 1666.9333 | S37: =F37 -> 12 | T37: =+R37*S37 -> 20003.2
A38: 34 | B38: Onayemi | C38: Olatunde | D38: Olalekan | E38: Regional Manager | F38: 12 | G38: 960000 | H38: 491200 | I38: 100 | J38: 42032 | L38: =G38 -> 960000 | M38: =L38*0.08 -> 76800 | N38: =L38-M38 -> 883200 | O38: =IF(N38<=300000,0,IF(N38>=20000000,(N38*0.21),(N38*0.2)+200000)) -> 376640 | P38: =+L38-O38-M38 -> 506560 | Q38: =IF(O38=0,(L38*0.01),IF(P38<=0,0.01*L38,IF(AND(P38>0,P38<=300000),P38*7%,IF(AND(P38>=300000,P38<600000),21000+(P38-300000)*11%,IF(AND(P38>=600000,P38<1100000),54000+(P38-600000)*15%,IF(AND(P38>=1100000,P38<1600000),129000+(P38-1100000)*19%,IF(AND(P38>=1600000,P38<3200000),224000+(P38-1600000)*21%,560000+(P38-3200000)*24%))))))) -> 43721.6 | R38: =Q38/12 -> 3643.4667 | S38: =F38 -> 12 | T38: =+R38*S38 -> 43721.6
A39: 35 | B39: Ifeanyi | C39: Osuji | D39: Franklin | E39: Store Supervisor | F39: 12 | G39: 540000 | H39: 188800 | I39: 100 | J39: 13216 | L39: =G39 -> 540000 | M39: =L39*0.08 -> 43200 | N39: =L39-M39 -> 496800 | O39: =IF(N39<=300000,0,IF(N39>=20000000,(N39*0.21),(N39*0.2)+200000)) -> 299360 | P39: =+L39-O39-M39 -> 197440 | Q39: =IF(O39=0,(L39*0.01),IF(P39<=0,0.01*L39,IF(AND(P39>0,P39<=300000),P39*7%,IF(AND(P39>=300000,P39<600000),21000+(P39-300000)*11%,IF(AND(P39>=600000,P39<1100000),54000+(P39-600000)*15%,IF(AND(P39>=1100000,P39<1600000),129000+(P39-1100000)*19%,IF(AND(P39>=1600000,P39<3200000),224000+(P39-1600000)*21%,560000+(P39-3200000)*24%))))))) -> 13820.8 | R39: =Q39/12 -> 1151.7333 | S39: =F39 -> 12 | T39: =+R39*S39 -> 13820.8
A40: 36 | B40: Gloria | C40: Awele | D40: Okonmah | E40: Manager | F40: 12 | G40: 540000 | H40: 188800 | I40: 100 | J40: 13216 | L40: =G40 -> 540000 | M40: =L40*0.08 -> 43200 | N40: =L40-M40 -> 496800 | O40: =IF(N40<=300000,0,IF(N40>=20000000,(N40*0.21),(N40*0.2)+200000)) -> 299360 | P40: =+L40-O40-M40 -> 197440 | Q40: =IF(O40=0,(L40*0.01),IF(P40<=0,0.01*L40,IF(AND(P40>0,P40<=300000),P40*7%,IF(AND(P40>=300000,P40<600000),21000+(P40-300000)*11%,IF(AND(P40>=600000,P40<1100000),54000+(P40-600000)*15%,IF(AND(P40>=1100000,P40<1600000),129000+(P40-1100000)*19%,IF(AND(P40>=1600000,P40<3200000),224000+(P40-1600000)*21%,560000+(P40-3200000)*24%))))))) -> 13820.8 | R40: =Q40/12 -> 1151.7333 | S40: =F40 -> 12 | T40: =+R40*S40 -> 13820.8
A41: 37 | B41: Adewunmi | C41: Ayomi | D41: Tunde | E41: Store Supervisor | F41: 12 | G41: 540000 | H41: 188800 | I41: 100 | J41: 13216 | L41: =G41 -> 540000 | M41: =L41*0.08 -> 43200 | N41: =L41-M41 -> 496800 | O41: =IF(N41<=300000,0,IF(N41>=20000000,(N41*0.21),(N41*0.2)+200000)) -> 299360 | P41: =+L41-O41-M41 -> 197440 | Q41: =IF(O41=0,(L41*0.01),IF(P41<=0,0.01*L41,IF(AND(P41>0,P41<=300000),P41*7%,IF(AND(P41>=300000,P41<600000),21000+(P41-300000)*11%,IF(AND(P41>=600000,P41<1100000),54000+(P41-600000)*15%,IF(AND(P41>=1100000,P41<1600000),129000+(P41-1100000)*19%,IF(AND(P41>=1600000,P41<3200000),224000+(P41-1600000)*21%,560000+(P41-3200000)*24%))))))) -> 13820.8 | R41: =Q41/12 -> 1151.7333 | S41: =F41 -> 12 | T41: =+R41*S41 -> 13820.8
A42: 38 | B42: ALICE | C42: GLORIA | D42: IDOBOGBE | E42: Cashier | F42: 12 | G42: 480000 | H42: 145600 | I42: 100 | J42: 10192 | L42: =G42 -> 480000 | M42: =L42*0.08 -> 38400 | N42: =L42-M42 -> 441600 | O42: =IF(N42<=300000,0,IF(N42>=20000000,(N42*0.21),(N42*0.2)+200000)) -> 288320 | P42: =+L42-O42-M42 -> 153280 | Q42: =IF(O42=0,(L42*0.01),IF(P42<=0,0.01*L42,IF(AND(P42>0,P42<=300000),P42*7%,IF(AND(P42>=300000,P42<600000),21000+(P42-300000)*11%,IF(AND(P42>=600000,P42<1100000),54000+(P42-600000)*15%,IF(AND(P42>=1100000,P42<1600000),129000+(P42-1100000)*19%,IF(AND(P42>=1600000,P42<3200000),224000+(P42-1600000)*21%,560000+(P42-3200000)*24%))))))) -> 10729.6 | R42: =Q42/12 -> 894.13333 | S42: =F42 -> 12 | T42: =+R42*S42 -> 10729.6
A43: 39 | B43: Iwalokun | C43: oluwatobi | E43: Cashier | F43: 12 | G43: 480000 | H43: 145600 | I43: 100 | J43: 10192 | L43: =G43 -> 480000 | M43: =L43*0.08 -> 38400 | N43: =L43-M43 -> 441600 | O43: =IF(N43<=300000,0,IF(N43>=20000000,(N43*0.21),(N43*0.2)+200000)) -> 288320 | P43: =+L43-O43-M43 -> 153280 | Q43: =IF(O43=0,(L43*0.01),IF(P43<=0,0.01*L43,IF(AND(P43>0,P43<=300000),P43*7%,IF(AND(P43>=300000,P43<600000),21000+(P43-300000)*11%,IF(AND(P43>=600000,P43<1100000),54000+(P43-600000)*15%,IF(AND(P43>=1100000,P43<1600000),129000+(P43-1100000)*19%,IF(AND(P43>=1600000,P43<3200000),224000+(P43-1600000)*21%,560000+(P43-3200000)*24%))))))) -> 10729.6 | R43: =Q43/12 -> 894.13333 | S43: =F43 -> 12 | T43: =+R43*S43 -> 10729.6
A44: 40 | B44: Olawuyi | C44: Damilola | E44: Electronics FSM | F44: 12 | G44: 420000 | H44: 102400 | I44: 100 | J44: 7168 | L44: =G44 -> 420000 | M44: =L44*0.08 -> 33600 | N44: =L44-M44 -> 386400 | O44: =IF(N44<=300000,0,IF(N44>=20000000,(N44*0.21),(N44*0.2)+200000)) -> 277280 | P44: =+L44-O44-M44 -> 109120 | Q44: =IF(O44=0,(L44*0.01),IF(P44<=0,0.01*L44,IF(AND(P44>0,P44<=300000),P44*7%,IF(AND(P44>=300000,P44<600000),21000+(P44-300000)*11%,IF(AND(P44>=600000,P44<1100000),54000+(P44-600000)*15%,IF(AND(P44>=1100000,P44<1600000),129000+(P44-1100000)*19%,IF(AND(P44>=1600000,P44<3200000),224000+(P44-1600000)*21%,560000+(P44-3200000)*24%))))))) -> 7638.4 | R44: =Q44/12 -> 636.53333 | S44: =F44 -> 12 | T44: =+R44*S44 -> 7638.4
A45: 41 | B45: Okparaku | C45: Chinonso | E45: Maintenance Assistant | F45: 12 | G45: 420000 | H45: 102400 | I45: 100 | J45: 7168 | L45: =G45 -> 420000 | M45: =L45*0.08 -> 33600 | N45: =L45-M45 -> 386400 | O45: =IF(N45<=300000,0,IF(N45>=20000000,(N45*0.21),(N45*0.2)+200000)) -> 277280 | P45: =+L45-O45-M45 -> 109120 | Q45: =IF(O45=0,(L45*0.01),IF(P45<=0,0.01*L45,IF(AND(P45>0,P45<=300000),P45*7%,IF(AND(P45>=300000,P45<600000),21000+(P45-300000)*11%,IF(AND(P45>=600000,P45<1100000),54000+(P45-600000)*15%,IF(AND(P45>=1100000,P45<1600000),129000+(P45-1100000)*19%,IF(AND(P45>=1600000,P45<3200000),224000+(P45-1600000)*21%,560000+(P45-3200000)*24%))))))) -> 7638.4 | R45: =Q45/12 -> 636.53333 | S45: =F45 -> 12 | T45: =+R45*S45 -> 7638.4
A46: 42 | B46: Odeyemi | C46: Grace. | D46: K. | E46: Cashier | F46: 12 | G46: 480000 | H46: 145600 | I46: 100 | J46: 10192 | L46: =G46 -> 480000 | M46: =L46*0.08 -> 38400 | N46: =L46-M46 -> 441600 | O46: =IF(N46<=300000,0,IF(N46>=20000000,(N46*0.21),(N46*0.2)+200000)) -> 288320 | P46: =+L46-O46-M46 -> 153280 | Q46: =IF(O46=0,(L46*0.01),IF(P46<=0,0.01*L46,IF(AND(P46>0,P46<=300000),P46*7%,IF(AND(P46>=300000,P46<600000),21000+(P46-300000)*11%,IF(AND(P46>=600000,P46<1100000),54000+(P46-600000)*15%,IF(AND(P46>=1100000,P46<1600000),129000+(P46-1100000)*19%,IF(AND(P46>=1600000,P46<3200000),224000+(P46-1600000)*21%,560000+(P46-3200000)*24%))))))) -> 10729.6 | R46: =Q46/12 -> 894.13333 | S46: =F46 -> 12 | T46: =+R46*S46 -> 10729.6
A47: 43 | B47: Sanni | C47: Oluwatoyin | E47: Franchise Officer-general | F47: 12 | G47: 480000 | H47: 145600 | I47: 100 | J47: 10192 | L47: =G47 -> 480000 | M47: =L47*0.08 -> 38400 | N47: =L47-M47 -> 441600 | O47: =IF(N47<=300000,0,IF(N47>=20000000,(N47*0.21),(N47*0.2)+200000)) -> 288320 | P47: =+L47-O47-M47 -> 153280 | Q47: =IF(O47=0,(L47*0.01),IF(P47<=0,0.01*L47,IF(AND(P47>0,P47<=300000),P47*7%,IF(AND(P47>=300000,P47<600000),21000+(P47-300000)*11%,IF(AND(P47>=600000,P47<1100000),54000+(P47-600000)*15%,IF(AND(P47>=1100000,P47<1600000),129000+(P47-1100000)*19%,IF(AND(P47>=1600000,P47<3200000),224000+(P47-1600000)*21%,560000+(P47-3200000)*24%))))))) -> 10729.6 | R47: =Q47/12 -> 894.13333 | S47: =F47 -> 12 | T47: =+R47*S47 -> 10729.6
A48: 44 | B48: Oguntola | C48: Tunji | E48: Store Management | F48: 12 | G48: 600000 | H48: 232000 | I48: 100 | J48: 16240 | L48: =G48 -> 600000 | M48: =L48*0.08 -> 48000 | N48: =L48-M48 -> 552000 | O48: =IF(N48<=300000,0,IF(N48>=20000000,(N48*0.21),(N48*0.2)+200000)) -> 310400 | P48: =+L48-O48-M48 -> 241600 | Q48: =IF(O48=0,(L48*0.01),IF(P48<=0,0.01*L48,IF(AND(P48>0,P48<=300000),P48*7%,IF(AND(P48>=300000,P48<600000),21000+(P48-300000)*11%,IF(AND(P48>=600000,P48<1100000),54000+(P48-600000)*15%,IF(AND(P48>=1100000,P48<1600000),129000+(P48-1100000)*19%,IF(AND(P48>=1600000,P48<3200000),224000+(P48-1600000)*21%,560000+(P48-3200000)*24%))))))) -> 16912 | R48: =Q48/12 -> 1409.3333 | S48: =F48 -> 12 | T48: =+R48*S48 -> 16912
A49: 45 | B49: Adegbite | C49: Fatai | E49: Store Supervisor | F49: 12 | G49: 540000 | H49: 188800 | I49: 100 | J49: 13216 | L49: =G49 -> 540000 | M49: =L49*0.08 -> 43200 | N49: =L49-M49 -> 496800 | O49: =IF(N49<=300000,0,IF(N49>=20000000,(N49*0.21),(N49*0.2)+200000)) -> 299360 | P49: =+L49-O49-M49 -> 197440 | Q49: =IF(O49=0,(L49*0.01),IF(P49<=0,0.01*L49,IF(AND(P49>0,P49<=300000),P49*7%,IF(AND(P49>=300000,P49<600000),21000+(P49-300000)*11%,IF(AND(P49>=600000,P49<1100000),54000+(P49-600000)*15%,IF(AND(P49>=1100000,P49<1600000),129000+(P49-1100000)*19%,IF(AND(P49>=1600000,P49<3200000),224000+(P49-1600000)*21%,560000+(P49-3200000)*24%))))))) -> 13820.8 | R49: =Q49/12 -> 1151.7333 | S49: =F49 -> 12 | T49: =+R49*S49 -> 13820.8
A50: 46 | B50: Dairo | C50: Gloria | D50: Temitope | E50: Manager | F50: 12 | G50: 540000 | H50: 188800 | I50: 100 | J50: 13216 | L50: =G50 -> 540000 | M50: =L50*0.08 -> 43200 | N50: =L50-M50 -> 496800 | O50: =IF(N50<=300000,0,IF(N50>=20000000,(N50*0.21),(N50*0.2)+200000)) -> 299360 | P50: =+L50-O50-M50 -> 197440 | Q50: =IF(O50=0,(L50*0.01),IF(P50<=0,0.01*L50,IF(AND(P50>0,P50<=300000),P50*7%,IF(AND(P50>=300000,P50<600000),21000+(P50-300000)*11%,IF(AND(P50>=600000,P50<1100000),54000+(P50-600000)*15%,IF(AND(P50>=1100000,P50<1600000),129000+(P50-1100000)*19%,IF(AND(P50>=1600000,P50<3200000),224000+(P50-1600000)*21%,560000+(P50-3200000)*24%))))))) -> 13820.8 | R50: =Q50/12 -> 1151.7333 | S50: =F50 -> 12 | T50: =+R50*S50 -> 13820.8
A51: 47 | B51: Njoku | C51: Doris | D51: Oluchi | E51: HR | F51: 12 | G51: 1560000 | H51: 923200 | I51: 100 | J51: 102480 | L51: =G51 -> 1560000 | M51: =L51*0.08 -> 124800 | N51: =L51-M51 -> 1435200 | O51: =IF(N51<=300000,0,IF(N51>=20000000,(N51*0.21),(N51*0.2)+200000)) -> 487040 | P51: =+L51-O51-M51 -> 948160 | Q51: =IF(O51=0,(L51*0.01),IF(P51<=0,0.01*L51,IF(AND(P51>0,P51<=300000),P51*7%,IF(AND(P51>=300000,P51<600000),21000+(P51-300000)*11%,IF(AND(P51>=600000,P51<1100000),54000+(P51-600000)*15%,IF(AND(P51>=1100000,P51<1600000),129000+(P51-1100000)*19%,IF(AND(P51>=1600000,P51<3200000),224000+(P51-1600000)*21%,560000+(P51-3200000)*24%))))))) -> 106224 | R51: =Q51/12 -> 8852 | S51: =F51 -> 12 | T51: =+R51*S51 -> 106224
A52: 48 | B52: Ogungboye | C52: Bukola | D52: Ganiyat | E52: Store Supervisor | F52: 12 | G52: 540000 | H52: 188800 | I52: 100 | J52: 13216 | L52: =G52 -> 540000 | M52: =L52*0.08 -> 43200 | N52: =L52-M52 -> 496800 | O52: =IF(N52<=300000,0,IF(N52>=20000000,(N52*0.21),(N52*0.2)+200000)) -> 299360 | P52: =+L52-O52-M52 -> 197440 | Q52: =IF(O52=0,(L52*0.01),IF(P52<=0,0.01*L52,IF(AND(P52>0,P52<=300000),P52*7%,IF(AND(P52>=300000,P52<600000),21000+(P52-300000)*11%,IF(AND(P52>=600000,P52<1100000),54000+(P52-600000)*15%,IF(AND(P52>=1100000,P52<1600000),129000+(P52-1100000)*19%,IF(AND(P52>=1600000,P52<3200000),224000+(P52-1600000)*21%,560000+(P52-3200000)*24%))))))) -> 13820.8 | R52: =Q52/12 -> 1151.7333 | S52: =F52 -> 12 | T52: =+R52*S52 -> 13820.8
A53: 49 | B53: Rafiu | C53: Abiola | D53: Sodiq | E53: Logistics Officer | F53: 12 | G53: 840000 | H53: 404800 | I53: 100 | J53: 32528 | L53: =G53 -> 840000 | M53: =L53*0.08 -> 67200 | N53: =L53-M53 -> 772800 | O53: =IF(N53<=300000,0,IF(N53>=20000000,(N53*0.21),(N53*0.2)+200000)) -> 354560 | P53: =+L53-O53-M53 -> 418240 | Q53: =IF(O53=0,(L53*0.01),IF(P53<=0,0.01*L53,IF(AND(P53>0,P53<=300000),P53*7%,IF(AND(P53>=300000,P53<600000),21000+(P53-300000)*11%,IF(AND(P53>=600000,P53<1100000),54000+(P53-600000)*15%,IF(AND(P53>=1100000,P53<1600000),129000+(P53-1100000)*19%,IF(AND(P53>=1600000,P53<3200000),224000+(P53-1600000)*21%,560000+(P53-3200000)*24%))))))) -> 34006.4 | R53: =Q53/12 -> 2833.8667 | S53: =F53 -> 12 | T53: =+R53*S53 -> 34006.4
A54: 50 | B54: Abdulkadir | C54: Idoko | D54: Haruna | E54: Regional Manager | F54: 12 | G54: 960000 | H54: 491200 | I54: 100 | J54: 42032 | L54: =G54 -> 960000 | M54: =L54*0.08 -> 76800 | N54: =L54-M54 -> 883200 | O54: =IF(N54<=300000,0,IF(N54>=20000000,(N54*0.21),(N54*0.2)+200000)) -> 376640 | P54: =+L54-O54-M54 -> 506560 | Q54: =IF(O54=0,(L54*0.01),IF(P54<=0,0.01*L54,IF(AND(P54>0,P54<=300000),P54*7%,IF(AND(P54>=300000,P54<600000),21000+(P54-300000)*11%,IF(AND(P54>=600000,P54<1100000),54000+(P54-600000)*15%,IF(AND(P54>=1100000,P54<1600000),129000+(P54-1100000)*19%,IF(AND(P54>=1600000,P54<3200000),224000+(P54-1600000)*21%,560000+(P54-3200000)*24%))))))) -> 43721.6 | R54: =Q54/12 -> 3643.4667 | S54: =F54 -> 12 | T54: =+R54*S54 -> 43721.6
A55: 51 | B55: Jonathan | C55: Yesufu | D55: Afekorioh | E55: Security Officer | F55: 12 | G55: 660000 | H55: 275200 | I55: 100 | J55: 19264 | L55: =G55 -> 660000 | M55: =L55*0.08 -> 52800 | N55: =L55-M55 -> 607200 | O55: =IF(N55<=300000,0,IF(N55>=20000000,(N55*0.21),(N55*0.2)+200000)) -> 321440 | P55: =+L55-O55-M55 -> 285760 | Q55: =IF(O55=0,(L55*0.01),IF(P55<=0,0.01*L55,IF(AND(P55>0,P55<=300000),P55*7%,IF(AND(P55>=300000,P55<600000),21000+(P55-300000)*11%,IF(AND(P55>=600000,P55<1100000),54000+(P55-600000)*15%,IF(AND(P55>=1100000,P55<1600000),129000+(P55-1100000)*19%,IF(AND(P55>=1600000,P55<3200000),224000+(P55-1600000)*21%,560000+(P55-3200000)*24%))))))) -> 20003.2 | R55: =Q55/12 -> 1666.9333 | S55: =F55 -> 12 | T55: =+R55*S55 -> 20003.2
A56: 52 | B56: Nwachukwu | C56: Wisdom | E56: Driver | F56: 12 | G56: 480000 | H56: 145600 | I56: 100 | J56: 10192 | L56: =G56 -> 480000 | M56: =L56*0.08 -> 38400 | N56: =L56-M56 -> 441600 | O56: =IF(N56<=300000,0,IF(N56>=20000000,(N56*0.21),(N56*0.2)+200000)) -> 288320 | P56: =+L56-O56-M56 -> 153280 | Q56: =IF(O56=0,(L56*0.01),IF(P56<=0,0.01*L56,IF(AND(P56>0,P56<=300000),P56*7%,IF(AND(P56>=300000,P56<600000),21000+(P56-300000)*11%,IF(AND(P56>=600000,P56<1100000),54000+(P56-600000)*15%,IF(AND(P56>=1100000,P56<1600000),129000+(P56-1100000)*19%,IF(AND(P56>=1600000,P56<3200000),224000+(P56-1600000)*21%,560000+(P56-3200000)*24%))))))) -> 10729.6 | R56: =Q56/12 -> 894.13333 | S56: =F56 -> 12 | T56: =+R56*S56 -> 10729.6
A57: 53 | B57: Vivian | C57: Duruzor | D57: Ugbe | E57: Cashier | F57: 12 | G57: 480000 | H57: 145600 | I57: 100 | J57: 10192 | L57: =G57 -> 480000 | M57: =L57*0.08 -> 38400 | N57: =L57-M57 -> 441600 | O57: =IF(N57<=300000,0,IF(N57>=20000000,(N57*0.21),(N57*0.2)+200000)) -> 288320 | P57: =+L57-O57-M57 -> 153280 | Q57: =IF(O57=0,(L57*0.01),IF(P57<=0,0.01*L57,IF(AND(P57>0,P57<=300000),P57*7%,IF(AND(P57>=300000,P57<600000),21000+(P57-300000)*11%,IF(AND(P57>=600000,P57<1100000),54000+(P57-600000)*15%,IF(AND(P57>=1100000,P57<1600000),129000+(P57-1100000)*19%,IF(AND(P57>=1600000,P57<3200000),224000+(P57-1600000)*21%,560000+(P57-3200000)*24%))))))) -> 10729.6 | R57: =Q57/12 -> 894.13333 | S57: =F57 -> 12 | T57: =+R57*S57 -> 10729.6
A58: 54 | B58: John | C58: Oreva | D58: Ikokide | E58: Manager | F58: 12 | G58: 540000 | H58: 188800 | I58: 100 | J58: 13216 | L58: =G58 -> 540000 | M58: =L58*0.08 -> 43200 | N58: =L58-M58 -> 496800 | O58: =IF(N58<=300000,0,IF(N58>=20000000,(N58*0.21),(N58*0.2)+200000)) -> 299360 | P58: =+L58-O58-M58 -> 197440 | Q58: =IF(O58=0,(L58*0.01),IF(P58<=0,0.01*L58,IF(AND(P58>0,P58<=300000),P58*7%,IF(AND(P58>=300000,P58<600000),21000+(P58-300000)*11%,IF(AND(P58>=600000,P58<1100000),54000+(P58-600000)*15%,IF(AND(P58>=1100000,P58<1600000),129000+(P58-1100000)*19%,IF(AND(P58>=1600000,P58<3200000),224000+(P58-1600000)*21%,560000+(P58-3200000)*24%))))))) -> 13820.8 | R58: =Q58/12 -> 1151.7333 | S58: =F58 -> 12 | T58: =+R58*S58 -> 13820.8
A59: 55 | B59: Emuze | C59: Smart | D59: Osas | E59: Data Analyst | F59: 12 | G59: 480000 | H59: 145600 | I59: 100 | J59: 10192 | L59: =G59 -> 480000 | M59: =L59*0.08 -> 38400 | N59: =L59-M59 -> 441600 | O59: =IF(N59<=300000,0,IF(N59>=20000000,(N59*0.21),(N59*0.2)+200000)) -> 288320 | P59: =+L59-O59-M59 -> 153280 | Q59: =IF(O59=0,(L59*0.01),IF(P59<=0,0.01*L59,IF(AND(P59>0,P59<=300000),P59*7%,IF(AND(P59>=300000,P59<600000),21000+(P59-300000)*11%,IF(AND(P59>=600000,P59<1100000),54000+(P59-600000)*15%,IF(AND(P59>=1100000,P59<1600000),129000+(P59-1100000)*19%,IF(AND(P59>=1600000,P59<3200000),224000+(P59-1600000)*21%,560000+(P59-3200000)*24%))))))) -> 10729.6 | R59: =Q59/12 -> 894.13333 | S59: =F59 -> 12 | T59: =+R59*S59 -> 10729.6
A60: 56 | B60: Otunuga | C60: Williams | E60: Purchase Assistant | F60: 12 | G60: 660000 | H60: 275200 | I60: 100 | J60: 19264 | L60: =G60 -> 660000 | M60: =L60*0.08 -> 52800 | N60: =L60-M60 -> 607200 | O60: =IF(N60<=300000,0,IF(N60>=20000000,(N60*0.21),(N60*0.2)+200000)) -> 321440 | P60: =+L60-O60-M60 -> 285760 | Q60: =IF(O60=0,(L60*0.01),IF(P60<=0,0.01*L60,IF(AND(P60>0,P60<=300000),P60*7%,IF(AND(P60>=300000,P60<600000),21000+(P60-300000)*11%,IF(AND(P60>=600000,P60<1100000),54000+(P60-600000)*15%,IF(AND(P60>=1100000,P60<1600000),129000+(P60-1100000)*19%,IF(AND(P60>=1600000,P60<3200000),224000+(P60-1600000)*21%,560000+(P60-3200000)*24%))))))) -> 20003.2 | R60: =Q60/12 -> 1666.9333 | S60: =F60 -> 12 | T60: =+R60*S60 -> 20003.2
A61: 57 | B61: Dada | C61: Israel | E61: Manager | F61: 12 | G61: 660000 | H61: 275200 | I61: 100 | J61: 19264 | L61: =G61 -> 660000 | M61: =L61*0.08 -> 52800 | N61: =L61-M61 -> 607200 | O61: =IF(N61<=300000,0,IF(N61>=20000000,(N61*0.21),(N61*0.2)+200000)) -> 321440 | P61: =+L61-O61-M61 -> 285760 | Q61: =IF(O61=0,(L61*0.01),IF(P61<=0,0.01*L61,IF(AND(P61>0,P61<=300000),P61*7%,IF(AND(P61>=300000,P61<600000),21000+(P61-300000)*11%,IF(AND(P61>=600000,P61<1100000),54000+(P61-600000)*15%,IF(AND(P61>=1100000,P61<1600000),129000+(P61-1100000)*19%,IF(AND(P61>=1600000,P61<3200000),224000+(P61-1600000)*21%,560000+(P61-3200000)*24%))))))) -> 20003.2 | R61: =Q61/12 -> 1666.9333 | S61: =F61 -> 12 | T61: =+R61*S61 -> 20003.2
A62: 58 | B62: Chidiebere | C62: Emeka | D62: .O. | E62: Maintainance | F62: 12 | G62: 420000 | H62: 102400 | I62: 100 | J62: 7168 | L62: =G62 -> 420000 | M62: =L62*0.08 -> 33600 | N62: =L62-M62 -> 386400 | O62: =IF(N62<=300000,0,IF(N62>=20000000,(N62*0.21),(N62*0.2)+200000)) -> 277280 | P62: =+L62-O62-M62 -> 109120 | Q62: =IF(O62=0,(L62*0.01),IF(P62<=0,0.01*L62,IF(AND(P62>0,P62<=300000),P62*7%,IF(AND(P62>=300000,P62<600000),21000+(P62-300000)*11%,IF(AND(P62>=600000,P62<1100000),54000+(P62-600000)*15%,IF(AND(P62>=1100000,P62<1600000),129000+(P62-1100000)*19%,IF(AND(P62>=1600000,P62<3200000),224000+(P62-1600000)*21%,560000+(P62-3200000)*24%))))))) -> 7638.4 | R62: =Q62/12 -> 636.53333 | S62: =F62 -> 12 | T62: =+R62*S62 -> 7638.4
A63: 59 | B63: Ajibola | C63: Rasaq | D63: Akin | E63: Aftersales Officer | F63: 12 | G63: 480000 | H63: 145600 | I63: 100 | J63: 10192 | L63: =G63 -> 480000 | M63: =L63*0.08 -> 38400 | N63: =L63-M63 -> 441600 | O63: =IF(N63<=300000,0,IF(N63>=20000000,(N63*0.21),(N63*0.2)+200000)) -> 288320 | P63: =+L63-O63-M63 -> 153280 | Q63: =IF(O63=0,(L63*0.01),IF(P63<=0,0.01*L63,IF(AND(P63>0,P63<=300000),P63*7%,IF(AND(P63>=300000,P63<600000),21000+(P63-300000)*11%,IF(AND(P63>=600000,P63<1100000),54000+(P63-600000)*15%,IF(AND(P63>=1100000,P63<1600000),129000+(P63-1100000)*19%,IF(AND(P63>=1600000,P63<3200000),224000+(P63-1600000)*21%,560000+(P63-3200000)*24%))))))) -> 10729.6 | R63: =Q63/12 -> 894.13333 | S63: =F63 -> 12 | T63: =+R63*S63 -> 10729.6
A64: 60 | B64: Victoria | C64: John | E64: Account officer | F64: 12 | G64: 660000 | H64: 275200 | I64: 100 | J64: 19264 | L64: =G64 -> 660000 | M64: =L64*0.08 -> 52800 | N64: =L64-M64 -> 607200 | O64: =IF(N64<=300000,0,IF(N64>=20000000,(N64*0.21),(N64*0.2)+200000)) -> 321440 | P64: =+L64-O64-M64 -> 285760 | Q64: =IF(O64=0,(L64*0.01),IF(P64<=0,0.01*L64,IF(AND(P64>0,P64<=300000),P64*7%,IF(AND(P64>=300000,P64<600000),21000+(P64-300000)*11%,IF(AND(P64>=600000,P64<1100000),54000+(P64-600000)*15%,IF(AND(P64>=1100000,P64<1600000),129000+(P64-1100000)*19%,IF(AND(P64>=1600000,P64<3200000),224000+(P64-1600000)*21%,560000+(P64-3200000)*24%))))))) -> 20003.2 | R64: =Q64/12 -> 1666.9333 | S64: =F64 -> 12 | T64: =+R64*S64 -> 20003.2
A65: 61 | B65: Taiwo | C65: Mathew | E65: Store Supervisor | F65: 12 | G65: 540000 | H65: 188800 | I65: 100 | J65: 13216 | L65: =G65 -> 540000 | M65: =L65*0.08 -> 43200 | N65: =L65-M65 -> 496800 | O65: =IF(N65<=300000,0,IF(N65>=20000000,(N65*0.21),(N65*0.2)+200000)) -> 299360 | P65: =+L65-O65-M65 -> 197440 | Q65: =IF(O65=0,(L65*0.01),IF(P65<=0,0.01*L65,IF(AND(P65>0,P65<=300000),P65*7%,IF(AND(P65>=300000,P65<600000),21000+(P65-300000)*11%,IF(AND(P65>=600000,P65<1100000),54000+(P65-600000)*15%,IF(AND(P65>=1100000,P65<1600000),129000+(P65-1100000)*19%,IF(AND(P65>=1600000,P65<3200000),224000+(P65-1600000)*21%,560000+(P65-3200000)*24%))))))) -> 13820.8 | R65: =Q65/12 -> 1151.7333 | S65: =F65 -> 12 | T65: =+R65*S65 -> 13820.8
A66: 62 | B66: Olasunkanmi | C66: Isaac | D66: Abiodun | E66: Manager | F66: 12 | G66: 540000 | H66: 188800 | I66: 100 | J66: 13216 | L66: =G66 -> 540000 | M66: =L66*0.08 -> 43200 | N66: =L66-M66 -> 496800 | O66: =IF(N66<=300000,0,IF(N66>=20000000,(N66*0.21),(N66*0.2)+200000)) -> 299360 | P66: =+L66-O66-M66 -> 197440 | Q66: =IF(O66=0,(L66*0.01),IF(P66<=0,0.01*L66,IF(AND(P66>0,P66<=300000),P66*7%,IF(AND(P66>=300000,P66<600000),21000+(P66-300000)*11%,IF(AND(P66>=600000,P66<1100000),54000+(P66-600000)*15%,IF(AND(P66>=1100000,P66<1600000),129000+(P66-1100000)*19%,IF(AND(P66>=1600000,P66<3200000),224000+(P66-1600000)*21%,560000+(P66-3200000)*24%))))))) -> 13820.8 | R66: =Q66/12 -> 1151.7333 | S66: =F66 -> 12 | T66: =+R66*S66 -> 13820.8
A67: 63 | B67: Adeola | C67: A.Openaike | E67: Material Officer | F67: 12 | G67: 540000 | H67: 188800 | I67: 100 | J67: 13216 | L67: =G67 -> 540000 | M67: =L67*0.08 -> 43200 | N67: =L67-M67 -> 496800 | O67: =IF(N67<=300000,0,IF(N67>=20000000,(N67*0.21),(N67*0.2)+200000)) -> 299360 | P67: =+L67-O67-M67 -> 197440 | Q67: =IF(O67=0,(L67*0.01),IF(P67<=0,0.01*L67,IF(AND(P67>0,P67<=300000),P67*7%,IF(AND(P67>=300000,P67<600000),21000+(P67-300000)*11%,IF(AND(P67>=600000,P67<1100000),54000+(P67-600000)*15%,IF(AND(P67>=1100000,P67<1600000),129000+(P67-1100000)*19%,IF(AND(P67>=1600000,P67<3200000),224000+(P67-1600000)*21%,560000+(P67-3200000)*24%))))))) -> 13820.8 | R67: =Q67/12 -> 1151.7333 | S67: =F67 -> 12 | T67: =+R67*S67 -> 13820.8
A68: 64 | B68: Banuso | C68: Michael | E68: Franchise Officer-general | F68: 12 | G68: 540000 | H68: 188800 | I68: 100 | J68: 13216 | L68: =G68 -> 540000 | M68: =L68*0.08 -> 43200 | N68: =L68-M68 -> 496800 | O68: =IF(N68<=300000,0,IF(N68>=20000000,(N68*0.21),(N68*0.2)+200000)) -> 299360 | P68: =+L68-O68-M68 -> 197440 | Q68: =IF(O68=0,(L68*0.01),IF(P68<=0,0.01*L68,IF(AND(P68>0,P68<=300000),P68*7%,IF(AND(P68>=300000,P68<600000),21000+(P68-300000)*11%,IF(AND(P68>=600000,P68<1100000),54000+(P68-600000)*15%,IF(AND(P68>=1100000,P68<1600000),129000+(P68-1100000)*19%,IF(AND(P68>=1600000,P68<3200000),224000+(P68-1600000)*21%,560000+(P68-3200000)*24%))))))) -> 13820.8 | R68: =Q68/12 -> 1151.7333 | S68: =F68 -> 12 | T68: =+R68*S68 -> 13820.8
A69: 65 | B69: Musbau | C69: Salam | E69: Project Manager | F69: 12 | G69: 1200000 | H69: 664000 | I69: 100 | J69: 63600 | L69: =G69 -> 1200000 | M69: =L69*0.08 -> 96000 | N69: =L69-M69 -> 1104000 | O69: =IF(N69<=300000,0,IF(N69>=20000000,(N69*0.21),(N69*0.2)+200000)) -> 420800 | P69: =+L69-O69-M69 -> 683200 | Q69: =IF(O69=0,(L69*0.01),IF(P69<=0,0.01*L69,IF(AND(P69>0,P69<=300000),P69*7%,IF(AND(P69>=300000,P69<600000),21000+(P69-300000)*11%,IF(AND(P69>=600000,P69<1100000),54000+(P69-600000)*15%,IF(AND(P69>=1100000,P69<1600000),129000+(P69-1100000)*19%,IF(AND(P69>=1600000,P69<3200000),224000+(P69-1600000)*21%,560000+(P69-3200000)*24%))))))) -> 66480 | R69: =Q69/12 -> 5540 | S69: =F69 -> 12 | T69: =+R69*S69 -> 66480
A70: 66 | B70: Adalemo | C70: Babatope | E70: Store Supervisor | F70: 12 | G70: 540000 | H70: 188800 | I70: 100 | J70: 13216 | L70: =G70 -> 540000 | M70: =L70*0.08 -> 43200 | N70: =L70-M70 -> 496800 | O70: =IF(N70<=300000,0,IF(N70>=20000000,(N70*0.21),(N70*0.2)+200000)) -> 299360 | P70: =+L70-O70-M70 -> 197440 | Q70: =IF(O70=0,(L70*0.01),IF(P70<=0,0.01*L70,IF(AND(P70>0,P70<=300000),P70*7%,IF(AND(P70>=300000,P70<600000),21000+(P70-300000)*11%,IF(AND(P70>=600000,P70<1100000),54000+(P70-600000)*15%,IF(AND(P70>=1100000,P70<1600000),129000+(P70-1100000)*19%,IF(AND(P70>=1600000,P70<3200000),224000+(P70-1600000)*21%,560000+(P70-3200000)*24%))))))) -> 13820.8 | R70: =Q70/12 -> 1151.7333 | S70: =F70 -> 12 | T70: =+R70*S70 -> 13820.8
A71: 67 | B71: Alex | C71: Aleburu | E71: Maintainance | F71: 12 | G71: 420000 | H71: 102400 | I71: 100 | J71: 7168 | L71: =G71 -> 420000 | M71: =L71*0.08 -> 33600 | N71: =L71-M71 -> 386400 | O71: =IF(N71<=300000,0,IF(N71>=20000000,(N71*0.21),(N71*0.2)+200000)) -> 277280 | P71: =+L71-O71-M71 -> 109120 | Q71: =IF(O71=0,(L71*0.01),IF(P71<=0,0.01*L71,IF(AND(P71>0,P71<=300000),P71*7%,IF(AND(P71>=300000,P71<600000),21000+(P71-300000)*11%,IF(AND(P71>=600000,P71<1100000),54000+(P71-600000)*15%,IF(AND(P71>=1100000,P71<1600000),129000+(P71-1100000)*19%,IF(AND(P71>=1600000,P71<3200000),224000+(P71-1600000)*21%,560000+(P71-3200000)*24%))))))) -> 7638.4 | R71: =Q71/12 -> 636.53333 | S71: =F71 -> 12 | T71: =+R71*S71 -> 7638.4
A72: 68 | B72: Oyeniyi | C72: Samson | D72: Olayiwole | E72: Legal Adviser | F72: 12 | G72: 1800000 | H72: 1096000 | I72: 100 | J72: 128400 | L72: =G72 -> 1800000 | M72: =L72*0.08 -> 144000 | N72: =L72-M72 -> 1656000 | O72: =IF(N72<=300000,0,IF(N72>=20000000,(N72*0.21),(N72*0.2)+200000)) -> 531200 | P72: =+L72-O72-M72 -> 1124800 | Q72: =IF(O72=0,(L72*0.01),IF(P72<=0,0.01*L72,IF(AND(P72>0,P72<=300000),P72*7%,IF(AND(P72>=300000,P72<600000),21000+(P72-300000)*11%,IF(AND(P72>=600000,P72<1100000),54000+(P72-600000)*15%,IF(AND(P72>=1100000,P72<1600000),129000+(P72-1100000)*19%,IF(AND(P72>=1600000,P72<3200000),224000+(P72-1600000)*21%,560000+(P72-3200000)*24%))))))) -> 133712 | R72: =Q72/12 -> 11142.667 | S72: =F72 -> 12 | T72: =+R72*S72 -> 133712
A73: 69 | B73: Adeboye | C73: Adewale | E73: Store keeper | F73: 12 | G73: 480000 | H73: 145600 | I73: 100 | J73: 10192 | L73: =G73 -> 480000 | M73: =L73*0.08 -> 38400 | N73: =L73-M73 -> 441600 | O73: =IF(N73<=300000,0,IF(N73>=20000000,(N73*0.21),(N73*0.2)+200000)) -> 288320 | P73: =+L73-O73-M73 -> 153280 | Q73: =IF(O73=0,(L73*0.01),IF(P73<=0,0.01*L73,IF(AND(P73>0,P73<=300000),P73*7%,IF(AND(P73>=300000,P73<600000),21000+(P73-300000)*11%,IF(AND(P73>=600000,P73<1100000),54000+(P73-600000)*15%,IF(AND(P73>=1100000,P73<1600000),129000+(P73-1100000)*19%,IF(AND(P73>=1600000,P73<3200000),224000+(P73-1600000)*21%,560000+(P73-3200000)*24%))))))) -> 10729.6 | R73: =Q73/12 -> 894.13333 | S73: =F73 -> 12 | T73: =+R73*S73 -> 10729.6
A74: 70 | B74: Adekunle | C74: David | E74: Store Supervisor | F74: 12 | G74: 540000 | H74: 188800 | I74: 100 | J74: 13216 | L74: =G74 -> 540000 | M74: =L74*0.08 -> 43200 | N74: =L74-M74 -> 496800 | O74: =IF(N74<=300000,0,IF(N74>=20000000,(N74*0.21),(N74*0.2)+200000)) -> 299360 | P74: =+L74-O74-M74 -> 197440 | Q74: =IF(O74=0,(L74*0.01),IF(P74<=0,0.01*L74,IF(AND(P74>0,P74<=300000),P74*7%,IF(AND(P74>=300000,P74<600000),21000+(P74-300000)*11%,IF(AND(P74>=600000,P74<1100000),54000+(P74-600000)*15%,IF(AND(P74>=1100000,P74<1600000),129000+(P74-1100000)*19%,IF(AND(P74>=1600000,P74<3200000),224000+(P74-1600000)*21%,560000+(P74-3200000)*24%))))))) -> 13820.8 | R74: =Q74/12 -> 1151.7333 | S74: =F74 -> 12 | T74: =+R74*S74 -> 13820.8
A75: 71 | B75: Adeleye | C75: Adeola | E75: Cashier | F75: 12 | G75: 480000 | H75: 145600 | I75: 100 | J75: 10192 | L75: =G75 -> 480000 | M75: =L75*0.08 -> 38400 | N75: =L75-M75 -> 441600 | O75: =IF(N75<=300000,0,IF(N75>=20000000,(N75*0.21),(N75*0.2)+200000)) -> 288320 | P75: =+L75-O75-M75 -> 153280 | Q75: =IF(O75=0,(L75*0.01),IF(P75<=0,0.01*L75,IF(AND(P75>0,P75<=300000),P75*7%,IF(AND(P75>=300000,P75<600000),21000+(P75-300000)*11%,IF(AND(P75>=600000,P75<1100000),54000+(P75-600000)*15%,IF(AND(P75>=1100000,P75<1600000),129000+(P75-1100000)*19%,IF(AND(P75>=1600000,P75<3200000),224000+(P75-1600000)*21%,560000+(P75-3200000)*24%))))))) -> 10729.6 | R75: =Q75/12 -> 894.13333 | S75: =F75 -> 12 | T75: =+R75*S75 -> 10729.6
A76: 72 | B76: Adeleye | C76: Kayode | D76: Daniel | E76: Accessories Manager | F76: 12 | G76: 1020000 | H76: 534400 | I76: 100 | J76: 46784 | L76: =G76 -> 1020000 | M76: =L76*0.08 -> 81600 | N76: =L76-M76 -> 938400 | O76: =IF(N76<=300000,0,IF(N76>=20000000,(N76*0.21),(N76*0.2)+200000)) -> 387680 | P76: =+L76-O76-M76 -> 550720 | Q76: =IF(O76=0,(L76*0.01),IF(P76<=0,0.01*L76,IF(AND(P76>0,P76<=300000),P76*7%,IF(AND(P76>=300000,P76<600000),21000+(P76-300000)*11%,IF(AND(P76>=600000,P76<1100000),54000+(P76-600000)*15%,IF(AND(P76>=1100000,P76<1600000),129000+(P76-1100000)*19%,IF(AND(P76>=1600000,P76<3200000),224000+(P76-1600000)*21%,560000+(P76-3200000)*24%))))))) -> 48579.2 | R76: =Q76/12 -> 4048.2667 | S76: =F76 -> 12 | T76: =+R76*S76 -> 48579.2
A77: 73 | B77: Adeniyi | C77: Adetokunbo | E77: Store Supervisor | F77: 12 | G77: 540000 | H77: 188800 | I77: 100 | J77: 13216 | L77: =G77 -> 540000 | M77: =L77*0.08 -> 43200 | N77: =L77-M77 -> 496800 | O77: =IF(N77<=300000,0,IF(N77>=20000000,(N77*0.21),(N77*0.2)+200000)) -> 299360 | P77: =+L77-O77-M77 -> 197440 | Q77: =IF(O77=0,(L77*0.01),IF(P77<=0,0.01*L77,IF(AND(P77>0,P77<=300000),P77*7%,IF(AND(P77>=300000,P77<600000),21000+(P77-300000)*11%,IF(AND(P77>=600000,P77<1100000),54000+(P77-600000)*15%,IF(AND(P77>=1100000,P77<1600000),129000+(P77-1100000)*19%,IF(AND(P77>=1600000,P77<3200000),224000+(P77-1600000)*21%,560000+(P77-3200000)*24%))))))) -> 13820.8 | R77: =Q77/12 -> 1151.7333 | S77: =F77 -> 12 | T77: =+R77*S77 -> 13820.8
A78: 74 | B78: Adesanya | C78: Oghoho | D78: Happiness | E78: Warehouse Supervisor | F78: 12 | G78: 660000 | H78: 275200 | I78: 100 | J78: 19264 | L78: =G78 -> 660000 | M78: =L78*0.08 -> 52800 | N78: =L78-M78 -> 607200 | O78: =IF(N78<=300000,0,IF(N78>=20000000,(N78*0.21),(N78*0.2)+200000)) -> 321440 | P78: =+L78-O78-M78 -> 285760 | Q78: =IF(O78=0,(L78*0.01),IF(P78<=0,0.01*L78,IF(AND(P78>0,P78<=300000),P78*7%,IF(AND(P78>=300000,P78<600000),21000+(P78-300000)*11%,IF(AND(P78>=600000,P78<1100000),54000+(P78-600000)*15%,IF(AND(P78>=1100000,P78<1600000),129000+(P78-1100000)*19%,IF(AND(P78>=1600000,P78<3200000),224000+(P78-1600000)*21%,560000+(P78-3200000)*24%))))))) -> 20003.2 | R78: =Q78/12 -> 1666.9333 | S78: =F78 -> 12 | T78: =+R78*S78 -> 20003.2
A79: 75 | B79: Adisa | C79: Saheed | D79: Abolore | E79: Driver | F79: 12 | G79: 480000 | H79: 145600 | I79: 100 | J79: 10192 | L79: =G79 -> 480000 | M79: =L79*0.08 -> 38400 | N79: =L79-M79 -> 441600 | O79: =IF(N79<=300000,0,IF(N79>=20000000,(N79*0.21),(N79*0.2)+200000)) -> 288320 | P79: =+L79-O79-M79 -> 153280 | Q79: =IF(O79=0,(L79*0.01),IF(P79<=0,0.01*L79,IF(AND(P79>0,P79<=300000),P79*7%,IF(AND(P79>=300000,P79<600000),21000+(P79-300000)*11%,IF(AND(P79>=600000,P79<1100000),54000+(P79-600000)*15%,IF(AND(P79>=1100000,P79<1600000),129000+(P79-1100000)*19%,IF(AND(P79>=1600000,P79<3200000),224000+(P79-1600000)*21%,560000+(P79-3200000)*24%))))))) -> 10729.6 | R79: =Q79/12 -> 894.13333 | S79: =F79 -> 12 | T79: =+R79*S79 -> 10729.6
A80: 76 | B80: Ajayi | C80: Dolapo | E80: Manager | F80: 12 | G80: 600000 | H80: 232000 | I80: 100 | J80: 16240 | L80: =G80 -> 600000 | M80: =L80*0.08 -> 48000 | N80: =L80-M80 -> 552000 | O80: =IF(N80<=300000,0,IF(N80>=20000000,(N80*0.21),(N80*0.2)+200000)) -> 310400 | P80: =+L80-O80-M80 -> 241600 | Q80: =IF(O80=0,(L80*0.01),IF(P80<=0,0.01*L80,IF(AND(P80>0,P80<=300000),P80*7%,IF(AND(P80>=300000,P80<600000),21000+(P80-300000)*11%,IF(AND(P80>=600000,P80<1100000),54000+(P80-600000)*15%,IF(AND(P80>=1100000,P80<1600000),129000+(P80-1100000)*19%,IF(AND(P80>=1600000,P80<3200000),224000+(P80-1600000)*21%,560000+(P80-3200000)*24%))))))) -> 16912 | R80: =Q80/12 -> 1409.3333 | S80: =F80 -> 12 | T80: =+R80*S80 -> 16912
A81: 77 | B81: Akinyemi | C81: Ibukun | E81: Maintainance | F81: 12 | G81: 420000 | H81: 102400 | I81: 100 | J81: 7168 | L81: =G81 -> 420000 | M81: =L81*0.08 -> 33600 | N81: =L81-M81 -> 386400 | O81: =IF(N81<=300000,0,IF(N81>=20000000,(N81*0.21),(N81*0.2)+200000)) -> 277280 | P81: =+L81-O81-M81 -> 109120 | Q81: =IF(O81=0,(L81*0.01),IF(P81<=0,0.01*L81,IF(AND(P81>0,P81<=300000),P81*7%,IF(AND(P81>=300000,P81<600000),21000+(P81-300000)*11%,IF(AND(P81>=600000,P81<1100000),54000+(P81-600000)*15%,IF(AND(P81>=1100000,P81<1600000),129000+(P81-1100000)*19%,IF(AND(P81>=1600000,P81<3200000),224000+(P81-1600000)*21%,560000+(P81-3200000)*24%))))))) -> 7638.4 | R81: =Q81/12 -> 636.53333 | S81: =F81 -> 12 | T81: =+R81*S81 -> 7638.4
A82: 78 | B82: Alaka | C82: Oluwaseun | D82: Micheal | E82: Manager | F82: 12 | G82: 540000 | H82: 188800 | I82: 100 | J82: 13216 | L82: =G82 -> 540000 | M82: =L82*0.08 -> 43200 | N82: =L82-M82 -> 496800 | O82: =IF(N82<=300000,0,IF(N82>=20000000,(N82*0.21),(N82*0.2)+200000)) -> 299360 | P82: =+L82-O82-M82 -> 197440 | Q82: =IF(O82=0,(L82*0.01),IF(P82<=0,0.01*L82,IF(AND(P82>0,P82<=300000),P82*7%,IF(AND(P82>=300000,P82<600000),21000+(P82-300000)*11%,IF(AND(P82>=600000,P82<1100000),54000+(P82-600000)*15%,IF(AND(P82>=1100000,P82<1600000),129000+(P82-1100000)*19%,IF(AND(P82>=1600000,P82<3200000),224000+(P82-1600000)*21%,560000+(P82-3200000)*24%))))))) -> 13820.8 | R82: =Q82/12 -> 1151.7333 | S82: =F82 -> 12 | T82: =+R82*S82 -> 13820.8
A83: 79 | B83: Alfonso | C83: Oladimeji | E83: Manager | F83: 12 | G83: 540000 | H83: 188800 | I83: 100 | J83: 13216 | L83: =G83 -> 540000 | M83: =L83*0.08 -> 43200 | N83: =L83-M83 -> 496800 | O83: =IF(N83<=300000,0,IF(N83>=20000000,(N83*0.21),(N83*0.2)+200000)) -> 299360 | P83: =+L83-O83-M83 -> 197440 | Q83: =IF(O83=0,(L83*0.01),IF(P83<=0,0.01*L83,IF(AND(P83>0,P83<=300000),P83*7%,IF(AND(P83>=300000,P83<600000),21000+(P83-300000)*11%,IF(AND(P83>=600000,P83<1100000),54000+(P83-600000)*15%,IF(AND(P83>=1100000,P83<1600000),129000+(P83-1100000)*19%,IF(AND(P83>=1600000,P83<3200000),224000+(P83-1600000)*21%,560000+(P83-3200000)*24%))))))) -> 13820.8 | R83: =Q83/12 -> 1151.7333 | S83: =F83 -> 12 | T83: =+R83*S83 -> 13820.8
A84: 80 | B84: Alimi | C84: Olanrewaju | E84: Accessory Officer | F84: 12 | G84: 480000 | H84: 145600 | I84: 100 | J84: 10192 | L84: =G84 -> 480000 | M84: =L84*0.08 -> 38400 | N84: =L84-M84 -> 441600 | O84: =IF(N84<=300000,0,IF(N84>=20000000,(N84*0.21),(N84*0.2)+200000)) -> 288320 | P84: =+L84-O84-M84 -> 153280 | Q84: =IF(O84=0,(L84*0.01),IF(P84<=0,0.01*L84,IF(AND(P84>0,P84<=300000),P84*7%,IF(AND(P84>=300000,P84<600000),21000+(P84-300000)*11%,IF(AND(P84>=600000,P84<1100000),54000+(P84-600000)*15%,IF(AND(P84>=1100000,P84<1600000),129000+(P84-1100000)*19%,IF(AND(P84>=1600000,P84<3200000),224000+(P84-1600000)*21%,560000+(P84-3200000)*24%))))))) -> 10729.6 | R84: =Q84/12 -> 894.13333 | S84: =F84 -> 12 | T84: =+R84*S84 -> 10729.6
A85: 81 | B85: Aliu | C85: Yakub | E85: Maintenance | F85: 12 | G85: 420000 | H85: 102400 | I85: 100 | J85: 7168 | L85: =G85 -> 420000 | M85: =L85*0.08 -> 33600 | N85: =L85-M85 -> 386400 | O85: =IF(N85<=300000,0,IF(N85>=20000000,(N85*0.21),(N85*0.2)+200000)) -> 277280 | P85: =+L85-O85-M85 -> 109120 | Q85: =IF(O85=0,(L85*0.01),IF(P85<=0,0.01*L85,IF(AND(P85>0,P85<=300000),P85*7%,IF(AND(P85>=300000,P85<600000),21000+(P85-300000)*11%,IF(AND(P85>=600000,P85<1100000),54000+(P85-600000)*15%,IF(AND(P85>=1100000,P85<1600000),129000+(P85-1100000)*19%,IF(AND(P85>=1600000,P85<3200000),224000+(P85-1600000)*21%,560000+(P85-3200000)*24%))))))) -> 7638.4 | R85: =Q85/12 -> 636.53333 | S85: =F85 -> 12 | T85: =+R85*S85 -> 7638.4
A86: 82 | B86: Ayang | C86: Mathias | D86: Adomi | E86: Maintaince | F86: 12 | G86: 420000 | H86: 102400 | I86: 100 | J86: 7168 | L86: =G86 -> 420000 | M86: =L86*0.08 -> 33600 | N86: =L86-M86 -> 386400 | O86: =IF(N86<=300000,0,IF(N86>=20000000,(N86*0.21),(N86*0.2)+200000)) -> 277280 | P86: =+L86-O86-M86 -> 109120 | Q86: =IF(O86=0,(L86*0.01),IF(P86<=0,0.01*L86,IF(AND(P86>0,P86<=300000),P86*7%,IF(AND(P86>=300000,P86<600000),21000+(P86-300000)*11%,IF(AND(P86>=600000,P86<1100000),54000+(P86-600000)*15%,IF(AND(P86>=1100000,P86<1600000),129000+(P86-1100000)*19%,IF(AND(P86>=1600000,P86<3200000),224000+(P86-1600000)*21%,560000+(P86-3200000)*24%))))))) -> 7638.4 | R86: =Q86/12 -> 636.53333 | S86: =F86 -> 12 | T86: =+R86*S86 -> 7638.4
A87: 83 | B87: Ayeyo | C87: Oluwasegun | E87: Manager | F87: 12 | G87: 540000 | H87: 188800 | I87: 100 | J87: 13216 | L87: =G87 -> 540000 | M87: =L87*0.08 -> 43200 | N87: =L87-M87 -> 496800 | O87: =IF(N87<=300000,0,IF(N87>=20000000,(N87*0.21),(N87*0.2)+200000)) -> 299360 | P87: =+L87-O87-M87 -> 197440 | Q87: =IF(O87=0,(L87*0.01),IF(P87<=0,0.01*L87,IF(AND(P87>0,P87<=300000),P87*7%,IF(AND(P87>=300000,P87<600000),21000+(P87-300000)*11%,IF(AND(P87>=600000,P87<1100000),54000+(P87-600000)*15%,IF(AND(P87>=1100000,P87<1600000),129000+(P87-1100000)*19%,IF(AND(P87>=1600000,P87<3200000),224000+(P87-1600000)*21%,560000+(P87-3200000)*24%))))))) -> 13820.8 | R87: =Q87/12 -> 1151.7333 | S87: =F87 -> 12 | T87: =+R87*S87 -> 13820.8
A88: 84 | B88: Bonioly | C88: Adetayo | D88: Ayobami | E88: Accessory Assistant | F88: 12 | G88: 600000 | H88: 232000 | I88: 100 | J88: 16240 | L88: =G88 -> 600000 | M88: =L88*0.08 -> 48000 | N88: =L88-M88 -> 552000 | O88: =IF(N88<=300000,0,IF(N88>=20000000,(N88*0.21),(N88*0.2)+200000)) -> 310400 | P88: =+L88-O88-M88 -> 241600 | Q88: =IF(O88=0,(L88*0.01),IF(P88<=0,0.01*L88,IF(AND(P88>0,P88<=300000),P88*7%,IF(AND(P88>=300000,P88<600000),21000+(P88-300000)*11%,IF(AND(P88>=600000,P88<1100000),54000+(P88-600000)*15%,IF(AND(P88>=1100000,P88<1600000),129000+(P88-1100000)*19%,IF(AND(P88>=1600000,P88<3200000),224000+(P88-1600000)*21%,560000+(P88-3200000)*24%))))))) -> 16912 | R88: =Q88/12 -> 1409.3333 | S88: =F88 -> 12 | T88: =+R88*S88 -> 16912
A89: 85 | B89: Chidiebere | C89: Peter | E89: Maintainance | F89: 12 | G89: 420000 | H89: 102400 | I89: 100 | J89: 7168 | L89: =G89 -> 420000 | M89: =L89*0.08 -> 33600 | N89: =L89-M89 -> 386400 | O89: =IF(N89<=300000,0,IF(N89>=20000000,(N89*0.21),(N89*0.2)+200000)) -> 277280 | P89: =+L89-O89-M89 -> 109120 | Q89: =IF(O89=0,(L89*0.01),IF(P89<=0,0.01*L89,IF(AND(P89>0,P89<=300000),P89*7%,IF(AND(P89>=300000,P89<600000),21000+(P89-300000)*11%,IF(AND(P89>=600000,P89<1100000),54000+(P89-600000)*15%,IF(AND(P89>=1100000,P89<1600000),129000+(P89-1100000)*19%,IF(AND(P89>=1600000,P89<3200000),224000+(P89-1600000)*21%,560000+(P89-3200000)*24%))))))) -> 7638.4 | R89: =Q89/12 -> 636.53333 | S89: =F89 -> 12 | T89: =+R89*S89 -> 7638.4
A90: 86 | B90: Dennis | C90: Anna | E90: Electronics FSM | F90: 12 | G90: 420000 | H90: 102400 | I90: 100 | J90: 7168 | L90: =G90 -> 420000 | M90: =L90*0.08 -> 33600 | N90: =L90-M90 -> 386400 | O90: =IF(N90<=300000,0,IF(N90>=20000000,(N90*0.21),(N90*0.2)+200000)) -> 277280 | P90: =+L90-O90-M90 -> 109120 | Q90: =IF(O90=0,(L90*0.01),IF(P90<=0,0.01*L90,IF(AND(P90>0,P90<=300000),P90*7%,IF(AND(P90>=300000,P90<600000),21000+(P90-300000)*11%,IF(AND(P90>=600000,P90<1100000),54000+(P90-600000)*15%,IF(AND(P90>=1100000,P90<1600000),129000+(P90-1100000)*19%,IF(AND(P90>=1600000,P90<3200000),224000+(P90-1600000)*21%,560000+(P90-3200000)*24%))))))) -> 7638.4 | R90: =Q90/12 -> 636.53333 | S90: =F90 -> 12 | T90: =+R90*S90 -> 7638.4
A91: 87 | B91: Edet | C91: Lucky | E91: Decoration officer | F91: 12 | G91: 420000 | H91: 102400 | I91: 100 | J91: 7168 | L91: =G91 -> 420000 | M91: =L91*0.08 -> 33600 | N91: =L91-M91 -> 386400 | O91: =IF(N91<=300000,0,IF(N91>=20000000,(N91*0.21),(N91*0.2)+200000)) -> 277280 | P91: =+L91-O91-M91 -> 109120 | Q91: =IF(O91=0,(L91*0.01),IF(P91<=0,0.01*L91,IF(AND(P91>0,P91<=300000),P91*7%,IF(AND(P91>=300000,P91<600000),21000+(P91-300000)*11%,IF(AND(P91>=600000,P91<1100000),54000+(P91-600000)*15%,IF(AND(P91>=1100000,P91<1600000),129000+(P91-1100000)*19%,IF(AND(P91>=1600000,P91<3200000),224000+(P91-1600000)*21%,560000+(P91-3200000)*24%))))))) -> 7638.4 | R91: =Q91/12 -> 636.53333 | S91: =F91 -> 12 | T91: =+R91*S91 -> 7638.4
A92: 88 | B92: Ehighalua | C92: Blessing | E92: Cashier | F92: 12 | G92: 480000 | H92: 145600 | I92: 100 | J92: 10192 | L92: =G92 -> 480000 | M92: =L92*0.08 -> 38400 | N92: =L92-M92 -> 441600 | O92: =IF(N92<=300000,0,IF(N92>=20000000,(N92*0.21),(N92*0.2)+200000)) -> 288320 | P92: =+L92-O92-M92 -> 153280 | Q92: =IF(O92=0,(L92*0.01),IF(P92<=0,0.01*L92,IF(AND(P92>0,P92<=300000),P92*7%,IF(AND(P92>=300000,P92<600000),21000+(P92-300000)*11%,IF(AND(P92>=600000,P92<1100000),54000+(P92-600000)*15%,IF(AND(P92>=1100000,P92<1600000),129000+(P92-1100000)*19%,IF(AND(P92>=1600000,P92<3200000),224000+(P92-1600000)*21%,560000+(P92-3200000)*24%))))))) -> 10729.6 | R92: =Q92/12 -> 894.13333 | S92: =F92 -> 12 | T92: =+R92*S92 -> 10729.6
A93: 89 | B93: Ejikemenwa | C93: Chinyere | E93: Cashier | F93: 12 | G93: 480000 | H93: 145600 | I93: 100 | J93: 10192 | L93: =G93 -> 480000 | M93: =L93*0.08 -> 38400 | N93: =L93-M93 -> 441600 | O93: =IF(N93<=300000,0,IF(N93>=20000000,(N93*0.21),(N93*0.2)+200000)) -> 288320 | P93: =+L93-O93-M93 -> 153280 | Q93: =IF(O93=0,(L93*0.01),IF(P93<=0,0.01*L93,IF(AND(P93>0,P93<=300000),P93*7%,IF(AND(P93>=300000,P93<600000),21000+(P93-300000)*11%,IF(AND(P93>=600000,P93<1100000),54000+(P93-600000)*15%,IF(AND(P93>=1100000,P93<1600000),129000+(P93-1100000)*19%,IF(AND(P93>=1600000,P93<3200000),224000+(P93-1600000)*21%,560000+(P93-3200000)*24%))))))) -> 10729.6 | R93: =Q93/12 -> 894.13333 | S93: =F93 -> 12 | T93: =+R93*S93 -> 10729.6
A94: 90 | B94: Elimian | C94: Okojie | D94: Omozokpa | E94: Manager | F94: 12 | G94: 540000 | H94: 188800 | I94: 100 | J94: 13216 | L94: =G94 -> 540000 | M94: =L94*0.08 -> 43200 | N94: =L94-M94 -> 496800 | O94: =IF(N94<=300000,0,IF(N94>=20000000,(N94*0.21),(N94*0.2)+200000)) -> 299360 | P94: =+L94-O94-M94 -> 197440 | Q94: =IF(O94=0,(L94*0.01),IF(P94<=0,0.01*L94,IF(AND(P94>0,P94<=300000),P94*7%,IF(AND(P94>=300000,P94<600000),21000+(P94-300000)*11%,IF(AND(P94>=600000,P94<1100000),54000+(P94-600000)*15%,IF(AND(P94>=1100000,P94<1600000),129000+(P94-1100000)*19%,IF(AND(P94>=1600000,P94<3200000),224000+(P94-1600000)*21%,560000+(P94-3200000)*24%))))))) -> 13820.8 | R94: =Q94/12 -> 1151.7333 | S94: =F94 -> 12 | T94: =+R94*S94 -> 13820.8
A95: 91 | B95: Elvis | C95: Uche | D95: Nkwocha | E95: Maintainance | F95: 12 | G95: 420000 | H95: 102400 | I95: 100 | J95: 7168 | L95: =G95 -> 420000 | M95: =L95*0.08 -> 33600 | N95: =L95-M95 -> 386400 | O95: =IF(N95<=300000,0,IF(N95>=20000000,(N95*0.21),(N95*0.2)+200000)) -> 277280 | P95: =+L95-O95-M95 -> 109120 | Q95: =IF(O95=0,(L95*0.01),IF(P95<=0,0.01*L95,IF(AND(P95>0,P95<=300000),P95*7%,IF(AND(P95>=300000,P95<600000),21000+(P95-300000)*11%,IF(AND(P95>=600000,P95<1100000),54000+(P95-600000)*15%,IF(AND(P95>=1100000,P95<1600000),129000+(P95-1100000)*19%,IF(AND(P95>=1600000,P95<3200000),224000+(P95-1600000)*21%,560000+(P95-3200000)*24%))))))) -> 7638.4 | R95: =Q95/12 -> 636.53333 | S95: =F95 -> 12 | T95: =+R95*S95 -> 7638.4
A96: 92 | B96: Emetoh | C96: Chizoba | D96: Genevieve | E96: Cashier | F96: 12 | G96: 480000 | H96: 145600 | I96: 100 | J96: 10192 | L96: =G96 -> 480000 | M96: =L96*0.08 -> 38400 | N96: =L96-M96 -> 441600 | O96: =IF(N96<=300000,0,IF(N96>=20000000,(N96*0.21),(N96*0.2)+200000)) -> 288320 | P96: =+L96-O96-M96 -> 153280 | Q96: =IF(O96=0,(L96*0.01),IF(P96<=0,0.01*L96,IF(AND(P96>0,P96<=300000),P96*7%,IF(AND(P96>=300000,P96<600000),21000+(P96-300000)*11%,IF(AND(P96>=600000,P96<1100000),54000+(P96-600000)*15%,IF(AND(P96>=1100000,P96<1600000),129000+(P96-1100000)*19%,IF(AND(P96>=1600000,P96<3200000),224000+(P96-1600000)*21%,560000+(P96-3200000)*24%))))))) -> 10729.6 | R96: =Q96/12 -> 894.13333 | S96: =F96 -> 12 | T96: =+R96*S96 -> 10729.6
A97: 93 | B97: Evborokhai | C97: Aigboje | D97: Courage | E97: Warehouse Supervisor | F97: 12 | G97: 600000 | H97: 232000 | I97: 100 | J97: 16240 | L97: =G97 -> 600000 | M97: =L97*0.08 -> 48000 | N97: =L97-M97 -> 552000 | O97: =IF(N97<=300000,0,IF(N97>=20000000,(N97*0.21),(N97*0.2)+200000)) -> 310400 | P97: =+L97-O97-M97 -> 241600 | Q97: =IF(O97=0,(L97*0.01),IF(P97<=0,0.01*L97,IF(AND(P97>0,P97<=300000),P97*7%,IF(AND(P97>=300000,P97<600000),21000+(P97-300000)*11%,IF(AND(P97>=600000,P97<1100000),54000+(P97-600000)*15%,IF(AND(P97>=1100000,P97<1600000),129000+(P97-1100000)*19%,IF(AND(P97>=1600000,P97<3200000),224000+(P97-1600000)*21%,560000+(P97-3200000)*24%))))))) -> 16912 | R97: =Q97/12 -> 1409.3333 | S97: =F97 -> 12 | T97: =+R97*S97 -> 16912
A98: 94 | B98: Gbadamosi | C98: Gabriel | E98: Store Supervior | F98: 12 | G98: 540000 | H98: 188800 | I98: 100 | J98: 13216 | L98: =G98 -> 540000 | M98: =L98*0.08 -> 43200 | N98: =L98-M98 -> 496800 | O98: =IF(N98<=300000,0,IF(N98>=20000000,(N98*0.21),(N98*0.2)+200000)) -> 299360 | P98: =+L98-O98-M98 -> 197440 | Q98: =IF(O98=0,(L98*0.01),IF(P98<=0,0.01*L98,IF(AND(P98>0,P98<=300000),P98*7%,IF(AND(P98>=300000,P98<600000),21000+(P98-300000)*11%,IF(AND(P98>=600000,P98<1100000),54000+(P98-600000)*15%,IF(AND(P98>=1100000,P98<1600000),129000+(P98-1100000)*19%,IF(AND(P98>=1600000,P98<3200000),224000+(P98-1600000)*21%,560000+(P98-3200000)*24%))))))) -> 13820.8 | R98: =Q98/12 -> 1151.7333 | S98: =F98 -> 12 | T98: =+R98*S98 -> 13820.8
A99: 95 | B99: Hassan | C99: Isah | E99: Wood worker | F99: 12 | G99: 720000 | H99: 318400 | I99: 100 | J99: 23024 | L99: =G99 -> 720000 | M99: =L99*0.08 -> 57600 | N99: =L99-M99 -> 662400 | O99: =IF(N99<=300000,0,IF(N99>=20000000,(N99*0.21),(N99*0.2)+200000)) -> 332480 | P99: =+L99-O99-M99 -> 329920 | Q99: =IF(O99=0,(L99*0.01),IF(P99<=0,0.01*L99,IF(AND(P99>0,P99<=300000),P99*7%,IF(AND(P99>=300000,P99<600000),21000+(P99-300000)*11%,IF(AND(P99>=600000,P99<1100000),54000+(P99-600000)*15%,IF(AND(P99>=1100000,P99<1600000),129000+(P99-1100000)*19%,IF(AND(P99>=1600000,P99<3200000),224000+(P99-1600000)*21%,560000+(P99-3200000)*24%))))))) -> 24291.2 | R99: =Q99/12 -> 2024.2667 | S99: =F99 -> 12 | T99: =+R99*S99 -> 24291.2
A100: 96 | B100: Henry | C100: Ugbah | E100: Accessories Manager | F100: 12 | G100: 1260000 | H100: 707200 | I100: 100 | J100: 70080 | L100: =G100 -> 1260000 | M100: =L100*0.08 -> 100800 | N100: =L100-M100 -> 1159200 | O100: =IF(N100<=300000,0,IF(N100>=20000000,(N100*0.21),(N100*0.2)+200000)) -> 431840 | P100: =+L100-O100-M100 -> 727360 | Q100: =IF(O100=0,(L100*0.01),IF(P100<=0,0.01*L100,IF(AND(P100>0,P100<=300000),P100*7%,IF(AND(P100>=300000,P100<600000),21000+(P100-300000)*11%,IF(AND(P100>=600000,P100<1100000),54000+(P100-600000)*15%,IF(AND(P100>=1100000,P100<1600000),129000+(P100-1100000)*19%,IF(AND(P100>=1600000,P100<3200000),224000+(P100-1600000)*21%,560000+(P100-3200000)*24%))))))) -> 73104 | R100: =Q100/12 -> 6092 | S100: =F100 -> 12 | T100: =+R100*S100 -> 73104
A101: 97 | B101: Ifionu | C101: Louisa | D101: Blessing | E101: FSM | F101: 12 | G101: 420000 | H101: 102400 | I101: 100 | J101: 7168 | L101: =G101 -> 420000 | M101: =L101*0.08 -> 33600 | N101: =L101-M101 -> 386400 | O101: =IF(N101<=300000,0,IF(N101>=20000000,(N101*0.21),(N101*0.2)+200000)) -> 277280 | P101: =+L101-O101-M101 -> 109120 | Q101: =IF(O101=0,(L101*0.01),IF(P101<=0,0.01*L101,IF(AND(P101>0,P101<=300000),P101*7%,IF(AND(P101>=300000,P101<600000),21000+(P101-300000)*11%,IF(AND(P101>=600000,P101<1100000),54000+(P101-600000)*15%,IF(AND(P101>=1100000,P101<1600000),129000+(P101-1100000)*19%,IF(AND(P101>=1600000,P101<3200000),224000+(P101-1600000)*21%,560000+(P101-3200000)*24%))))))) -> 7638.4 | R101: =Q101/12 -> 636.53333 | S101: =F101 -> 12 | T101: =+R101*S101 -> 7638.4
...

Sheet expat 2023
A1: 3C HUB BRAND MANAGEMENT LIMITED 2023
A2: LIST | B2: NAME-ENGLISH | C2: NATIONALITY | D2: POSITION IN THE COMPANY | F2: MTH | G2: ANNUAL TOTAL GROSS INCOME + BIK | H2: CRA | I2: TAXABLE INCOME | J2: ANNUAL TAX-YEARLY | K2: MONTHLY TAX | L2: ANNUAL TOTAL GROSS INCOME + BIK | M2: CRA | N2: TAXABLE INCOME | O2: ANNUAL TAX | P2: MONTHLY TAX | Q2: MNTH | R2: PRO BY MNTH
A3: 1 | B3: DONGQIN LIU | C3: CHINESE | D3: Quality Control Analyst | F3: 12 | G3: 25000000 | H3: 1400000 | I3: 4600000 | J3: 896000 | K3: 74666.67 | L3: 8000000 | M3: =IF(L3<=300000,0,IF(L3>=20000000,(L3*0.21),(L3*0.2)+200000)) -> 1800000 | N3: =+L3-M3 -> 6200000 | O3: =IF(M3=0,(L3*0.01),IF(N3<=0,0.01*L3,IF(AND(N3>0,N3<=300000),N3*7%,IF(AND(N3>=300000,N3<600000),21000+(N3-300000)*11%,IF(AND(N3>=600000,N3<1100000),54000+(N3-600000)*15%,IF(AND(N3>=1100000,N3<1600000),129000+(N3-1100000)*19%,IF(AND(N3>=1600000,N3<3200000),224000+(N3-1600000)*21%,560000+(N3-3200000)*24%))))))) -> 1280000 | P3: =O3/12 -> 106666.67 | Q3: =F3 -> 12 | R3: =+P3*Q3 -> 1280000
A4: 2 | B4: CAI GENG | C4: CHINESE | D4: Information Technologist | F4: 12 | G4: 10000000 | H4: 1400000 | I4: 4600000 | J4: 896000 | K4: 74666.67 | L4: 7000000 | M4: =IF(L4<=300000,0,IF(L4>=20000000,(L4*0.21),(L4*0.2)+200000)) -> 1600000 | N4: =+L4-M4 -> 5400000 | O4: =IF(M4=0,(L4*0.01),IF(N4<=0,0.01*L4,IF(AND(N4>0,N4<=300000),N4*7%,IF(AND(N4>=300000,N4<600000),21000+(N4-300000)*11%,IF(AND(N4>=600000,N4<1100000),54000+(N4-600000)*15%,IF(AND(N4>=1100000,N4<1600000),129000+(N4-1100000)*19%,IF(AND(N4>=1600000,N4<3200000),224000+(N4-1600000)*21%,560000+(N4-3200000)*24%))))))) -> 1088000 | P4: =O4/12 -> 90666.667 | Q4: =F4 -> 12 | R4: =+P4*Q4 -> 1088000
A5: 3 | B5: WANG HAO | C5: CHINESE | D5: Quality Control Analyst | F5: 12 | G5: 10000000 | H5: 1400000 | I5: 4600000 | J5: 896000 | K5: 74666.67 | L5: 7000000 | M5: =IF(L5<=300000,0,IF(L5>=20000000,(L5*0.21),(L5*0.2)+200000)) -> 1600000 | N5: =+L5-M5 -> 5400000 | O5: =IF(M5=0,(L5*0.01),IF(N5<=0,0.01*L5,IF(AND(N5>0,N5<=300000),N5*7%,IF(AND(N5>=300000,N5<600000),21000+(N5-300000)*11%,IF(AND(N5>=600000,N5<1100000),54000+(N5-600000)*15%,IF(AND(N5>=1100000,N5<1600000),129000+(N5-1100000)*19%,IF(AND(N5>=1600000,N5<3200000),224000+(N5-1600000)*21%,560000+(N5-3200000)*24%))))))) -> 1088000 | P5: =O5/12 -> 90666.667 | Q5: =F5 -> 12 | R5: =+P5*Q5 -> 1088000
A6: 4 | B6: KUANG TAO | C6: CHINESE | D6: Quality Control Analyst | F6: 12 | G6: 10000000 | H6: 1400000 | I6: 4600000 | J6: 896000 | K6: 74666.67 | L6: 7000000 | M6: =IF(L6<=300000,0,IF(L6>=20000000,(L6*0.21),(L6*0.2)+200000)) -> 1600000 | N6: =+L6-M6 -> 5400000 | O6: =IF(M6=0,(L6*0.01),IF(N6<=0,0.01*L6,IF(AND(N6>0,N6<=300000),N6*7%,IF(AND(N6>=300000,N6<600000),21000+(N6-300000)*11%,IF(AND(N6>=600000,N6<1100000),54000+(N6-600000)*15%,IF(AND(N6>=1100000,N6<1600000),129000+(N6-1100000)*19%,IF(AND(N6>=1600000,N6<3200000),224000+(N6-1600000)*21%,560000+(N6-3200000)*24%))))))) -> 1088000 | P6: =O6/12 -> 90666.667 | Q6: =F6 -> 12 | R6: =+P6*Q6 -> 1088000
A7: 5 | B7: YUNHUA HAN | C7: CHINESE | D7: Brand Dev. Manager | F7: 12 | G7: 10000000 | H7: 1400000 | I7: 4600000 | J7: 896000 | K7: 74666.67 | L7: 7000000 | M7: =IF(L7<=300000,0,IF(L7>=20000000,(L7*0.21),(L7*0.2)+200000)) -> 1600000 | N7: =+L7-M7 -> 5400000 | O7: =IF(M7=0,(L7*0.01),IF(N7<=0,0.01*L7,IF(AND(N7>0,N7<=300000),N7*7%,IF(AND(N7>=300000,N7<600000),21000+(N7-300000)*11%,IF(AND(N7>=600000,N7<1100000),54000+(N7-600000)*15%,IF(AND(N7>=1100000,N7<1600000),129000+(N7-1100000)*19%,IF(AND(N7>=1600000,N7<3200000),224000+(N7-1600000)*21%,560000+(N7-3200000)*24%))))))) -> 1088000 | P7: =O7/12 -> 90666.667 | Q7: =F7 -> 12 | R7: =+P7*Q7 -> 1088000
G8: =SUM(G3:G7) -> 65000000 | H8: =SUM(H3:H7) -> 7000000 | I8: =SUM(I3:I7) -> 23000000 | J8: =SUM(J3:J7) -> 4480000 | K8: =SUM(K3:K7) -> 373333.35 | L8: =SUM(L3:L7) -> 36000000 | M8: =SUM(M3:M7) -> 8200000 | N8: =SUM(N3:N7) -> 27800000 | ... P8: =SUM(P3:P7) -> 469333.33 | R8: =SUM(R3:R7) -> 5632000

Sheet expat 2024 
A1: 3C HUB BRAND MANAGEMENT LIMITED 2024 JANUARY TO JUNE
A2: LIST | B2: NAME-ENGLISH | C2: NATIONALITY | D2: POSITION IN THE COMPANY | E2: ANNUAL TOTAL GROSS INCOME + BIK | F2: MTH | G2: CRA | H2: TAXABLE INCOME | I2: ANNUAL TAX-YEARLY | J2: MONTHLY TAX | K2: ANNUAL TOTAL GROSS INCOME + BIK | L2: CRA | M2: TAXABLE INCOME | N2: ANNUAL TAX | O2: MONTHLY TAX | P2: MNTH | Q2: PRO BY MNTH
A3: 1 | B3: DONGQIN LIU | C3: CHINESE | D3: Quality Control Analyst | F3: 12 | G3: 1400000 | H3: 4600000 | I3: 896000 | J3: 74666.67 | K3: 9000000 | L3: =IF(K3<=300000,0,IF(K3>=20000000,(K3*0.21),(K3*0.2)+200000)) -> 2000000 | M3: =+K3-L3 -> 7000000 | N3: =IF(L3=0,(K3*0.01),IF(M3<=0,0.01*K3,IF(AND(M3>0,M3<=300000),M3*7%,IF(AND(M3>=300000,M3<600000),21000+(M3-300000)*11%,IF(AND(M3>=600000,M3<1100000),54000+(M3-600000)*15%,IF(AND(M3>=1100000,M3<1600000),129000+(M3-1100000)*19%,IF(AND(M3>=1600000,M3<3200000),224000+(M3-1600000)*21%,560000+(M3-3200000)*24%))))))) -> 1472000 | O3: =N3/12 -> 122666.67 | P3: =F3 -> 12 | Q3: =+O3*P3 -> 1472000
A4: 2 | B4: CAI GENG | C4: CHINESE | D4: Information Technologist | F4: 12 | G4: 1400000 | H4: 4600000 | I4: 896000 | J4: 74666.67 | K4: 7500000 | L4: =IF(K4<=300000,0,IF(K4>=20000000,(K4*0.21),(K4*0.2)+200000)) -> 1700000 | M4: =+K4-L4 -> 5800000 | N4: =IF(L4=0,(K4*0.01),IF(M4<=0,0.01*K4,IF(AND(M4>0,M4<=300000),M4*7%,IF(AND(M4>=300000,M4<600000),21000+(M4-300000)*11%,IF(AND(M4>=600000,M4<1100000),54000+(M4-600000)*15%,IF(AND(M4>=1100000,M4<1600000),129000+(M4-1100000)*19%,IF(AND(M4>=1600000,M4<3200000),224000+(M4-1600000)*21%,560000+(M4-3200000)*24%))))))) -> 1184000 | O4: =N4/12 -> 98666.667 | P4: =F4 -> 12 | Q4: =+O4*P4 -> 1184000
A5: 3 | B5: WANG HAO | C5: CHINESE | D5: Quality Control Analyst | F5: 12 | G5: 1400000 | H5: 4600000 | I5: 896000 | J5: 74666.67 | K5: 7500000 | L5: =IF(K5<=300000,0,IF(K5>=20000000,(K5*0.21),(K5*0.2)+200000)) -> 1700000 | M5: =+K5-L5 -> 5800000 | N5: =IF(L5=0,(K5*0.01),IF(M5<=0,0.01*K5,IF(AND(M5>0,M5<=300000),M5*7%,IF(AND(M5>=300000,M5<600000),21000+(M5-300000)*11%,IF(AND(M5>=600000,M5<1100000),54000+(M5-600000)*15%,IF(AND(M5>=1100000,M5<1600000),129000+(M5-1100000)*19%,IF(AND(M5>=1600000,M5<3200000),224000+(M5-1600000)*21%,560000+(M5-3200000)*24%))))))) -> 1184000 | O5: =N5/12 -> 98666.667 | P5: =F5 -> 12 | Q5: =+O5*P5 -> 1184000
A6: 4 | B6: KUANG TAO | C6: CHINESE | D6: Quality Control Analyst | F6: 12 | G6: 1400000 | H6: 4600000 | I6: 896000 | J6: 74666.67 | K6: 7500000 | L6: =IF(K6<=300000,0,IF(K6>=20000000,(K6*0.21),(K6*0.2)+200000)) -> 1700000 | M6: =+K6-L6 -> 5800000 | N6: =IF(L6=0,(K6*0.01),IF(M6<=0,0.01*K6,IF(AND(M6>0,M6<=300000),M6*7%,IF(AND(M6>=300000,M6<600000),21000+(M6-300000)*11%,IF(AND(M6>=600000,M6<1100000),54000+(M6-600000)*15%,IF(AND(M6>=1100000,M6<1600000),129000+(M6-1100000)*19%,IF(AND(M6>=1600000,M6<3200000),224000+(M6-1600000)*21%,560000+(M6-3200000)*24%))))))) -> 1184000 | O6: =N6/12 -> 98666.667 | P6: =F6 -> 12 | Q6: =+O6*P6 -> 1184000
A7: 5 | B7: YUNHUA HAN | C7: CHINESE | D7: Brand Dev. Manager | F7: 12 | G7: 1400000 | H7: 4600000 | I7: 896000 | J7: 74666.67 | K7: 7500000 | L7: =IF(K7<=300000,0,IF(K7>=20000000,(K7*0.21),(K7*0.2)+200000)) -> 1700000 | M7: =+K7-L7 -> 5800000 | N7: =IF(L7=0,(K7*0.01),IF(M7<=0,0.01*K7,IF(AND(M7>0,M7<=300000),M7*7%,IF(AND(M7>=300000,M7<600000),21000+(M7-300000)*11%,IF(AND(M7>=600000,M7<1100000),54000+(M7-600000)*15%,IF(AND(M7>=1100000,M7<1600000),129000+(M7-1100000)*19%,IF(AND(M7>=1600000,M7<3200000),224000+(M7-1600000)*21%,560000+(M7-3200000)*24%))))))) -> 1184000 | O7: =N7/12 -> 98666.667 | P7: =F7 -> 12 | Q7: =+O7*P7 -> 1184000
E8: =SUM(E3:E7) -> 0 | G8: =SUM(G3:G7) -> 7000000 | H8: =SUM(H3:H7) -> 23000000 | I8: =SUM(I3:I7) -> 4480000 | J8: =SUM(J3:J7) -> 373333.35 | Q8: =SUM(Q3:Q7) -> 6208000

Sheet SCHEDULE OF PAYMENT (2)
A1: APPENDIX 3 | C1: LAGOS STATE INTERNAL REVENUE SERVICE
C2: 2023
A3: COMPANY NAME: | C3: 3C HUB BRAND MANAGEMENT LIMITED
A4: COMPANY ID (CID) : | C4: C-1717563
A5: COMPANY ADDRESS : | C5: 20 AWOLOWO WAY,IKEJA LAGOS
B8: SCHEDULE OF PAYMENT FOR LOCAL AND EXPATRIATE 2023
A9: SN | B9: DATE OF PAYMENT | C9: AMOUNT | D9: PERIOD OF | E9: RECEIPT | F9: COMPANY ID (CID)
C10: PAID EXPATRIATE /LOCAL | D10: PAYMENT | E10: NUMBER
A11: 1 | B11: MARCH 22,2023 | C11: 580200 | D11: JANUARY ,2023 | E11: 51239606/TNMGNVUP | F11: C-1717563
A12: =A11+1 -> 2 | B12: MARCH 22,2023 | C12: 585800 | D12: FEBRUARY,2023 | E12: 51239599/NRHPNMWI | F12: C-1717563
A13: =A12+1 -> 3 | B13: MAY,2023 | C13: 587400 | D13: MARCH,2023 | E13: 51720496/XJYHLULI | F13: C-1717563
A14: =A13+1 -> 4 | B14: MAY,2023 | C14: 572300 | D14: APRIL, 2023 | E14: 51720513/ANLATDFY | F14: C-1717563
A15: =A14+1 -> 5 | B15: JUNE,2023 | C15: 577100 | D15: MAY,2023 | E15: 51941341/MVWHPLHW | F15: C-1717563
A16: =A15+1 -> 6 | B16: JULY,2023 | C16: 574500 | D16: JUNE,2023 | E16: 52216957/JUKYUZUR | F16: C-1717563
A17: =A16+1 -> 7 | B17: AUGUST,2023 | C17: 577400 | D17: JULY,2023 | E17: 52521244/ZDKBGECC | F17: C-1717563
A18: =A17+1 -> 8 | B18: SEPTEMBER,2023 | C18: 581500 | D18: AUGUST,2023 | E18: 52769775/CRIXGYDV | F18: C-1717563
A19: =A18+1 -> 9 | B19: OCTOBER,2023 | C19: 569500 | D19: SEPTEMBER,2023 | E19: 53106832/KEPNJGDD | F19: C-1717563
A20: =A19+1 -> 10 | B20: NOVEMBER,2023 | C20: 563593 | D20: OCTOBER,2023 | E20: 53433029/RZNAWYNZ | F20: C-1717563
A21: =A20+1 -> 11 | B21: DECEMBER,2023 | C21: 562902 | D21: NOVEMBER,2023 | E21: 53819864/QJWRMQDS | F21: C-1717563
A22: =A21+1 -> 12 | B22: JANUARY,2023 | C22: 562902 | D22: DECEMBER,2023 | E22: 54023592/JAEJRYRT | F22: C-1717563
C23: =SUM(C11:C22) -> 6895097

Sheet 2024
A1: APPENDIX 3 | C1: LAGOS STATE INTERNAL REVENUE SERVICE
C2: 2024
A3: COMPANY NAME: | C3: 3C HUB BRAND MANAGEMENT LIMITED
A4: COMPANY ID (CID) : | C4: C-1717563
A5: COMPANY ADDRESS : | C5: 20 AWOLOWO WAY,IKEJA LAGOS
C7: SCHEDULE OF RETURNS
B8: SCHEDULE OF PAYMENT
A9: SN | B9: DATE OF PAYMENT | C9: AMOUNT | D9: AMOUNT | E9: PERIOD OF | F9: RECEIPT | G9: COMPANY ID (CID)
C10: PAID FOR LOCAL | D10: PAID FOR EXPARTRIATE | E10: PAYMENT | F10: NUMBER
A11: 1 | B11: FEBRUARY ,2024 | C11: 545253.33 | E11: JANUARY ,2024 | F11: 54409365/YKZAJTJN | G11: C-1717563
A12: =A11+1 -> 2 | B12: MARCH ,2024 | C12: 545253.35 | E12: FEBRUARY,2024 | F12: 54725500/AYSWDGBU | G12: C-1717563
A13: =A12+1 -> 3 | B13: APRIL ,2024 | C13: 546102.66 | E13: MARCH,2024 | F13: 54947689/USELDNTH | G13: C-1717563
A14: =A13+1 -> 4 | B14: MAY,2024 | D14: 373334 | E14: APRIL, 2024 | F14: 55304711/NDPQTKZV | G14: C-1717563
A15: =A14+1 -> 5 | B15: MAY,2024 | C15: 170222 | E15: APRIL,2024 | F15: 55304724/KTLPDQII | G15: C-1717563
A16: =A15+1 -> 6 | B16: JUNE,2024 | D16: 373400 | E16: MAY,2024 | F16: 55567104/KLHJCIWD | G16: C-1717563
A17: =A16+1 -> 7 | B17: JUNE,2024 | C17: 170300 | E17: MAY,2024 | F17: 55567069/AGMGFMUR | G17: C-1717563
A18: =A17+1 -> 8 | B18: JULY,2024 | C18: 171071 | E18: JUNE,2024 | F18: 55886106/ZANJHMKW | G18: C-1717563
A19: =A18+1 -> 9 | B19: JULY,2024 | D19: 373333 | E19: JUNE,2024 | F19: 55886071/UPXLBSPJ | G19: C-1717563
A20: 10 | B20: AUGUST,2024 | C20: 170000 | E20: JULY,2024 | F20: 56037877/GYCFMTHE | G20: C-1717563
A21: 11 | B21: AUGUST,2024 | D21: 374000 | E21: JULY,2024 | F21: 56037872/DAPZDPXC | G21: C-1717563
A22: 12 | B22: SEPTEMBER,2024 | C22: 166863 | E22: AUGUST,2024 | F22: 56151305/TAKKZCQP | G22: C-1717563
A23: 13 | B23: SEPTEMBER,2024 | D23: 373334 | E23: AUGUST,2024 | F23: 56151308/PZGQJHGB | G23: C-1717563
A24: 14 | B24: OCTOBER,2024 | C24: 159108 | E24: SEPTEMBER,2024 | F24: 56593668/DPTVPGYG | G24: C-1717563
A25: 15 | B25: OCTOBER,2024 | D25: 373334 | E25: SEPTEMBER,2024 | F25: 56593697/PUNQPACA | G25: C-1717563
A26: 16 | B26: NOVEMBER,2024 | D26: 373334 | E26: OCTOBER,2024 | F26: 56894696/RDRSJEUP | G26: C-1717563
A27: 17 | B27: NOVEMBER,2024 | C27: 159677 | E27: OCTOBER,2024 | F27: 56894697/ATFALKRE | G27: C-1717563
A28: 18 | B28: JANUARY ,2025 | C28: 154630 | E28: NOVEMBER,2024 | F28: 57374232/DLFRLXMD | G28: C-1717563
A29: 19 | B29: JANUARY ,2025 | D29: 373334 | E29: NOVEMBER,2024 | F29: 57374086/MREIKEAN | G29: C-1717563
A30: 20 | B30: JANUARY ,2025 | C30: 154630 | E30: DECEMBER,2024 | F30: 57374082/DXTKHMGP | G30: C-1717563
A31: 21 | B31: JANUARY ,2025 | D31: 373334 | E31: DECEMBER,2024 | F31: 57374234/LUTNFFDC | G31: C-1717563
D32: 280000
C33: =SUM(C11:C32) -> 3113110.3 | D33: =SUM(D11:D32) -> 3640737 | E33: =C33+D33 -> 6753847.3
